Classfile jar:file:///app/libs/minecolonies-1.20.1-1.1.1133-snapshot.jar!/com/minecolonies/api/equipment/ModEquipmentTypes.class
  Last modified Nov 30, 2025; size 15844 bytes
  SHA-256 checksum 2ca4361392592b2283937868194f716f033b1b59d9eff165d3d6784bfc58d208
  Compiled from "ModEquipmentTypes.java"
public class com.minecolonies.api.equipment.ModEquipmentTypes
  minor version: 0
  major version: 61
  flags: (0x0021) ACC_PUBLIC, ACC_SUPER
  this_class: #2                          // com/minecolonies/api/equipment/ModEquipmentTypes
  super_class: #4                         // java/lang/Object
  interfaces: 0, fields: 17, methods: 51, attributes: 3
Constant pool:
    #1 = Utf8               com/minecolonies/api/equipment/ModEquipmentTypes
    #2 = Class              #1            // com/minecolonies/api/equipment/ModEquipmentTypes
    #3 = Utf8               java/lang/Object
    #4 = Class              #3            // java/lang/Object
    #5 = Utf8               ModEquipmentTypes.java
    #6 = Utf8               com/minecolonies/api/equipment/registry/EquipmentTypeEntry$Builder
    #7 = Class              #6            // com/minecolonies/api/equipment/registry/EquipmentTypeEntry$Builder
    #8 = Utf8               com/minecolonies/api/equipment/registry/EquipmentTypeEntry
    #9 = Class              #8            // com/minecolonies/api/equipment/registry/EquipmentTypeEntry
   #10 = Utf8               Builder
   #11 = Utf8               java/lang/invoke/MethodHandles$Lookup
   #12 = Class              #11           // java/lang/invoke/MethodHandles$Lookup
   #13 = Utf8               java/lang/invoke/MethodHandles
   #14 = Class              #13           // java/lang/invoke/MethodHandles
   #15 = Utf8               Lookup
   #16 = Utf8               DEFERRED_REGISTER
   #17 = Utf8               Lnet/minecraftforge/registries/DeferredRegister;
   #18 = Utf8               Lnet/minecraftforge/registries/DeferredRegister<Lcom/minecolonies/api/equipment/registry/EquipmentTypeEntry;>;
   #19 = Utf8               none
   #20 = Utf8               Lnet/minecraftforge/registries/RegistryObject;
   #21 = Utf8               Lnet/minecraftforge/registries/RegistryObject<Lcom/minecolonies/api/equipment/registry/EquipmentTypeEntry;>;
   #22 = Utf8               pickaxe
   #23 = Utf8               shovel
   #24 = Utf8               axe
   #25 = Utf8               hoe
   #26 = Utf8               sword
   #27 = Utf8               bow
   #28 = Utf8               fishing_rod
   #29 = Utf8               shears
   #30 = Utf8               shield
   #31 = Utf8               helmet
   #32 = Utf8               leggings
   #33 = Utf8               chestplate
   #34 = Utf8               boots
   #35 = Utf8               flint_and_steel
   #36 = Utf8               lead
   #37 = Utf8               <init>
   #38 = Utf8               ()V
   #39 = NameAndType        #37:#38       // "<init>":()V
   #40 = Methodref          #4.#39        // java/lang/Object."<init>":()V
   #41 = Utf8               this
   #42 = Utf8               Lcom/minecolonies/api/equipment/ModEquipmentTypes;
   #43 = Utf8               getRegistry
   #44 = Utf8               ()Lnet/minecraftforge/registries/IForgeRegistry;
   #45 = Utf8               ()Lnet/minecraftforge/registries/IForgeRegistry<Lcom/minecolonies/api/equipment/registry/EquipmentTypeEntry;>;
   #46 = Utf8               com/minecolonies/api/IMinecoloniesAPI
   #47 = Class              #46           // com/minecolonies/api/IMinecoloniesAPI
   #48 = Utf8               getInstance
   #49 = Utf8               ()Lcom/minecolonies/api/IMinecoloniesAPI;
   #50 = NameAndType        #48:#49       // getInstance:()Lcom/minecolonies/api/IMinecoloniesAPI;
   #51 = InterfaceMethodref #47.#50       // com/minecolonies/api/IMinecoloniesAPI.getInstance:()Lcom/minecolonies/api/IMinecoloniesAPI;
   #52 = Utf8               getEquipmentTypeRegistry
   #53 = NameAndType        #52:#44       // getEquipmentTypeRegistry:()Lnet/minecraftforge/registries/IForgeRegistry;
   #54 = InterfaceMethodref #47.#53       // com/minecolonies/api/IMinecoloniesAPI.getEquipmentTypeRegistry:()Lnet/minecraftforge/registries/IForgeRegistry;
   #55 = Utf8               register
   #56 = Utf8               (Ljava/lang/String;Ljava/util/function/Consumer;)Lnet/minecraftforge/registries/RegistryObject;
   #57 = Utf8               (Ljava/lang/String;Ljava/util/function/Consumer<Lcom/minecolonies/api/equipment/registry/EquipmentTypeEntry$Builder;>;)Lnet/minecraftforge/registries/RegistryObject<Lcom/minecolonies/api/equipment/registry/EquipmentTypeEntry;>;
   #58 = Methodref          #7.#39        // com/minecolonies/api/equipment/registry/EquipmentTypeEntry$Builder."<init>":()V
   #59 = Utf8               net/minecraft/resources/ResourceLocation
   #60 = Class              #59           // net/minecraft/resources/ResourceLocation
   #61 = Utf8               minecolonies
   #62 = String             #61           // minecolonies
   #63 = Utf8               (Ljava/lang/String;Ljava/lang/String;)V
   #64 = NameAndType        #37:#63       // "<init>":(Ljava/lang/String;Ljava/lang/String;)V
   #65 = Methodref          #60.#64       // net/minecraft/resources/ResourceLocation."<init>":(Ljava/lang/String;Ljava/lang/String;)V
   #66 = Utf8               setRegistryName
   #67 = Utf8               (Lnet/minecraft/resources/ResourceLocation;)Lcom/minecolonies/api/equipment/registry/EquipmentTypeEntry$Builder;
   #68 = NameAndType        #66:#67       // setRegistryName:(Lnet/minecraft/resources/ResourceLocation;)Lcom/minecolonies/api/equipment/registry/EquipmentTypeEntry$Builder;
   #69 = Methodref          #7.#68        // com/minecolonies/api/equipment/registry/EquipmentTypeEntry$Builder.setRegistryName:(Lnet/minecraft/resources/ResourceLocation;)Lcom/minecolonies/api/equipment/registry/EquipmentTypeEntry$Builder;
   #70 = Utf8               java/util/function/Consumer
   #71 = Class              #70           // java/util/function/Consumer
   #72 = Utf8               accept
   #73 = Utf8               (Ljava/lang/Object;)V
   #74 = NameAndType        #72:#73       // accept:(Ljava/lang/Object;)V
   #75 = InterfaceMethodref #71.#74       // java/util/function/Consumer.accept:(Ljava/lang/Object;)V
   #76 = NameAndType        #16:#17       // DEFERRED_REGISTER:Lnet/minecraftforge/registries/DeferredRegister;
   #77 = Fieldref           #2.#76        // com/minecolonies/api/equipment/ModEquipmentTypes.DEFERRED_REGISTER:Lnet/minecraftforge/registries/DeferredRegister;
   #78 = Utf8               java/util/Objects
   #79 = Class              #78           // java/util/Objects
   #80 = Utf8               requireNonNull
   #81 = Utf8               (Ljava/lang/Object;)Ljava/lang/Object;
   #82 = NameAndType        #80:#81       // requireNonNull:(Ljava/lang/Object;)Ljava/lang/Object;
   #83 = Methodref          #79.#82       // java/util/Objects.requireNonNull:(Ljava/lang/Object;)Ljava/lang/Object;
   #84 = Utf8               ()Ljava/lang/Object;
   #85 = MethodType         #84           //  ()Ljava/lang/Object;
   #86 = Utf8               build
   #87 = Utf8               ()Lcom/minecolonies/api/equipment/registry/EquipmentTypeEntry;
   #88 = NameAndType        #86:#87       // build:()Lcom/minecolonies/api/equipment/registry/EquipmentTypeEntry;
   #89 = Methodref          #7.#88        // com/minecolonies/api/equipment/registry/EquipmentTypeEntry$Builder.build:()Lcom/minecolonies/api/equipment/registry/EquipmentTypeEntry;
   #90 = MethodHandle       5:#89         // REF_invokeVirtual com/minecolonies/api/equipment/registry/EquipmentTypeEntry$Builder.build:()Lcom/minecolonies/api/equipment/registry/EquipmentTypeEntry;
   #91 = MethodType         #87           //  ()Lcom/minecolonies/api/equipment/registry/EquipmentTypeEntry;
   #92 = Utf8               java/lang/invoke/LambdaMetafactory
   #93 = Class              #92           // java/lang/invoke/LambdaMetafactory
   #94 = Utf8               metafactory
   #95 = Utf8               (Ljava/lang/invoke/MethodHandles$Lookup;Ljava/lang/String;Ljava/lang/invoke/MethodType;Ljava/lang/invoke/MethodType;Ljava/lang/invoke/MethodHandle;Ljava/lang/invoke/MethodType;)Ljava/lang/invoke/CallSite;
   #96 = NameAndType        #94:#95       // metafactory:(Ljava/lang/invoke/MethodHandles$Lookup;Ljava/lang/String;Ljava/lang/invoke/MethodType;Ljava/lang/invoke/MethodType;Ljava/lang/invoke/MethodHandle;Ljava/lang/invoke/MethodType;)Ljava/lang/invoke/CallSite;
   #97 = Methodref          #93.#96       // java/lang/invoke/LambdaMetafactory.metafactory:(Ljava/lang/invoke/MethodHandles$Lookup;Ljava/lang/String;Ljava/lang/invoke/MethodType;Ljava/lang/invoke/MethodType;Ljava/lang/invoke/MethodHandle;Ljava/lang/invoke/MethodType;)Ljava/lang/invoke/CallSite;
   #98 = MethodHandle       6:#97         // REF_invokeStatic java/lang/invoke/LambdaMetafactory.metafactory:(Ljava/lang/invoke/MethodHandles$Lookup;Ljava/lang/String;Ljava/lang/invoke/MethodType;Ljava/lang/invoke/MethodType;Ljava/lang/invoke/MethodHandle;Ljava/lang/invoke/MethodType;)Ljava/lang/invoke/CallSite;
   #99 = Utf8               get
  #100 = Utf8               (Lcom/minecolonies/api/equipment/registry/EquipmentTypeEntry$Builder;)Ljava/util/function/Supplier;
  #101 = NameAndType        #99:#100      // get:(Lcom/minecolonies/api/equipment/registry/EquipmentTypeEntry$Builder;)Ljava/util/function/Supplier;
  #102 = InvokeDynamic      #0:#101       // #0:get:(Lcom/minecolonies/api/equipment/registry/EquipmentTypeEntry$Builder;)Ljava/util/function/Supplier;
  #103 = Utf8               net/minecraftforge/registries/DeferredRegister
  #104 = Class              #103          // net/minecraftforge/registries/DeferredRegister
  #105 = Utf8               (Ljava/lang/String;Ljava/util/function/Supplier;)Lnet/minecraftforge/registries/RegistryObject;
  #106 = NameAndType        #55:#105      // register:(Ljava/lang/String;Ljava/util/function/Supplier;)Lnet/minecraftforge/registries/RegistryObject;
  #107 = Methodref          #104.#106     // net/minecraftforge/registries/DeferredRegister.register:(Ljava/lang/String;Ljava/util/function/Supplier;)Lnet/minecraftforge/registries/RegistryObject;
  #108 = Utf8               id
  #109 = Utf8               Ljava/lang/String;
  #110 = Utf8               consumer
  #111 = Utf8               Ljava/util/function/Consumer<Lcom/minecolonies/api/equipment/registry/EquipmentTypeEntry$Builder;>;
  #112 = Utf8               Ljava/util/function/Consumer;
  #113 = Utf8               equipmentType
  #114 = Utf8               Lcom/minecolonies/api/equipment/registry/EquipmentTypeEntry$Builder;
  #115 = Utf8               vanillaToolLevel
  #116 = Utf8               (Lnet/minecraft/world/item/ItemStack;Lcom/minecolonies/api/equipment/registry/EquipmentTypeEntry;)I
  #117 = Utf8               com/minecolonies/api/compatibility/Compatibility
  #118 = Class              #117          // com/minecolonies/api/compatibility/Compatibility
  #119 = Utf8               isTinkersTool
  #120 = Utf8               (Lnet/minecraft/world/item/ItemStack;Lcom/minecolonies/api/equipment/registry/EquipmentTypeEntry;)Z
  #121 = NameAndType        #119:#120     // isTinkersTool:(Lnet/minecraft/world/item/ItemStack;Lcom/minecolonies/api/equipment/registry/EquipmentTypeEntry;)Z
  #122 = Methodref          #118.#121     // com/minecolonies/api/compatibility/Compatibility.isTinkersTool:(Lnet/minecraft/world/item/ItemStack;Lcom/minecolonies/api/equipment/registry/EquipmentTypeEntry;)Z
  #123 = Utf8               getToolLevel
  #124 = Utf8               (Lnet/minecraft/world/item/ItemStack;)I
  #125 = NameAndType        #123:#124     // getToolLevel:(Lnet/minecraft/world/item/ItemStack;)I
  #126 = Methodref          #118.#125     // com/minecolonies/api/compatibility/Compatibility.getToolLevel:(Lnet/minecraft/world/item/ItemStack;)I
  #127 = Utf8               net/minecraft/world/item/ItemStack
  #128 = Class              #127          // net/minecraft/world/item/ItemStack
  #129 = Utf8               m_41720_
  #130 = Utf8               ()Lnet/minecraft/world/item/Item;
  #131 = NameAndType        #129:#130     // m_41720_:()Lnet/minecraft/world/item/Item;
  #132 = Methodref          #128.#131     // net/minecraft/world/item/ItemStack.m_41720_:()Lnet/minecraft/world/item/Item;
  #133 = Utf8               net/minecraft/world/item/TieredItem
  #134 = Class              #133          // net/minecraft/world/item/TieredItem
  #135 = Utf8               m_43314_
  #136 = Utf8               ()Lnet/minecraft/world/item/Tier;
  #137 = NameAndType        #135:#136     // m_43314_:()Lnet/minecraft/world/item/Tier;
  #138 = Methodref          #134.#137     // net/minecraft/world/item/TieredItem.m_43314_:()Lnet/minecraft/world/item/Tier;
  #139 = Utf8               net/minecraft/world/item/Tier
  #140 = Class              #139          // net/minecraft/world/item/Tier
  #141 = Utf8               m_6604_
  #142 = Utf8               ()I
  #143 = NameAndType        #141:#142     // m_6604_:()I
  #144 = InterfaceMethodref #140.#143     // net/minecraft/world/item/Tier.m_6604_:()I
  #145 = Utf8               tieredItem
  #146 = Utf8               Lnet/minecraft/world/item/TieredItem;
  #147 = Utf8               itemStack
  #148 = Utf8               Lnet/minecraft/world/item/ItemStack;
  #149 = Utf8               Lcom/minecolonies/api/equipment/registry/EquipmentTypeEntry;
  #150 = Utf8               durabilityBasedLevel
  #151 = Utf8               (Lnet/minecraft/world/item/ItemStack;I)I
  #152 = Utf8               m_41763_
  #153 = Utf8               ()Z
  #154 = NameAndType        #152:#153     // m_41763_:()Z
  #155 = Methodref          #128.#154     // net/minecraft/world/item/ItemStack.m_41763_:()Z
  #156 = Utf8               m_41776_
  #157 = NameAndType        #156:#142     // m_41776_:()I
  #158 = Methodref          #128.#157     // net/minecraft/world/item/ItemStack.m_41776_:()I
  #159 = Utf8               java/lang/Math
  #160 = Class              #159          // java/lang/Math
  #161 = Utf8               min
  #162 = Utf8               (II)I
  #163 = NameAndType        #161:#162     // min:(II)I
  #164 = Methodref          #160.#163     // java/lang/Math.min:(II)I
  #165 = Utf8               vanillaItemDurability
  #166 = Utf8               I
  #167 = Utf8               canPerformDefaultActions
  #168 = Utf8               (Lnet/minecraft/world/item/ItemStack;Ljava/util/Set;)Z
  #169 = Utf8               (Lnet/minecraft/world/item/ItemStack;Ljava/util/Set<Lnet/minecraftforge/common/ToolAction;>;)Z
  #170 = Utf8               java/util/Set
  #171 = Class              #170          // java/util/Set
  #172 = Utf8               iterator
  #173 = Utf8               ()Ljava/util/Iterator;
  #174 = NameAndType        #172:#173     // iterator:()Ljava/util/Iterator;
  #175 = InterfaceMethodref #171.#174     // java/util/Set.iterator:()Ljava/util/Iterator;
  #176 = Utf8               java/util/Iterator
  #177 = Class              #176          // java/util/Iterator
  #178 = Utf8               hasNext
  #179 = NameAndType        #178:#153     // hasNext:()Z
  #180 = InterfaceMethodref #177.#179     // java/util/Iterator.hasNext:()Z
  #181 = Utf8               next
  #182 = NameAndType        #181:#84      // next:()Ljava/lang/Object;
  #183 = InterfaceMethodref #177.#182     // java/util/Iterator.next:()Ljava/lang/Object;
  #184 = Utf8               net/minecraftforge/common/ToolAction
  #185 = Class              #184          // net/minecraftforge/common/ToolAction
  #186 = Utf8               canPerformAction
  #187 = Utf8               (Lnet/minecraftforge/common/ToolAction;)Z
  #188 = NameAndType        #186:#187     // canPerformAction:(Lnet/minecraftforge/common/ToolAction;)Z
  #189 = Methodref          #128.#188     // net/minecraft/world/item/ItemStack.canPerformAction:(Lnet/minecraftforge/common/ToolAction;)Z
  #190 = Utf8               toolAction
  #191 = Utf8               Lnet/minecraftforge/common/ToolAction;
  #192 = Utf8               actions
  #193 = Utf8               Ljava/util/Set<Lnet/minecraftforge/common/ToolAction;>;
  #194 = Utf8               Ljava/util/Set;
  #195 = Utf8               lambda$static$43
  #196 = Utf8               (Lcom/minecolonies/api/equipment/registry/EquipmentTypeEntry$Builder;)V
  #197 = Utf8               com.minecolonies.coremod.tooltype.lead
  #198 = String             #197          // com.minecolonies.coremod.tooltype.lead
  #199 = Utf8               net/minecraft/network/chat/Component
  #200 = Class              #199          // net/minecraft/network/chat/Component
  #201 = Utf8               m_237115_
  #202 = Utf8               (Ljava/lang/String;)Lnet/minecraft/network/chat/MutableComponent;
  #203 = NameAndType        #201:#202     // m_237115_:(Ljava/lang/String;)Lnet/minecraft/network/chat/MutableComponent;
  #204 = InterfaceMethodref #200.#203     // net/minecraft/network/chat/Component.m_237115_:(Ljava/lang/String;)Lnet/minecraft/network/chat/MutableComponent;
  #205 = Utf8               setDisplayName
  #206 = Utf8               (Lnet/minecraft/network/chat/Component;)Lcom/minecolonies/api/equipment/registry/EquipmentTypeEntry$Builder;
  #207 = NameAndType        #205:#206     // setDisplayName:(Lnet/minecraft/network/chat/Component;)Lcom/minecolonies/api/equipment/registry/EquipmentTypeEntry$Builder;
  #208 = Methodref          #7.#207       // com/minecolonies/api/equipment/registry/EquipmentTypeEntry$Builder.setDisplayName:(Lnet/minecraft/network/chat/Component;)Lcom/minecolonies/api/equipment/registry/EquipmentTypeEntry$Builder;
  #209 = Utf8               (Ljava/lang/Object;Ljava/lang/Object;)Z
  #210 = MethodType         #209          //  (Ljava/lang/Object;Ljava/lang/Object;)Z
  #211 = Utf8               lambda$static$41
  #212 = NameAndType        #211:#120     // lambda$static$41:(Lnet/minecraft/world/item/ItemStack;Lcom/minecolonies/api/equipment/registry/EquipmentTypeEntry;)Z
  #213 = Methodref          #2.#212       // com/minecolonies/api/equipment/ModEquipmentTypes.lambda$static$41:(Lnet/minecraft/world/item/ItemStack;Lcom/minecolonies/api/equipment/registry/EquipmentTypeEntry;)Z
  #214 = MethodHandle       6:#213        // REF_invokeStatic com/minecolonies/api/equipment/ModEquipmentTypes.lambda$static$41:(Lnet/minecraft/world/item/ItemStack;Lcom/minecolonies/api/equipment/registry/EquipmentTypeEntry;)Z
  #215 = MethodType         #120          //  (Lnet/minecraft/world/item/ItemStack;Lcom/minecolonies/api/equipment/registry/EquipmentTypeEntry;)Z
  #216 = Utf8               test
  #217 = Utf8               ()Ljava/util/function/BiPredicate;
  #218 = NameAndType        #216:#217     // test:()Ljava/util/function/BiPredicate;
  #219 = InvokeDynamic      #1:#218       // #1:test:()Ljava/util/function/BiPredicate;
  #220 = Utf8               setIsEquipment
  #221 = Utf8               (Ljava/util/function/BiPredicate;)Lcom/minecolonies/api/equipment/registry/EquipmentTypeEntry$Builder;
  #222 = NameAndType        #220:#221     // setIsEquipment:(Ljava/util/function/BiPredicate;)Lcom/minecolonies/api/equipment/registry/EquipmentTypeEntry$Builder;
  #223 = Methodref          #7.#222       // com/minecolonies/api/equipment/registry/EquipmentTypeEntry$Builder.setIsEquipment:(Ljava/util/function/BiPredicate;)Lcom/minecolonies/api/equipment/registry/EquipmentTypeEntry$Builder;
  #224 = Utf8               (Ljava/lang/Object;Ljava/lang/Object;)Ljava/lang/Object;
  #225 = MethodType         #224          //  (Ljava/lang/Object;Ljava/lang/Object;)Ljava/lang/Object;
  #226 = Utf8               lambda$static$42
  #227 = Utf8               (Lnet/minecraft/world/item/ItemStack;Lcom/minecolonies/api/equipment/registry/EquipmentTypeEntry;)Ljava/lang/Integer;
  #228 = NameAndType        #226:#227     // lambda$static$42:(Lnet/minecraft/world/item/ItemStack;Lcom/minecolonies/api/equipment/registry/EquipmentTypeEntry;)Ljava/lang/Integer;
  #229 = Methodref          #2.#228       // com/minecolonies/api/equipment/ModEquipmentTypes.lambda$static$42:(Lnet/minecraft/world/item/ItemStack;Lcom/minecolonies/api/equipment/registry/EquipmentTypeEntry;)Ljava/lang/Integer;
  #230 = MethodHandle       6:#229        // REF_invokeStatic com/minecolonies/api/equipment/ModEquipmentTypes.lambda$static$42:(Lnet/minecraft/world/item/ItemStack;Lcom/minecolonies/api/equipment/registry/EquipmentTypeEntry;)Ljava/lang/Integer;
  #231 = MethodType         #227          //  (Lnet/minecraft/world/item/ItemStack;Lcom/minecolonies/api/equipment/registry/EquipmentTypeEntry;)Ljava/lang/Integer;
  #232 = Utf8               apply
  #233 = Utf8               ()Ljava/util/function/BiFunction;
  #234 = NameAndType        #232:#233     // apply:()Ljava/util/function/BiFunction;
  #235 = InvokeDynamic      #2:#234       // #2:apply:()Ljava/util/function/BiFunction;
  #236 = Utf8               setEquipmentLevel
  #237 = Utf8               (Ljava/util/function/BiFunction;)Lcom/minecolonies/api/equipment/registry/EquipmentTypeEntry$Builder;
  #238 = NameAndType        #236:#237     // setEquipmentLevel:(Ljava/util/function/BiFunction;)Lcom/minecolonies/api/equipment/registry/EquipmentTypeEntry$Builder;
  #239 = Methodref          #7.#238       // com/minecolonies/api/equipment/registry/EquipmentTypeEntry$Builder.setEquipmentLevel:(Ljava/util/function/BiFunction;)Lcom/minecolonies/api/equipment/registry/EquipmentTypeEntry$Builder;
  #240 = Utf8               builder
  #241 = Utf8               java/lang/Integer
  #242 = Class              #241          // java/lang/Integer
  #243 = Utf8               valueOf
  #244 = Utf8               (I)Ljava/lang/Integer;
  #245 = NameAndType        #243:#244     // valueOf:(I)Ljava/lang/Integer;
  #246 = Methodref          #242.#245     // java/lang/Integer.valueOf:(I)Ljava/lang/Integer;
  #247 = Utf8               net/minecraft/world/item/LeadItem
  #248 = Class              #247          // net/minecraft/world/item/LeadItem
  #249 = Utf8               lambda$static$40
  #250 = Utf8               com.minecolonies.coremod.tooltype.lighter
  #251 = String             #250          // com.minecolonies.coremod.tooltype.lighter
  #252 = Utf8               lambda$static$38
  #253 = NameAndType        #252:#120     // lambda$static$38:(Lnet/minecraft/world/item/ItemStack;Lcom/minecolonies/api/equipment/registry/EquipmentTypeEntry;)Z
  #254 = Methodref          #2.#253       // com/minecolonies/api/equipment/ModEquipmentTypes.lambda$static$38:(Lnet/minecraft/world/item/ItemStack;Lcom/minecolonies/api/equipment/registry/EquipmentTypeEntry;)Z
  #255 = MethodHandle       6:#254        // REF_invokeStatic com/minecolonies/api/equipment/ModEquipmentTypes.lambda$static$38:(Lnet/minecraft/world/item/ItemStack;Lcom/minecolonies/api/equipment/registry/EquipmentTypeEntry;)Z
  #256 = InvokeDynamic      #3:#218       // #3:test:()Ljava/util/function/BiPredicate;
  #257 = Utf8               lambda$static$39
  #258 = NameAndType        #257:#227     // lambda$static$39:(Lnet/minecraft/world/item/ItemStack;Lcom/minecolonies/api/equipment/registry/EquipmentTypeEntry;)Ljava/lang/Integer;
  #259 = Methodref          #2.#258       // com/minecolonies/api/equipment/ModEquipmentTypes.lambda$static$39:(Lnet/minecraft/world/item/ItemStack;Lcom/minecolonies/api/equipment/registry/EquipmentTypeEntry;)Ljava/lang/Integer;
  #260 = MethodHandle       6:#259        // REF_invokeStatic com/minecolonies/api/equipment/ModEquipmentTypes.lambda$static$39:(Lnet/minecraft/world/item/ItemStack;Lcom/minecolonies/api/equipment/registry/EquipmentTypeEntry;)Ljava/lang/Integer;
  #261 = InvokeDynamic      #4:#234       // #4:apply:()Ljava/util/function/BiFunction;
  #262 = Utf8               net/minecraft/world/item/Items
  #263 = Class              #262          // net/minecraft/world/item/Items
  #264 = Utf8               f_42409_
  #265 = Utf8               Lnet/minecraft/world/item/Item;
  #266 = NameAndType        #264:#265     // f_42409_:Lnet/minecraft/world/item/Item;
  #267 = Fieldref           #263.#266     // net/minecraft/world/item/Items.f_42409_:Lnet/minecraft/world/item/Item;
  #268 = Utf8               net/minecraft/world/item/Item
  #269 = Class              #268          // net/minecraft/world/item/Item
  #270 = Utf8               m_41462_
  #271 = NameAndType        #270:#142     // m_41462_:()I
  #272 = Methodref          #269.#271     // net/minecraft/world/item/Item.m_41462_:()I
  #273 = NameAndType        #150:#151     // durabilityBasedLevel:(Lnet/minecraft/world/item/ItemStack;I)I
  #274 = Methodref          #2.#273       // com/minecolonies/api/equipment/ModEquipmentTypes.durabilityBasedLevel:(Lnet/minecraft/world/item/ItemStack;I)I
  #275 = Utf8               net/minecraft/world/item/FlintAndSteelItem
  #276 = Class              #275          // net/minecraft/world/item/FlintAndSteelItem
  #277 = Utf8               lambda$static$37
  #278 = Utf8               com.minecolonies.coremod.tooltype.boots
  #279 = String             #278          // com.minecolonies.coremod.tooltype.boots
  #280 = Utf8               lambda$static$35
  #281 = NameAndType        #280:#120     // lambda$static$35:(Lnet/minecraft/world/item/ItemStack;Lcom/minecolonies/api/equipment/registry/EquipmentTypeEntry;)Z
  #282 = Methodref          #2.#281       // com/minecolonies/api/equipment/ModEquipmentTypes.lambda$static$35:(Lnet/minecraft/world/item/ItemStack;Lcom/minecolonies/api/equipment/registry/EquipmentTypeEntry;)Z
  #283 = MethodHandle       6:#282        // REF_invokeStatic com/minecolonies/api/equipment/ModEquipmentTypes.lambda$static$35:(Lnet/minecraft/world/item/ItemStack;Lcom/minecolonies/api/equipment/registry/EquipmentTypeEntry;)Z
  #284 = InvokeDynamic      #5:#218       // #5:test:()Ljava/util/function/BiPredicate;
  #285 = Utf8               lambda$static$36
  #286 = NameAndType        #285:#227     // lambda$static$36:(Lnet/minecraft/world/item/ItemStack;Lcom/minecolonies/api/equipment/registry/EquipmentTypeEntry;)Ljava/lang/Integer;
  #287 = Methodref          #2.#286       // com/minecolonies/api/equipment/ModEquipmentTypes.lambda$static$36:(Lnet/minecraft/world/item/ItemStack;Lcom/minecolonies/api/equipment/registry/EquipmentTypeEntry;)Ljava/lang/Integer;
  #288 = MethodHandle       6:#287        // REF_invokeStatic com/minecolonies/api/equipment/ModEquipmentTypes.lambda$static$36:(Lnet/minecraft/world/item/ItemStack;Lcom/minecolonies/api/equipment/registry/EquipmentTypeEntry;)Ljava/lang/Integer;
  #289 = InvokeDynamic      #6:#234       // #6:apply:()Ljava/util/function/BiFunction;
  #290 = Utf8               com/minecolonies/api/util/ItemStackUtils
  #291 = Class              #290          // com/minecolonies/api/util/ItemStackUtils
  #292 = Utf8               getArmorLevel
  #293 = NameAndType        #292:#124     // getArmorLevel:(Lnet/minecraft/world/item/ItemStack;)I
  #294 = Methodref          #291.#293     // com/minecolonies/api/util/ItemStackUtils.getArmorLevel:(Lnet/minecraft/world/item/ItemStack;)I
  #295 = Utf8               net/minecraft/world/item/ArmorItem
  #296 = Class              #295          // net/minecraft/world/item/ArmorItem
  #297 = Utf8               net/minecraft/world/entity/EquipmentSlot
  #298 = Class              #297          // net/minecraft/world/entity/EquipmentSlot
  #299 = Utf8               FEET
  #300 = Utf8               Lnet/minecraft/world/entity/EquipmentSlot;
  #301 = NameAndType        #299:#300     // FEET:Lnet/minecraft/world/entity/EquipmentSlot;
  #302 = Fieldref           #298.#301     // net/minecraft/world/entity/EquipmentSlot.FEET:Lnet/minecraft/world/entity/EquipmentSlot;
  #303 = Utf8               m_40402_
  #304 = Utf8               ()Lnet/minecraft/world/entity/EquipmentSlot;
  #305 = NameAndType        #303:#304     // m_40402_:()Lnet/minecraft/world/entity/EquipmentSlot;
  #306 = Methodref          #296.#305     // net/minecraft/world/item/ArmorItem.m_40402_:()Lnet/minecraft/world/entity/EquipmentSlot;
  #307 = Utf8               equals
  #308 = Utf8               (Ljava/lang/Object;)Z
  #309 = NameAndType        #307:#308     // equals:(Ljava/lang/Object;)Z
  #310 = Methodref          #298.#309     // net/minecraft/world/entity/EquipmentSlot.equals:(Ljava/lang/Object;)Z
  #311 = Utf8               patt8875$temp
  #312 = Utf8               armor
  #313 = Utf8               Lnet/minecraft/world/item/ArmorItem;
  #314 = Utf8               lambda$static$34
  #315 = Utf8               com.minecolonies.coremod.tooltype.chestplate
  #316 = String             #315          // com.minecolonies.coremod.tooltype.chestplate
  #317 = Utf8               lambda$static$32
  #318 = NameAndType        #317:#120     // lambda$static$32:(Lnet/minecraft/world/item/ItemStack;Lcom/minecolonies/api/equipment/registry/EquipmentTypeEntry;)Z
  #319 = Methodref          #2.#318       // com/minecolonies/api/equipment/ModEquipmentTypes.lambda$static$32:(Lnet/minecraft/world/item/ItemStack;Lcom/minecolonies/api/equipment/registry/EquipmentTypeEntry;)Z
  #320 = MethodHandle       6:#319        // REF_invokeStatic com/minecolonies/api/equipment/ModEquipmentTypes.lambda$static$32:(Lnet/minecraft/world/item/ItemStack;Lcom/minecolonies/api/equipment/registry/EquipmentTypeEntry;)Z
  #321 = InvokeDynamic      #7:#218       // #7:test:()Ljava/util/function/BiPredicate;
  #322 = Utf8               lambda$static$33
  #323 = NameAndType        #322:#227     // lambda$static$33:(Lnet/minecraft/world/item/ItemStack;Lcom/minecolonies/api/equipment/registry/EquipmentTypeEntry;)Ljava/lang/Integer;
  #324 = Methodref          #2.#323       // com/minecolonies/api/equipment/ModEquipmentTypes.lambda$static$33:(Lnet/minecraft/world/item/ItemStack;Lcom/minecolonies/api/equipment/registry/EquipmentTypeEntry;)Ljava/lang/Integer;
  #325 = MethodHandle       6:#324        // REF_invokeStatic com/minecolonies/api/equipment/ModEquipmentTypes.lambda$static$33:(Lnet/minecraft/world/item/ItemStack;Lcom/minecolonies/api/equipment/registry/EquipmentTypeEntry;)Ljava/lang/Integer;
  #326 = InvokeDynamic      #8:#234       // #8:apply:()Ljava/util/function/BiFunction;
  #327 = Utf8               CHEST
  #328 = NameAndType        #327:#300     // CHEST:Lnet/minecraft/world/entity/EquipmentSlot;
  #329 = Fieldref           #298.#328     // net/minecraft/world/entity/EquipmentSlot.CHEST:Lnet/minecraft/world/entity/EquipmentSlot;
  #330 = Utf8               patt8415$temp
  #331 = Utf8               lambda$static$31
  #332 = Utf8               com.minecolonies.coremod.tooltype.leggings
  #333 = String             #332          // com.minecolonies.coremod.tooltype.leggings
  #334 = Utf8               lambda$static$29
  #335 = NameAndType        #334:#120     // lambda$static$29:(Lnet/minecraft/world/item/ItemStack;Lcom/minecolonies/api/equipment/registry/EquipmentTypeEntry;)Z
  #336 = Methodref          #2.#335       // com/minecolonies/api/equipment/ModEquipmentTypes.lambda$static$29:(Lnet/minecraft/world/item/ItemStack;Lcom/minecolonies/api/equipment/registry/EquipmentTypeEntry;)Z
  #337 = MethodHandle       6:#336        // REF_invokeStatic com/minecolonies/api/equipment/ModEquipmentTypes.lambda$static$29:(Lnet/minecraft/world/item/ItemStack;Lcom/minecolonies/api/equipment/registry/EquipmentTypeEntry;)Z
  #338 = InvokeDynamic      #9:#218       // #9:test:()Ljava/util/function/BiPredicate;
  #339 = Utf8               lambda$static$30
  #340 = NameAndType        #339:#227     // lambda$static$30:(Lnet/minecraft/world/item/ItemStack;Lcom/minecolonies/api/equipment/registry/EquipmentTypeEntry;)Ljava/lang/Integer;
  #341 = Methodref          #2.#340       // com/minecolonies/api/equipment/ModEquipmentTypes.lambda$static$30:(Lnet/minecraft/world/item/ItemStack;Lcom/minecolonies/api/equipment/registry/EquipmentTypeEntry;)Ljava/lang/Integer;
  #342 = MethodHandle       6:#341        // REF_invokeStatic com/minecolonies/api/equipment/ModEquipmentTypes.lambda$static$30:(Lnet/minecraft/world/item/ItemStack;Lcom/minecolonies/api/equipment/registry/EquipmentTypeEntry;)Ljava/lang/Integer;
  #343 = InvokeDynamic      #10:#234      // #10:apply:()Ljava/util/function/BiFunction;
  #344 = Utf8               LEGS
  #345 = NameAndType        #344:#300     // LEGS:Lnet/minecraft/world/entity/EquipmentSlot;
  #346 = Fieldref           #298.#345     // net/minecraft/world/entity/EquipmentSlot.LEGS:Lnet/minecraft/world/entity/EquipmentSlot;
  #347 = Utf8               patt7940$temp
  #348 = Utf8               lambda$static$28
  #349 = Utf8               com.minecolonies.coremod.tooltype.helmet
  #350 = String             #349          // com.minecolonies.coremod.tooltype.helmet
  #351 = Utf8               lambda$static$26
  #352 = NameAndType        #351:#120     // lambda$static$26:(Lnet/minecraft/world/item/ItemStack;Lcom/minecolonies/api/equipment/registry/EquipmentTypeEntry;)Z
  #353 = Methodref          #2.#352       // com/minecolonies/api/equipment/ModEquipmentTypes.lambda$static$26:(Lnet/minecraft/world/item/ItemStack;Lcom/minecolonies/api/equipment/registry/EquipmentTypeEntry;)Z
  #354 = MethodHandle       6:#353        // REF_invokeStatic com/minecolonies/api/equipment/ModEquipmentTypes.lambda$static$26:(Lnet/minecraft/world/item/ItemStack;Lcom/minecolonies/api/equipment/registry/EquipmentTypeEntry;)Z
  #355 = InvokeDynamic      #11:#218      // #11:test:()Ljava/util/function/BiPredicate;
  #356 = Utf8               lambda$static$27
  #357 = NameAndType        #356:#227     // lambda$static$27:(Lnet/minecraft/world/item/ItemStack;Lcom/minecolonies/api/equipment/registry/EquipmentTypeEntry;)Ljava/lang/Integer;
  #358 = Methodref          #2.#357       // com/minecolonies/api/equipment/ModEquipmentTypes.lambda$static$27:(Lnet/minecraft/world/item/ItemStack;Lcom/minecolonies/api/equipment/registry/EquipmentTypeEntry;)Ljava/lang/Integer;
  #359 = MethodHandle       6:#358        // REF_invokeStatic com/minecolonies/api/equipment/ModEquipmentTypes.lambda$static$27:(Lnet/minecraft/world/item/ItemStack;Lcom/minecolonies/api/equipment/registry/EquipmentTypeEntry;)Ljava/lang/Integer;
  #360 = InvokeDynamic      #12:#234      // #12:apply:()Ljava/util/function/BiFunction;
  #361 = Utf8               HEAD
  #362 = NameAndType        #361:#300     // HEAD:Lnet/minecraft/world/entity/EquipmentSlot;
  #363 = Fieldref           #298.#362     // net/minecraft/world/entity/EquipmentSlot.HEAD:Lnet/minecraft/world/entity/EquipmentSlot;
  #364 = Utf8               patt7472$temp
  #365 = Utf8               lambda$static$25
  #366 = Utf8               com.minecolonies.coremod.tooltype.shield
  #367 = String             #366          // com.minecolonies.coremod.tooltype.shield
  #368 = Utf8               lambda$static$23
  #369 = NameAndType        #368:#120     // lambda$static$23:(Lnet/minecraft/world/item/ItemStack;Lcom/minecolonies/api/equipment/registry/EquipmentTypeEntry;)Z
  #370 = Methodref          #2.#369       // com/minecolonies/api/equipment/ModEquipmentTypes.lambda$static$23:(Lnet/minecraft/world/item/ItemStack;Lcom/minecolonies/api/equipment/registry/EquipmentTypeEntry;)Z
  #371 = MethodHandle       6:#370        // REF_invokeStatic com/minecolonies/api/equipment/ModEquipmentTypes.lambda$static$23:(Lnet/minecraft/world/item/ItemStack;Lcom/minecolonies/api/equipment/registry/EquipmentTypeEntry;)Z
  #372 = InvokeDynamic      #13:#218      // #13:test:()Ljava/util/function/BiPredicate;
  #373 = Utf8               lambda$static$24
  #374 = NameAndType        #373:#227     // lambda$static$24:(Lnet/minecraft/world/item/ItemStack;Lcom/minecolonies/api/equipment/registry/EquipmentTypeEntry;)Ljava/lang/Integer;
  #375 = Methodref          #2.#374       // com/minecolonies/api/equipment/ModEquipmentTypes.lambda$static$24:(Lnet/minecraft/world/item/ItemStack;Lcom/minecolonies/api/equipment/registry/EquipmentTypeEntry;)Ljava/lang/Integer;
  #376 = MethodHandle       6:#375        // REF_invokeStatic com/minecolonies/api/equipment/ModEquipmentTypes.lambda$static$24:(Lnet/minecraft/world/item/ItemStack;Lcom/minecolonies/api/equipment/registry/EquipmentTypeEntry;)Ljava/lang/Integer;
  #377 = InvokeDynamic      #14:#234      // #14:apply:()Ljava/util/function/BiFunction;
  #378 = Utf8               f_42740_
  #379 = NameAndType        #378:#265     // f_42740_:Lnet/minecraft/world/item/Item;
  #380 = Fieldref           #263.#379     // net/minecraft/world/item/Items.f_42740_:Lnet/minecraft/world/item/Item;
  #381 = Utf8               net/minecraftforge/common/ToolActions
  #382 = Class              #381          // net/minecraftforge/common/ToolActions
  #383 = Utf8               DEFAULT_SHIELD_ACTIONS
  #384 = NameAndType        #383:#194     // DEFAULT_SHIELD_ACTIONS:Ljava/util/Set;
  #385 = Fieldref           #382.#384     // net/minecraftforge/common/ToolActions.DEFAULT_SHIELD_ACTIONS:Ljava/util/Set;
  #386 = NameAndType        #167:#168     // canPerformDefaultActions:(Lnet/minecraft/world/item/ItemStack;Ljava/util/Set;)Z
  #387 = Methodref          #2.#386       // com/minecolonies/api/equipment/ModEquipmentTypes.canPerformDefaultActions:(Lnet/minecraft/world/item/ItemStack;Ljava/util/Set;)Z
  #388 = Utf8               lambda$static$22
  #389 = Utf8               com.minecolonies.coremod.tooltype.shears
  #390 = String             #389          // com.minecolonies.coremod.tooltype.shears
  #391 = Utf8               lambda$static$20
  #392 = NameAndType        #391:#120     // lambda$static$20:(Lnet/minecraft/world/item/ItemStack;Lcom/minecolonies/api/equipment/registry/EquipmentTypeEntry;)Z
  #393 = Methodref          #2.#392       // com/minecolonies/api/equipment/ModEquipmentTypes.lambda$static$20:(Lnet/minecraft/world/item/ItemStack;Lcom/minecolonies/api/equipment/registry/EquipmentTypeEntry;)Z
  #394 = MethodHandle       6:#393        // REF_invokeStatic com/minecolonies/api/equipment/ModEquipmentTypes.lambda$static$20:(Lnet/minecraft/world/item/ItemStack;Lcom/minecolonies/api/equipment/registry/EquipmentTypeEntry;)Z
  #395 = InvokeDynamic      #15:#218      // #15:test:()Ljava/util/function/BiPredicate;
  #396 = Utf8               lambda$static$21
  #397 = NameAndType        #396:#227     // lambda$static$21:(Lnet/minecraft/world/item/ItemStack;Lcom/minecolonies/api/equipment/registry/EquipmentTypeEntry;)Ljava/lang/Integer;
  #398 = Methodref          #2.#397       // com/minecolonies/api/equipment/ModEquipmentTypes.lambda$static$21:(Lnet/minecraft/world/item/ItemStack;Lcom/minecolonies/api/equipment/registry/EquipmentTypeEntry;)Ljava/lang/Integer;
  #399 = MethodHandle       6:#398        // REF_invokeStatic com/minecolonies/api/equipment/ModEquipmentTypes.lambda$static$21:(Lnet/minecraft/world/item/ItemStack;Lcom/minecolonies/api/equipment/registry/EquipmentTypeEntry;)Ljava/lang/Integer;
  #400 = InvokeDynamic      #16:#234      // #16:apply:()Ljava/util/function/BiFunction;
  #401 = Utf8               f_42574_
  #402 = NameAndType        #401:#265     // f_42574_:Lnet/minecraft/world/item/Item;
  #403 = Fieldref           #263.#402     // net/minecraft/world/item/Items.f_42574_:Lnet/minecraft/world/item/Item;
  #404 = Utf8               DEFAULT_SHEARS_ACTIONS
  #405 = NameAndType        #404:#194     // DEFAULT_SHEARS_ACTIONS:Ljava/util/Set;
  #406 = Fieldref           #382.#405     // net/minecraftforge/common/ToolActions.DEFAULT_SHEARS_ACTIONS:Ljava/util/Set;
  #407 = Utf8               lambda$static$19
  #408 = Utf8               com.minecolonies.coremod.tooltype.fishingrod
  #409 = String             #408          // com.minecolonies.coremod.tooltype.fishingrod
  #410 = Utf8               lambda$static$17
  #411 = NameAndType        #410:#120     // lambda$static$17:(Lnet/minecraft/world/item/ItemStack;Lcom/minecolonies/api/equipment/registry/EquipmentTypeEntry;)Z
  #412 = Methodref          #2.#411       // com/minecolonies/api/equipment/ModEquipmentTypes.lambda$static$17:(Lnet/minecraft/world/item/ItemStack;Lcom/minecolonies/api/equipment/registry/EquipmentTypeEntry;)Z
  #413 = MethodHandle       6:#412        // REF_invokeStatic com/minecolonies/api/equipment/ModEquipmentTypes.lambda$static$17:(Lnet/minecraft/world/item/ItemStack;Lcom/minecolonies/api/equipment/registry/EquipmentTypeEntry;)Z
  #414 = InvokeDynamic      #17:#218      // #17:test:()Ljava/util/function/BiPredicate;
  #415 = Utf8               lambda$static$18
  #416 = NameAndType        #415:#227     // lambda$static$18:(Lnet/minecraft/world/item/ItemStack;Lcom/minecolonies/api/equipment/registry/EquipmentTypeEntry;)Ljava/lang/Integer;
  #417 = Methodref          #2.#416       // com/minecolonies/api/equipment/ModEquipmentTypes.lambda$static$18:(Lnet/minecraft/world/item/ItemStack;Lcom/minecolonies/api/equipment/registry/EquipmentTypeEntry;)Ljava/lang/Integer;
  #418 = MethodHandle       6:#417        // REF_invokeStatic com/minecolonies/api/equipment/ModEquipmentTypes.lambda$static$18:(Lnet/minecraft/world/item/ItemStack;Lcom/minecolonies/api/equipment/registry/EquipmentTypeEntry;)Ljava/lang/Integer;
  #419 = InvokeDynamic      #18:#234      // #18:apply:()Ljava/util/function/BiFunction;
  #420 = Utf8               f_42523_
  #421 = NameAndType        #420:#265     // f_42523_:Lnet/minecraft/world/item/Item;
  #422 = Fieldref           #263.#421     // net/minecraft/world/item/Items.f_42523_:Lnet/minecraft/world/item/Item;
  #423 = Utf8               DEFAULT_FISHING_ROD_ACTIONS
  #424 = NameAndType        #423:#194     // DEFAULT_FISHING_ROD_ACTIONS:Ljava/util/Set;
  #425 = Fieldref           #382.#424     // net/minecraftforge/common/ToolActions.DEFAULT_FISHING_ROD_ACTIONS:Ljava/util/Set;
  #426 = Utf8               lambda$static$16
  #427 = Utf8               com.minecolonies.coremod.tooltype.bow
  #428 = String             #427          // com.minecolonies.coremod.tooltype.bow
  #429 = Utf8               lambda$static$14
  #430 = NameAndType        #429:#120     // lambda$static$14:(Lnet/minecraft/world/item/ItemStack;Lcom/minecolonies/api/equipment/registry/EquipmentTypeEntry;)Z
  #431 = Methodref          #2.#430       // com/minecolonies/api/equipment/ModEquipmentTypes.lambda$static$14:(Lnet/minecraft/world/item/ItemStack;Lcom/minecolonies/api/equipment/registry/EquipmentTypeEntry;)Z
  #432 = MethodHandle       6:#431        // REF_invokeStatic com/minecolonies/api/equipment/ModEquipmentTypes.lambda$static$14:(Lnet/minecraft/world/item/ItemStack;Lcom/minecolonies/api/equipment/registry/EquipmentTypeEntry;)Z
  #433 = InvokeDynamic      #19:#218      // #19:test:()Ljava/util/function/BiPredicate;
  #434 = Utf8               lambda$static$15
  #435 = NameAndType        #434:#227     // lambda$static$15:(Lnet/minecraft/world/item/ItemStack;Lcom/minecolonies/api/equipment/registry/EquipmentTypeEntry;)Ljava/lang/Integer;
  #436 = Methodref          #2.#435       // com/minecolonies/api/equipment/ModEquipmentTypes.lambda$static$15:(Lnet/minecraft/world/item/ItemStack;Lcom/minecolonies/api/equipment/registry/EquipmentTypeEntry;)Ljava/lang/Integer;
  #437 = MethodHandle       6:#436        // REF_invokeStatic com/minecolonies/api/equipment/ModEquipmentTypes.lambda$static$15:(Lnet/minecraft/world/item/ItemStack;Lcom/minecolonies/api/equipment/registry/EquipmentTypeEntry;)Ljava/lang/Integer;
  #438 = InvokeDynamic      #20:#234      // #20:apply:()Ljava/util/function/BiFunction;
  #439 = Utf8               f_42411_
  #440 = NameAndType        #439:#265     // f_42411_:Lnet/minecraft/world/item/Item;
  #441 = Fieldref           #263.#440     // net/minecraft/world/item/Items.f_42411_:Lnet/minecraft/world/item/Item;
  #442 = Utf8               net/minecraft/world/item/BowItem
  #443 = Class              #442          // net/minecraft/world/item/BowItem
  #444 = Utf8               lambda$static$13
  #445 = Utf8               com.minecolonies.coremod.tooltype.sword
  #446 = String             #445          // com.minecolonies.coremod.tooltype.sword
  #447 = Utf8               lambda$static$11
  #448 = NameAndType        #447:#120     // lambda$static$11:(Lnet/minecraft/world/item/ItemStack;Lcom/minecolonies/api/equipment/registry/EquipmentTypeEntry;)Z
  #449 = Methodref          #2.#448       // com/minecolonies/api/equipment/ModEquipmentTypes.lambda$static$11:(Lnet/minecraft/world/item/ItemStack;Lcom/minecolonies/api/equipment/registry/EquipmentTypeEntry;)Z
  #450 = MethodHandle       6:#449        // REF_invokeStatic com/minecolonies/api/equipment/ModEquipmentTypes.lambda$static$11:(Lnet/minecraft/world/item/ItemStack;Lcom/minecolonies/api/equipment/registry/EquipmentTypeEntry;)Z
  #451 = InvokeDynamic      #21:#218      // #21:test:()Ljava/util/function/BiPredicate;
  #452 = Utf8               lambda$static$12
  #453 = NameAndType        #452:#227     // lambda$static$12:(Lnet/minecraft/world/item/ItemStack;Lcom/minecolonies/api/equipment/registry/EquipmentTypeEntry;)Ljava/lang/Integer;
  #454 = Methodref          #2.#453       // com/minecolonies/api/equipment/ModEquipmentTypes.lambda$static$12:(Lnet/minecraft/world/item/ItemStack;Lcom/minecolonies/api/equipment/registry/EquipmentTypeEntry;)Ljava/lang/Integer;
  #455 = MethodHandle       6:#454        // REF_invokeStatic com/minecolonies/api/equipment/ModEquipmentTypes.lambda$static$12:(Lnet/minecraft/world/item/ItemStack;Lcom/minecolonies/api/equipment/registry/EquipmentTypeEntry;)Ljava/lang/Integer;
  #456 = InvokeDynamic      #22:#234      // #22:apply:()Ljava/util/function/BiFunction;
  #457 = Utf8               isTinkersWeapon
  #458 = Utf8               (Lnet/minecraft/world/item/ItemStack;)Z
  #459 = NameAndType        #457:#458     // isTinkersWeapon:(Lnet/minecraft/world/item/ItemStack;)Z
  #460 = Methodref          #118.#459     // com/minecolonies/api/compatibility/Compatibility.isTinkersWeapon:(Lnet/minecraft/world/item/ItemStack;)Z
  #461 = Utf8               patt5214$temp
  #462 = Utf8               DEFAULT_SWORD_ACTIONS
  #463 = NameAndType        #462:#194     // DEFAULT_SWORD_ACTIONS:Ljava/util/Set;
  #464 = Fieldref           #382.#463     // net/minecraftforge/common/ToolActions.DEFAULT_SWORD_ACTIONS:Ljava/util/Set;
  #465 = Utf8               lambda$static$10
  #466 = Utf8               com.minecolonies.coremod.tooltype.hoe
  #467 = String             #466          // com.minecolonies.coremod.tooltype.hoe
  #468 = Utf8               lambda$static$9
  #469 = NameAndType        #468:#120     // lambda$static$9:(Lnet/minecraft/world/item/ItemStack;Lcom/minecolonies/api/equipment/registry/EquipmentTypeEntry;)Z
  #470 = Methodref          #2.#469       // com/minecolonies/api/equipment/ModEquipmentTypes.lambda$static$9:(Lnet/minecraft/world/item/ItemStack;Lcom/minecolonies/api/equipment/registry/EquipmentTypeEntry;)Z
  #471 = MethodHandle       6:#470        // REF_invokeStatic com/minecolonies/api/equipment/ModEquipmentTypes.lambda$static$9:(Lnet/minecraft/world/item/ItemStack;Lcom/minecolonies/api/equipment/registry/EquipmentTypeEntry;)Z
  #472 = InvokeDynamic      #23:#218      // #23:test:()Ljava/util/function/BiPredicate;
  #473 = NameAndType        #115:#116     // vanillaToolLevel:(Lnet/minecraft/world/item/ItemStack;Lcom/minecolonies/api/equipment/registry/EquipmentTypeEntry;)I
  #474 = Methodref          #2.#473       // com/minecolonies/api/equipment/ModEquipmentTypes.vanillaToolLevel:(Lnet/minecraft/world/item/ItemStack;Lcom/minecolonies/api/equipment/registry/EquipmentTypeEntry;)I
  #475 = MethodHandle       6:#474        // REF_invokeStatic com/minecolonies/api/equipment/ModEquipmentTypes.vanillaToolLevel:(Lnet/minecraft/world/item/ItemStack;Lcom/minecolonies/api/equipment/registry/EquipmentTypeEntry;)I
  #476 = InvokeDynamic      #24:#234      // #24:apply:()Ljava/util/function/BiFunction;
  #477 = Utf8               DEFAULT_HOE_ACTIONS
  #478 = NameAndType        #477:#194     // DEFAULT_HOE_ACTIONS:Ljava/util/Set;
  #479 = Fieldref           #382.#478     // net/minecraftforge/common/ToolActions.DEFAULT_HOE_ACTIONS:Ljava/util/Set;
  #480 = Utf8               lambda$static$8
  #481 = Utf8               com.minecolonies.coremod.tooltype.axe
  #482 = String             #481          // com.minecolonies.coremod.tooltype.axe
  #483 = Utf8               lambda$static$7
  #484 = NameAndType        #483:#120     // lambda$static$7:(Lnet/minecraft/world/item/ItemStack;Lcom/minecolonies/api/equipment/registry/EquipmentTypeEntry;)Z
  #485 = Methodref          #2.#484       // com/minecolonies/api/equipment/ModEquipmentTypes.lambda$static$7:(Lnet/minecraft/world/item/ItemStack;Lcom/minecolonies/api/equipment/registry/EquipmentTypeEntry;)Z
  #486 = MethodHandle       6:#485        // REF_invokeStatic com/minecolonies/api/equipment/ModEquipmentTypes.lambda$static$7:(Lnet/minecraft/world/item/ItemStack;Lcom/minecolonies/api/equipment/registry/EquipmentTypeEntry;)Z
  #487 = InvokeDynamic      #25:#218      // #25:test:()Ljava/util/function/BiPredicate;
  #488 = Utf8               DEFAULT_AXE_ACTIONS
  #489 = NameAndType        #488:#194     // DEFAULT_AXE_ACTIONS:Ljava/util/Set;
  #490 = Fieldref           #382.#489     // net/minecraftforge/common/ToolActions.DEFAULT_AXE_ACTIONS:Ljava/util/Set;
  #491 = Utf8               lambda$static$6
  #492 = Utf8               com.minecolonies.coremod.tooltype.shovel
  #493 = String             #492          // com.minecolonies.coremod.tooltype.shovel
  #494 = Utf8               lambda$static$5
  #495 = NameAndType        #494:#120     // lambda$static$5:(Lnet/minecraft/world/item/ItemStack;Lcom/minecolonies/api/equipment/registry/EquipmentTypeEntry;)Z
  #496 = Methodref          #2.#495       // com/minecolonies/api/equipment/ModEquipmentTypes.lambda$static$5:(Lnet/minecraft/world/item/ItemStack;Lcom/minecolonies/api/equipment/registry/EquipmentTypeEntry;)Z
  #497 = MethodHandle       6:#496        // REF_invokeStatic com/minecolonies/api/equipment/ModEquipmentTypes.lambda$static$5:(Lnet/minecraft/world/item/ItemStack;Lcom/minecolonies/api/equipment/registry/EquipmentTypeEntry;)Z
  #498 = InvokeDynamic      #26:#218      // #26:test:()Ljava/util/function/BiPredicate;
  #499 = Utf8               DEFAULT_SHOVEL_ACTIONS
  #500 = NameAndType        #499:#194     // DEFAULT_SHOVEL_ACTIONS:Ljava/util/Set;
  #501 = Fieldref           #382.#500     // net/minecraftforge/common/ToolActions.DEFAULT_SHOVEL_ACTIONS:Ljava/util/Set;
  #502 = Utf8               lambda$static$4
  #503 = Utf8               com.minecolonies.coremod.tooltype.pickaxe
  #504 = String             #503          // com.minecolonies.coremod.tooltype.pickaxe
  #505 = Utf8               lambda$static$3
  #506 = NameAndType        #505:#120     // lambda$static$3:(Lnet/minecraft/world/item/ItemStack;Lcom/minecolonies/api/equipment/registry/EquipmentTypeEntry;)Z
  #507 = Methodref          #2.#506       // com/minecolonies/api/equipment/ModEquipmentTypes.lambda$static$3:(Lnet/minecraft/world/item/ItemStack;Lcom/minecolonies/api/equipment/registry/EquipmentTypeEntry;)Z
  #508 = MethodHandle       6:#507        // REF_invokeStatic com/minecolonies/api/equipment/ModEquipmentTypes.lambda$static$3:(Lnet/minecraft/world/item/ItemStack;Lcom/minecolonies/api/equipment/registry/EquipmentTypeEntry;)Z
  #509 = InvokeDynamic      #27:#218      // #27:test:()Ljava/util/function/BiPredicate;
  #510 = Utf8               DEFAULT_PICKAXE_ACTIONS
  #511 = NameAndType        #510:#194     // DEFAULT_PICKAXE_ACTIONS:Ljava/util/Set;
  #512 = Fieldref           #382.#511     // net/minecraftforge/common/ToolActions.DEFAULT_PICKAXE_ACTIONS:Ljava/util/Set;
  #513 = Utf8               lambda$static$2
  #514 = Utf8               com.minecolonies.coremod.tooltype.none
  #515 = String             #514          // com.minecolonies.coremod.tooltype.none
  #516 = Utf8               lambda$static$0
  #517 = NameAndType        #516:#120     // lambda$static$0:(Lnet/minecraft/world/item/ItemStack;Lcom/minecolonies/api/equipment/registry/EquipmentTypeEntry;)Z
  #518 = Methodref          #2.#517       // com/minecolonies/api/equipment/ModEquipmentTypes.lambda$static$0:(Lnet/minecraft/world/item/ItemStack;Lcom/minecolonies/api/equipment/registry/EquipmentTypeEntry;)Z
  #519 = MethodHandle       6:#518        // REF_invokeStatic com/minecolonies/api/equipment/ModEquipmentTypes.lambda$static$0:(Lnet/minecraft/world/item/ItemStack;Lcom/minecolonies/api/equipment/registry/EquipmentTypeEntry;)Z
  #520 = InvokeDynamic      #28:#218      // #28:test:()Ljava/util/function/BiPredicate;
  #521 = Utf8               lambda$static$1
  #522 = NameAndType        #521:#227     // lambda$static$1:(Lnet/minecraft/world/item/ItemStack;Lcom/minecolonies/api/equipment/registry/EquipmentTypeEntry;)Ljava/lang/Integer;
  #523 = Methodref          #2.#522       // com/minecolonies/api/equipment/ModEquipmentTypes.lambda$static$1:(Lnet/minecraft/world/item/ItemStack;Lcom/minecolonies/api/equipment/registry/EquipmentTypeEntry;)Ljava/lang/Integer;
  #524 = MethodHandle       6:#523        // REF_invokeStatic com/minecolonies/api/equipment/ModEquipmentTypes.lambda$static$1:(Lnet/minecraft/world/item/ItemStack;Lcom/minecolonies/api/equipment/registry/EquipmentTypeEntry;)Ljava/lang/Integer;
  #525 = InvokeDynamic      #29:#234      // #29:apply:()Ljava/util/function/BiFunction;
  #526 = Utf8               <clinit>
  #527 = Utf8               equipmenttypes
  #528 = String             #527          // equipmenttypes
  #529 = Utf8               create
  #530 = Utf8               (Lnet/minecraft/resources/ResourceLocation;Ljava/lang/String;)Lnet/minecraftforge/registries/DeferredRegister;
  #531 = NameAndType        #529:#530     // create:(Lnet/minecraft/resources/ResourceLocation;Ljava/lang/String;)Lnet/minecraftforge/registries/DeferredRegister;
  #532 = Methodref          #104.#531     // net/minecraftforge/registries/DeferredRegister.create:(Lnet/minecraft/resources/ResourceLocation;Ljava/lang/String;)Lnet/minecraftforge/registries/DeferredRegister;
  #533 = String             #19           // none
  #534 = MethodType         #73           //  (Ljava/lang/Object;)V
  #535 = NameAndType        #513:#196     // lambda$static$2:(Lcom/minecolonies/api/equipment/registry/EquipmentTypeEntry$Builder;)V
  #536 = Methodref          #2.#535       // com/minecolonies/api/equipment/ModEquipmentTypes.lambda$static$2:(Lcom/minecolonies/api/equipment/registry/EquipmentTypeEntry$Builder;)V
  #537 = MethodHandle       6:#536        // REF_invokeStatic com/minecolonies/api/equipment/ModEquipmentTypes.lambda$static$2:(Lcom/minecolonies/api/equipment/registry/EquipmentTypeEntry$Builder;)V
  #538 = MethodType         #196          //  (Lcom/minecolonies/api/equipment/registry/EquipmentTypeEntry$Builder;)V
  #539 = Utf8               ()Ljava/util/function/Consumer;
  #540 = NameAndType        #72:#539      // accept:()Ljava/util/function/Consumer;
  #541 = InvokeDynamic      #30:#540      // #30:accept:()Ljava/util/function/Consumer;
  #542 = NameAndType        #55:#56       // register:(Ljava/lang/String;Ljava/util/function/Consumer;)Lnet/minecraftforge/registries/RegistryObject;
  #543 = Methodref          #2.#542       // com/minecolonies/api/equipment/ModEquipmentTypes.register:(Ljava/lang/String;Ljava/util/function/Consumer;)Lnet/minecraftforge/registries/RegistryObject;
  #544 = NameAndType        #19:#20       // none:Lnet/minecraftforge/registries/RegistryObject;
  #545 = Fieldref           #2.#544       // com/minecolonies/api/equipment/ModEquipmentTypes.none:Lnet/minecraftforge/registries/RegistryObject;
  #546 = String             #22           // pickaxe
  #547 = NameAndType        #502:#196     // lambda$static$4:(Lcom/minecolonies/api/equipment/registry/EquipmentTypeEntry$Builder;)V
  #548 = Methodref          #2.#547       // com/minecolonies/api/equipment/ModEquipmentTypes.lambda$static$4:(Lcom/minecolonies/api/equipment/registry/EquipmentTypeEntry$Builder;)V
  #549 = MethodHandle       6:#548        // REF_invokeStatic com/minecolonies/api/equipment/ModEquipmentTypes.lambda$static$4:(Lcom/minecolonies/api/equipment/registry/EquipmentTypeEntry$Builder;)V
  #550 = InvokeDynamic      #31:#540      // #31:accept:()Ljava/util/function/Consumer;
  #551 = NameAndType        #22:#20       // pickaxe:Lnet/minecraftforge/registries/RegistryObject;
  #552 = Fieldref           #2.#551       // com/minecolonies/api/equipment/ModEquipmentTypes.pickaxe:Lnet/minecraftforge/registries/RegistryObject;
  #553 = String             #23           // shovel
  #554 = NameAndType        #491:#196     // lambda$static$6:(Lcom/minecolonies/api/equipment/registry/EquipmentTypeEntry$Builder;)V
  #555 = Methodref          #2.#554       // com/minecolonies/api/equipment/ModEquipmentTypes.lambda$static$6:(Lcom/minecolonies/api/equipment/registry/EquipmentTypeEntry$Builder;)V
  #556 = MethodHandle       6:#555        // REF_invokeStatic com/minecolonies/api/equipment/ModEquipmentTypes.lambda$static$6:(Lcom/minecolonies/api/equipment/registry/EquipmentTypeEntry$Builder;)V
  #557 = InvokeDynamic      #32:#540      // #32:accept:()Ljava/util/function/Consumer;
  #558 = NameAndType        #23:#20       // shovel:Lnet/minecraftforge/registries/RegistryObject;
  #559 = Fieldref           #2.#558       // com/minecolonies/api/equipment/ModEquipmentTypes.shovel:Lnet/minecraftforge/registries/RegistryObject;
  #560 = String             #24           // axe
  #561 = NameAndType        #480:#196     // lambda$static$8:(Lcom/minecolonies/api/equipment/registry/EquipmentTypeEntry$Builder;)V
  #562 = Methodref          #2.#561       // com/minecolonies/api/equipment/ModEquipmentTypes.lambda$static$8:(Lcom/minecolonies/api/equipment/registry/EquipmentTypeEntry$Builder;)V
  #563 = MethodHandle       6:#562        // REF_invokeStatic com/minecolonies/api/equipment/ModEquipmentTypes.lambda$static$8:(Lcom/minecolonies/api/equipment/registry/EquipmentTypeEntry$Builder;)V
  #564 = InvokeDynamic      #33:#540      // #33:accept:()Ljava/util/function/Consumer;
  #565 = NameAndType        #24:#20       // axe:Lnet/minecraftforge/registries/RegistryObject;
  #566 = Fieldref           #2.#565       // com/minecolonies/api/equipment/ModEquipmentTypes.axe:Lnet/minecraftforge/registries/RegistryObject;
  #567 = String             #25           // hoe
  #568 = NameAndType        #465:#196     // lambda$static$10:(Lcom/minecolonies/api/equipment/registry/EquipmentTypeEntry$Builder;)V
  #569 = Methodref          #2.#568       // com/minecolonies/api/equipment/ModEquipmentTypes.lambda$static$10:(Lcom/minecolonies/api/equipment/registry/EquipmentTypeEntry$Builder;)V
  #570 = MethodHandle       6:#569        // REF_invokeStatic com/minecolonies/api/equipment/ModEquipmentTypes.lambda$static$10:(Lcom/minecolonies/api/equipment/registry/EquipmentTypeEntry$Builder;)V
  #571 = InvokeDynamic      #34:#540      // #34:accept:()Ljava/util/function/Consumer;
  #572 = NameAndType        #25:#20       // hoe:Lnet/minecraftforge/registries/RegistryObject;
  #573 = Fieldref           #2.#572       // com/minecolonies/api/equipment/ModEquipmentTypes.hoe:Lnet/minecraftforge/registries/RegistryObject;
  #574 = String             #26           // sword
  #575 = NameAndType        #444:#196     // lambda$static$13:(Lcom/minecolonies/api/equipment/registry/EquipmentTypeEntry$Builder;)V
  #576 = Methodref          #2.#575       // com/minecolonies/api/equipment/ModEquipmentTypes.lambda$static$13:(Lcom/minecolonies/api/equipment/registry/EquipmentTypeEntry$Builder;)V
  #577 = MethodHandle       6:#576        // REF_invokeStatic com/minecolonies/api/equipment/ModEquipmentTypes.lambda$static$13:(Lcom/minecolonies/api/equipment/registry/EquipmentTypeEntry$Builder;)V
  #578 = InvokeDynamic      #35:#540      // #35:accept:()Ljava/util/function/Consumer;
  #579 = NameAndType        #26:#20       // sword:Lnet/minecraftforge/registries/RegistryObject;
  #580 = Fieldref           #2.#579       // com/minecolonies/api/equipment/ModEquipmentTypes.sword:Lnet/minecraftforge/registries/RegistryObject;
  #581 = String             #27           // bow
  #582 = NameAndType        #426:#196     // lambda$static$16:(Lcom/minecolonies/api/equipment/registry/EquipmentTypeEntry$Builder;)V
  #583 = Methodref          #2.#582       // com/minecolonies/api/equipment/ModEquipmentTypes.lambda$static$16:(Lcom/minecolonies/api/equipment/registry/EquipmentTypeEntry$Builder;)V
  #584 = MethodHandle       6:#583        // REF_invokeStatic com/minecolonies/api/equipment/ModEquipmentTypes.lambda$static$16:(Lcom/minecolonies/api/equipment/registry/EquipmentTypeEntry$Builder;)V
  #585 = InvokeDynamic      #36:#540      // #36:accept:()Ljava/util/function/Consumer;
  #586 = NameAndType        #27:#20       // bow:Lnet/minecraftforge/registries/RegistryObject;
  #587 = Fieldref           #2.#586       // com/minecolonies/api/equipment/ModEquipmentTypes.bow:Lnet/minecraftforge/registries/RegistryObject;
  #588 = Utf8               rod
  #589 = String             #588          // rod
  #590 = NameAndType        #407:#196     // lambda$static$19:(Lcom/minecolonies/api/equipment/registry/EquipmentTypeEntry$Builder;)V
  #591 = Methodref          #2.#590       // com/minecolonies/api/equipment/ModEquipmentTypes.lambda$static$19:(Lcom/minecolonies/api/equipment/registry/EquipmentTypeEntry$Builder;)V
  #592 = MethodHandle       6:#591        // REF_invokeStatic com/minecolonies/api/equipment/ModEquipmentTypes.lambda$static$19:(Lcom/minecolonies/api/equipment/registry/EquipmentTypeEntry$Builder;)V
  #593 = InvokeDynamic      #37:#540      // #37:accept:()Ljava/util/function/Consumer;
  #594 = NameAndType        #28:#20       // fishing_rod:Lnet/minecraftforge/registries/RegistryObject;
  #595 = Fieldref           #2.#594       // com/minecolonies/api/equipment/ModEquipmentTypes.fishing_rod:Lnet/minecraftforge/registries/RegistryObject;
  #596 = String             #29           // shears
  #597 = NameAndType        #388:#196     // lambda$static$22:(Lcom/minecolonies/api/equipment/registry/EquipmentTypeEntry$Builder;)V
  #598 = Methodref          #2.#597       // com/minecolonies/api/equipment/ModEquipmentTypes.lambda$static$22:(Lcom/minecolonies/api/equipment/registry/EquipmentTypeEntry$Builder;)V
  #599 = MethodHandle       6:#598        // REF_invokeStatic com/minecolonies/api/equipment/ModEquipmentTypes.lambda$static$22:(Lcom/minecolonies/api/equipment/registry/EquipmentTypeEntry$Builder;)V
  #600 = InvokeDynamic      #38:#540      // #38:accept:()Ljava/util/function/Consumer;
  #601 = NameAndType        #29:#20       // shears:Lnet/minecraftforge/registries/RegistryObject;
  #602 = Fieldref           #2.#601       // com/minecolonies/api/equipment/ModEquipmentTypes.shears:Lnet/minecraftforge/registries/RegistryObject;
  #603 = String             #30           // shield
  #604 = NameAndType        #365:#196     // lambda$static$25:(Lcom/minecolonies/api/equipment/registry/EquipmentTypeEntry$Builder;)V
  #605 = Methodref          #2.#604       // com/minecolonies/api/equipment/ModEquipmentTypes.lambda$static$25:(Lcom/minecolonies/api/equipment/registry/EquipmentTypeEntry$Builder;)V
  #606 = MethodHandle       6:#605        // REF_invokeStatic com/minecolonies/api/equipment/ModEquipmentTypes.lambda$static$25:(Lcom/minecolonies/api/equipment/registry/EquipmentTypeEntry$Builder;)V
  #607 = InvokeDynamic      #39:#540      // #39:accept:()Ljava/util/function/Consumer;
  #608 = NameAndType        #30:#20       // shield:Lnet/minecraftforge/registries/RegistryObject;
  #609 = Fieldref           #2.#608       // com/minecolonies/api/equipment/ModEquipmentTypes.shield:Lnet/minecraftforge/registries/RegistryObject;
  #610 = String             #31           // helmet
  #611 = NameAndType        #348:#196     // lambda$static$28:(Lcom/minecolonies/api/equipment/registry/EquipmentTypeEntry$Builder;)V
  #612 = Methodref          #2.#611       // com/minecolonies/api/equipment/ModEquipmentTypes.lambda$static$28:(Lcom/minecolonies/api/equipment/registry/EquipmentTypeEntry$Builder;)V
  #613 = MethodHandle       6:#612        // REF_invokeStatic com/minecolonies/api/equipment/ModEquipmentTypes.lambda$static$28:(Lcom/minecolonies/api/equipment/registry/EquipmentTypeEntry$Builder;)V
  #614 = InvokeDynamic      #40:#540      // #40:accept:()Ljava/util/function/Consumer;
  #615 = NameAndType        #31:#20       // helmet:Lnet/minecraftforge/registries/RegistryObject;
  #616 = Fieldref           #2.#615       // com/minecolonies/api/equipment/ModEquipmentTypes.helmet:Lnet/minecraftforge/registries/RegistryObject;
  #617 = String             #32           // leggings
  #618 = NameAndType        #331:#196     // lambda$static$31:(Lcom/minecolonies/api/equipment/registry/EquipmentTypeEntry$Builder;)V
  #619 = Methodref          #2.#618       // com/minecolonies/api/equipment/ModEquipmentTypes.lambda$static$31:(Lcom/minecolonies/api/equipment/registry/EquipmentTypeEntry$Builder;)V
  #620 = MethodHandle       6:#619        // REF_invokeStatic com/minecolonies/api/equipment/ModEquipmentTypes.lambda$static$31:(Lcom/minecolonies/api/equipment/registry/EquipmentTypeEntry$Builder;)V
  #621 = InvokeDynamic      #41:#540      // #41:accept:()Ljava/util/function/Consumer;
  #622 = NameAndType        #32:#20       // leggings:Lnet/minecraftforge/registries/RegistryObject;
  #623 = Fieldref           #2.#622       // com/minecolonies/api/equipment/ModEquipmentTypes.leggings:Lnet/minecraftforge/registries/RegistryObject;
  #624 = String             #33           // chestplate
  #625 = NameAndType        #314:#196     // lambda$static$34:(Lcom/minecolonies/api/equipment/registry/EquipmentTypeEntry$Builder;)V
  #626 = Methodref          #2.#625       // com/minecolonies/api/equipment/ModEquipmentTypes.lambda$static$34:(Lcom/minecolonies/api/equipment/registry/EquipmentTypeEntry$Builder;)V
  #627 = MethodHandle       6:#626        // REF_invokeStatic com/minecolonies/api/equipment/ModEquipmentTypes.lambda$static$34:(Lcom/minecolonies/api/equipment/registry/EquipmentTypeEntry$Builder;)V
  #628 = InvokeDynamic      #42:#540      // #42:accept:()Ljava/util/function/Consumer;
  #629 = NameAndType        #33:#20       // chestplate:Lnet/minecraftforge/registries/RegistryObject;
  #630 = Fieldref           #2.#629       // com/minecolonies/api/equipment/ModEquipmentTypes.chestplate:Lnet/minecraftforge/registries/RegistryObject;
  #631 = String             #34           // boots
  #632 = NameAndType        #277:#196     // lambda$static$37:(Lcom/minecolonies/api/equipment/registry/EquipmentTypeEntry$Builder;)V
  #633 = Methodref          #2.#632       // com/minecolonies/api/equipment/ModEquipmentTypes.lambda$static$37:(Lcom/minecolonies/api/equipment/registry/EquipmentTypeEntry$Builder;)V
  #634 = MethodHandle       6:#633        // REF_invokeStatic com/minecolonies/api/equipment/ModEquipmentTypes.lambda$static$37:(Lcom/minecolonies/api/equipment/registry/EquipmentTypeEntry$Builder;)V
  #635 = InvokeDynamic      #43:#540      // #43:accept:()Ljava/util/function/Consumer;
  #636 = NameAndType        #34:#20       // boots:Lnet/minecraftforge/registries/RegistryObject;
  #637 = Fieldref           #2.#636       // com/minecolonies/api/equipment/ModEquipmentTypes.boots:Lnet/minecraftforge/registries/RegistryObject;
  #638 = Utf8               flintandsteel
  #639 = String             #638          // flintandsteel
  #640 = NameAndType        #249:#196     // lambda$static$40:(Lcom/minecolonies/api/equipment/registry/EquipmentTypeEntry$Builder;)V
  #641 = Methodref          #2.#640       // com/minecolonies/api/equipment/ModEquipmentTypes.lambda$static$40:(Lcom/minecolonies/api/equipment/registry/EquipmentTypeEntry$Builder;)V
  #642 = MethodHandle       6:#641        // REF_invokeStatic com/minecolonies/api/equipment/ModEquipmentTypes.lambda$static$40:(Lcom/minecolonies/api/equipment/registry/EquipmentTypeEntry$Builder;)V
  #643 = InvokeDynamic      #44:#540      // #44:accept:()Ljava/util/function/Consumer;
  #644 = NameAndType        #35:#20       // flint_and_steel:Lnet/minecraftforge/registries/RegistryObject;
  #645 = Fieldref           #2.#644       // com/minecolonies/api/equipment/ModEquipmentTypes.flint_and_steel:Lnet/minecraftforge/registries/RegistryObject;
  #646 = String             #36           // lead
  #647 = NameAndType        #195:#196     // lambda$static$43:(Lcom/minecolonies/api/equipment/registry/EquipmentTypeEntry$Builder;)V
  #648 = Methodref          #2.#647       // com/minecolonies/api/equipment/ModEquipmentTypes.lambda$static$43:(Lcom/minecolonies/api/equipment/registry/EquipmentTypeEntry$Builder;)V
  #649 = MethodHandle       6:#648        // REF_invokeStatic com/minecolonies/api/equipment/ModEquipmentTypes.lambda$static$43:(Lcom/minecolonies/api/equipment/registry/EquipmentTypeEntry$Builder;)V
  #650 = InvokeDynamic      #45:#540      // #45:accept:()Ljava/util/function/Consumer;
  #651 = NameAndType        #36:#20       // lead:Lnet/minecraftforge/registries/RegistryObject;
  #652 = Fieldref           #2.#651       // com/minecolonies/api/equipment/ModEquipmentTypes.lead:Lnet/minecraftforge/registries/RegistryObject;
  #653 = Utf8               Signature
  #654 = Utf8               Code
  #655 = Utf8               LineNumberTable
  #656 = Utf8               LocalVariableTable
  #657 = Utf8               LocalVariableTypeTable
  #658 = Utf8               StackMapTable
  #659 = Utf8               InnerClasses
  #660 = Utf8               SourceFile
  #661 = Utf8               BootstrapMethods
{
  public static final net.minecraftforge.registries.DeferredRegister<com.minecolonies.api.equipment.registry.EquipmentTypeEntry> DEFERRED_REGISTER;
    descriptor: Lnet/minecraftforge/registries/DeferredRegister;
    flags: (0x0019) ACC_PUBLIC, ACC_STATIC, ACC_FINAL
    Signature: #18                          // Lnet/minecraftforge/registries/DeferredRegister<Lcom/minecolonies/api/equipment/registry/EquipmentTypeEntry;>;

  public static final net.minecraftforge.registries.RegistryObject<com.minecolonies.api.equipment.registry.EquipmentTypeEntry> none;
    descriptor: Lnet/minecraftforge/registries/RegistryObject;
    flags: (0x0019) ACC_PUBLIC, ACC_STATIC, ACC_FINAL
    Signature: #21                          // Lnet/minecraftforge/registries/RegistryObject<Lcom/minecolonies/api/equipment/registry/EquipmentTypeEntry;>;

  public static final net.minecraftforge.registries.RegistryObject<com.minecolonies.api.equipment.registry.EquipmentTypeEntry> pickaxe;
    descriptor: Lnet/minecraftforge/registries/RegistryObject;
    flags: (0x0019) ACC_PUBLIC, ACC_STATIC, ACC_FINAL
    Signature: #21                          // Lnet/minecraftforge/registries/RegistryObject<Lcom/minecolonies/api/equipment/registry/EquipmentTypeEntry;>;

  public static final net.minecraftforge.registries.RegistryObject<com.minecolonies.api.equipment.registry.EquipmentTypeEntry> shovel;
    descriptor: Lnet/minecraftforge/registries/RegistryObject;
    flags: (0x0019) ACC_PUBLIC, ACC_STATIC, ACC_FINAL
    Signature: #21                          // Lnet/minecraftforge/registries/RegistryObject<Lcom/minecolonies/api/equipment/registry/EquipmentTypeEntry;>;

  public static final net.minecraftforge.registries.RegistryObject<com.minecolonies.api.equipment.registry.EquipmentTypeEntry> axe;
    descriptor: Lnet/minecraftforge/registries/RegistryObject;
    flags: (0x0019) ACC_PUBLIC, ACC_STATIC, ACC_FINAL
    Signature: #21                          // Lnet/minecraftforge/registries/RegistryObject<Lcom/minecolonies/api/equipment/registry/EquipmentTypeEntry;>;

  public static final net.minecraftforge.registries.RegistryObject<com.minecolonies.api.equipment.registry.EquipmentTypeEntry> hoe;
    descriptor: Lnet/minecraftforge/registries/RegistryObject;
    flags: (0x0019) ACC_PUBLIC, ACC_STATIC, ACC_FINAL
    Signature: #21                          // Lnet/minecraftforge/registries/RegistryObject<Lcom/minecolonies/api/equipment/registry/EquipmentTypeEntry;>;

  public static final net.minecraftforge.registries.RegistryObject<com.minecolonies.api.equipment.registry.EquipmentTypeEntry> sword;
    descriptor: Lnet/minecraftforge/registries/RegistryObject;
    flags: (0x0019) ACC_PUBLIC, ACC_STATIC, ACC_FINAL
    Signature: #21                          // Lnet/minecraftforge/registries/RegistryObject<Lcom/minecolonies/api/equipment/registry/EquipmentTypeEntry;>;

  public static final net.minecraftforge.registries.RegistryObject<com.minecolonies.api.equipment.registry.EquipmentTypeEntry> bow;
    descriptor: Lnet/minecraftforge/registries/RegistryObject;
    flags: (0x0019) ACC_PUBLIC, ACC_STATIC, ACC_FINAL
    Signature: #21                          // Lnet/minecraftforge/registries/RegistryObject<Lcom/minecolonies/api/equipment/registry/EquipmentTypeEntry;>;

  public static final net.minecraftforge.registries.RegistryObject<com.minecolonies.api.equipment.registry.EquipmentTypeEntry> fishing_rod;
    descriptor: Lnet/minecraftforge/registries/RegistryObject;
    flags: (0x0019) ACC_PUBLIC, ACC_STATIC, ACC_FINAL
    Signature: #21                          // Lnet/minecraftforge/registries/RegistryObject<Lcom/minecolonies/api/equipment/registry/EquipmentTypeEntry;>;

  public static final net.minecraftforge.registries.RegistryObject<com.minecolonies.api.equipment.registry.EquipmentTypeEntry> shears;
    descriptor: Lnet/minecraftforge/registries/RegistryObject;
    flags: (0x0019) ACC_PUBLIC, ACC_STATIC, ACC_FINAL
    Signature: #21                          // Lnet/minecraftforge/registries/RegistryObject<Lcom/minecolonies/api/equipment/registry/EquipmentTypeEntry;>;

  public static final net.minecraftforge.registries.RegistryObject<com.minecolonies.api.equipment.registry.EquipmentTypeEntry> shield;
    descriptor: Lnet/minecraftforge/registries/RegistryObject;
    flags: (0x0019) ACC_PUBLIC, ACC_STATIC, ACC_FINAL
    Signature: #21                          // Lnet/minecraftforge/registries/RegistryObject<Lcom/minecolonies/api/equipment/registry/EquipmentTypeEntry;>;

  public static final net.minecraftforge.registries.RegistryObject<com.minecolonies.api.equipment.registry.EquipmentTypeEntry> helmet;
    descriptor: Lnet/minecraftforge/registries/RegistryObject;
    flags: (0x0019) ACC_PUBLIC, ACC_STATIC, ACC_FINAL
    Signature: #21                          // Lnet/minecraftforge/registries/RegistryObject<Lcom/minecolonies/api/equipment/registry/EquipmentTypeEntry;>;

  public static final net.minecraftforge.registries.RegistryObject<com.minecolonies.api.equipment.registry.EquipmentTypeEntry> leggings;
    descriptor: Lnet/minecraftforge/registries/RegistryObject;
    flags: (0x0019) ACC_PUBLIC, ACC_STATIC, ACC_FINAL
    Signature: #21                          // Lnet/minecraftforge/registries/RegistryObject<Lcom/minecolonies/api/equipment/registry/EquipmentTypeEntry;>;

  public static final net.minecraftforge.registries.RegistryObject<com.minecolonies.api.equipment.registry.EquipmentTypeEntry> chestplate;
    descriptor: Lnet/minecraftforge/registries/RegistryObject;
    flags: (0x0019) ACC_PUBLIC, ACC_STATIC, ACC_FINAL
    Signature: #21                          // Lnet/minecraftforge/registries/RegistryObject<Lcom/minecolonies/api/equipment/registry/EquipmentTypeEntry;>;

  public static final net.minecraftforge.registries.RegistryObject<com.minecolonies.api.equipment.registry.EquipmentTypeEntry> boots;
    descriptor: Lnet/minecraftforge/registries/RegistryObject;
    flags: (0x0019) ACC_PUBLIC, ACC_STATIC, ACC_FINAL
    Signature: #21                          // Lnet/minecraftforge/registries/RegistryObject<Lcom/minecolonies/api/equipment/registry/EquipmentTypeEntry;>;

  public static final net.minecraftforge.registries.RegistryObject<com.minecolonies.api.equipment.registry.EquipmentTypeEntry> flint_and_steel;
    descriptor: Lnet/minecraftforge/registries/RegistryObject;
    flags: (0x0019) ACC_PUBLIC, ACC_STATIC, ACC_FINAL
    Signature: #21                          // Lnet/minecraftforge/registries/RegistryObject<Lcom/minecolonies/api/equipment/registry/EquipmentTypeEntry;>;

  public static final net.minecraftforge.registries.RegistryObject<com.minecolonies.api.equipment.registry.EquipmentTypeEntry> lead;
    descriptor: Lnet/minecraftforge/registries/RegistryObject;
    flags: (0x0019) ACC_PUBLIC, ACC_STATIC, ACC_FINAL
    Signature: #21                          // Lnet/minecraftforge/registries/RegistryObject<Lcom/minecolonies/api/equipment/registry/EquipmentTypeEntry;>;

  public com.minecolonies.api.equipment.ModEquipmentTypes();
    descriptor: ()V
    flags: (0x0001) ACC_PUBLIC
    Code:
      stack=1, locals=1, args_size=1
         0: aload_0
         1: invokespecial #40                 // Method java/lang/Object."<init>":()V
         4: return
      LineNumberTable:
        line 25: 0
      LocalVariableTable:
        Start  Length  Slot  Name   Signature
            0       5     0  this   Lcom/minecolonies/api/equipment/ModEquipmentTypes;

  public static net.minecraftforge.registries.IForgeRegistry<com.minecolonies.api.equipment.registry.EquipmentTypeEntry> getRegistry();
    descriptor: ()Lnet/minecraftforge/registries/IForgeRegistry;
    flags: (0x0009) ACC_PUBLIC, ACC_STATIC
    Code:
      stack=1, locals=0, args_size=0
         0: invokestatic  #51                 // InterfaceMethod com/minecolonies/api/IMinecoloniesAPI.getInstance:()Lcom/minecolonies/api/IMinecoloniesAPI;
         3: invokeinterface #54,  1           // InterfaceMethod com/minecolonies/api/IMinecoloniesAPI.getEquipmentTypeRegistry:()Lnet/minecraftforge/registries/IForgeRegistry;
         8: areturn
      LineNumberTable:
        line 171: 0
    Signature: #45                          // ()Lnet/minecraftforge/registries/IForgeRegistry<Lcom/minecolonies/api/equipment/registry/EquipmentTypeEntry;>;

  private static net.minecraftforge.registries.RegistryObject<com.minecolonies.api.equipment.registry.EquipmentTypeEntry> register(java.lang.String, java.util.function.Consumer<com.minecolonies.api.equipment.registry.EquipmentTypeEntry$Builder>);
    descriptor: (Ljava/lang/String;Ljava/util/function/Consumer;)Lnet/minecraftforge/registries/RegistryObject;
    flags: (0x000a) ACC_PRIVATE, ACC_STATIC
    Code:
      stack=5, locals=3, args_size=2
         0: new           #7                  // class com/minecolonies/api/equipment/registry/EquipmentTypeEntry$Builder
         3: dup
         4: invokespecial #58                 // Method com/minecolonies/api/equipment/registry/EquipmentTypeEntry$Builder."<init>":()V
         7: new           #60                 // class net/minecraft/resources/ResourceLocation
        10: dup
        11: ldc           #62                 // String minecolonies
        13: aload_0
        14: invokespecial #65                 // Method net/minecraft/resources/ResourceLocation."<init>":(Ljava/lang/String;Ljava/lang/String;)V
        17: invokevirtual #69                 // Method com/minecolonies/api/equipment/registry/EquipmentTypeEntry$Builder.setRegistryName:(Lnet/minecraft/resources/ResourceLocation;)Lcom/minecolonies/api/equipment/registry/EquipmentTypeEntry$Builder;
        20: astore_2
        21: aload_1
        22: aload_2
        23: invokeinterface #75,  2           // InterfaceMethod java/util/function/Consumer.accept:(Ljava/lang/Object;)V
        28: getstatic     #77                 // Field DEFERRED_REGISTER:Lnet/minecraftforge/registries/DeferredRegister;
        31: aload_0
        32: aload_2
        33: dup
        34: invokestatic  #83                 // Method java/util/Objects.requireNonNull:(Ljava/lang/Object;)Ljava/lang/Object;
        37: pop
        38: invokedynamic #102,  0            // InvokeDynamic #0:get:(Lcom/minecolonies/api/equipment/registry/EquipmentTypeEntry$Builder;)Ljava/util/function/Supplier;
        43: invokevirtual #107                // Method net/minecraftforge/registries/DeferredRegister.register:(Ljava/lang/String;Ljava/util/function/Supplier;)Lnet/minecraftforge/registries/RegistryObject;
        46: areturn
      LineNumberTable:
        line 183: 0
        line 184: 17
        line 185: 21
        line 186: 28
      LocalVariableTable:
        Start  Length  Slot  Name   Signature
            0      47     0    id   Ljava/lang/String;
            0      47     1 consumer   Ljava/util/function/Consumer;
           21      26     2 equipmentType   Lcom/minecolonies/api/equipment/registry/EquipmentTypeEntry$Builder;
      LocalVariableTypeTable:
        Start  Length  Slot  Name   Signature
            0      47     1 consumer   Ljava/util/function/Consumer<Lcom/minecolonies/api/equipment/registry/EquipmentTypeEntry$Builder;>;
    Signature: #57                          // (Ljava/lang/String;Ljava/util/function/Consumer<Lcom/minecolonies/api/equipment/registry/EquipmentTypeEntry$Builder;>;)Lnet/minecraftforge/registries/RegistryObject<Lcom/minecolonies/api/equipment/registry/EquipmentTypeEntry;>;

  public static int vanillaToolLevel(net.minecraft.world.item.ItemStack, com.minecolonies.api.equipment.registry.EquipmentTypeEntry);
    descriptor: (Lnet/minecraft/world/item/ItemStack;Lcom/minecolonies/api/equipment/registry/EquipmentTypeEntry;)I
    flags: (0x0009) ACC_PUBLIC, ACC_STATIC
    Code:
      stack=2, locals=4, args_size=2
         0: aload_0
         1: aload_1
         2: invokestatic  #122                // Method com/minecolonies/api/compatibility/Compatibility.isTinkersTool:(Lnet/minecraft/world/item/ItemStack;Lcom/minecolonies/api/equipment/registry/EquipmentTypeEntry;)Z
         5: ifeq          13
         8: aload_0
         9: invokestatic  #126                // Method com/minecolonies/api/compatibility/Compatibility.getToolLevel:(Lnet/minecraft/world/item/ItemStack;)I
        12: ireturn
        13: aload_0
        14: invokevirtual #132                // Method net/minecraft/world/item/ItemStack.m_41720_:()Lnet/minecraft/world/item/Item;
        17: astore_3
        18: aload_3
        19: instanceof    #134                // class net/minecraft/world/item/TieredItem
        22: ifeq          40
        25: aload_3
        26: checkcast     #134                // class net/minecraft/world/item/TieredItem
        29: astore_2
        30: aload_2
        31: invokevirtual #138                // Method net/minecraft/world/item/TieredItem.m_43314_:()Lnet/minecraft/world/item/Tier;
        34: invokeinterface #144,  1          // InterfaceMethod net/minecraft/world/item/Tier.m_6604_:()I
        39: ireturn
        40: iconst_m1
        41: ireturn
      StackMapTable: number_of_entries = 2
        frame_type = 13 /* same */
        frame_type = 26 /* same */
      LineNumberTable:
        line 198: 0
        line 200: 8
        line 202: 13
        line 204: 30
        line 206: 40
      LocalVariableTable:
        Start  Length  Slot  Name   Signature
           30      10     2 tieredItem   Lnet/minecraft/world/item/TieredItem;
            0      42     0 itemStack   Lnet/minecraft/world/item/ItemStack;
            0      42     1 equipmentType   Lcom/minecolonies/api/equipment/registry/EquipmentTypeEntry;

  public static int durabilityBasedLevel(net.minecraft.world.item.ItemStack, int);
    descriptor: (Lnet/minecraft/world/item/ItemStack;I)I
    flags: (0x0009) ACC_PUBLIC, ACC_STATIC
    Code:
      stack=2, locals=2, args_size=2
         0: aload_0
         1: invokevirtual #155                // Method net/minecraft/world/item/ItemStack.m_41763_:()Z
         4: ifne          9
         7: iconst_5
         8: ireturn
         9: aload_0
        10: invokevirtual #158                // Method net/minecraft/world/item/ItemStack.m_41776_:()I
        13: iload_1
        14: idiv
        15: iconst_5
        16: invokestatic  #164                // Method java/lang/Math.min:(II)I
        19: ireturn
      StackMapTable: number_of_entries = 1
        frame_type = 9 /* same */
      LineNumberTable:
        line 217: 0
        line 219: 7
        line 222: 9
      LocalVariableTable:
        Start  Length  Slot  Name   Signature
            0      20     0 itemStack   Lnet/minecraft/world/item/ItemStack;
            0      20     1 vanillaItemDurability   I

  public static boolean canPerformDefaultActions(net.minecraft.world.item.ItemStack, java.util.Set<net.minecraftforge.common.ToolAction>);
    descriptor: (Lnet/minecraft/world/item/ItemStack;Ljava/util/Set;)Z
    flags: (0x0009) ACC_PUBLIC, ACC_STATIC
    Code:
      stack=2, locals=4, args_size=2
         0: aload_1
         1: invokeinterface #175,  1          // InterfaceMethod java/util/Set.iterator:()Ljava/util/Iterator;
         6: astore_2
         7: aload_2
         8: invokeinterface #180,  1          // InterfaceMethod java/util/Iterator.hasNext:()Z
        13: ifeq          39
        16: aload_2
        17: invokeinterface #183,  1          // InterfaceMethod java/util/Iterator.next:()Ljava/lang/Object;
        22: checkcast     #185                // class net/minecraftforge/common/ToolAction
        25: astore_3
        26: aload_0
        27: aload_3
        28: invokevirtual #189                // Method net/minecraft/world/item/ItemStack.canPerformAction:(Lnet/minecraftforge/common/ToolAction;)Z
        31: ifne          36
        34: iconst_0
        35: ireturn
        36: goto          7
        39: iconst_1
        40: ireturn
      StackMapTable: number_of_entries = 3
        frame_type = 252 /* append */
          offset_delta = 7
          locals = [ class java/util/Iterator ]
        frame_type = 28 /* same */
        frame_type = 250 /* chop */
          offset_delta = 2
      LineNumberTable:
        line 234: 0
        line 236: 26
        line 238: 34
        line 240: 36
        line 241: 39
      LocalVariableTable:
        Start  Length  Slot  Name   Signature
           26      10     3 toolAction   Lnet/minecraftforge/common/ToolAction;
            0      41     0 itemStack   Lnet/minecraft/world/item/ItemStack;
            0      41     1 actions   Ljava/util/Set;
      LocalVariableTypeTable:
        Start  Length  Slot  Name   Signature
            0      41     1 actions   Ljava/util/Set<Lnet/minecraftforge/common/ToolAction;>;
    Signature: #169                         // (Lnet/minecraft/world/item/ItemStack;Ljava/util/Set<Lnet/minecraftforge/common/ToolAction;>;)Z

  private static void lambda$static$43(com.minecolonies.api.equipment.registry.EquipmentTypeEntry$Builder);
    descriptor: (Lcom/minecolonies/api/equipment/registry/EquipmentTypeEntry$Builder;)V
    flags: (0x100a) ACC_PRIVATE, ACC_STATIC, ACC_SYNTHETIC
    Code:
      stack=2, locals=1, args_size=1
         0: aload_0
         1: ldc           #198                // String com.minecolonies.coremod.tooltype.lead
         3: invokestatic  #204                // InterfaceMethod net/minecraft/network/chat/Component.m_237115_:(Ljava/lang/String;)Lnet/minecraft/network/chat/MutableComponent;
         6: invokevirtual #208                // Method com/minecolonies/api/equipment/registry/EquipmentTypeEntry$Builder.setDisplayName:(Lnet/minecraft/network/chat/Component;)Lcom/minecolonies/api/equipment/registry/EquipmentTypeEntry$Builder;
         9: invokedynamic #219,  0            // InvokeDynamic #1:test:()Ljava/util/function/BiPredicate;
        14: invokevirtual #223                // Method com/minecolonies/api/equipment/registry/EquipmentTypeEntry$Builder.setIsEquipment:(Ljava/util/function/BiPredicate;)Lcom/minecolonies/api/equipment/registry/EquipmentTypeEntry$Builder;
        17: invokedynamic #235,  0            // InvokeDynamic #2:apply:()Ljava/util/function/BiFunction;
        22: invokevirtual #239                // Method com/minecolonies/api/equipment/registry/EquipmentTypeEntry$Builder.setEquipmentLevel:(Ljava/util/function/BiFunction;)Lcom/minecolonies/api/equipment/registry/EquipmentTypeEntry$Builder;
        25: invokevirtual #89                 // Method com/minecolonies/api/equipment/registry/EquipmentTypeEntry$Builder.build:()Lcom/minecolonies/api/equipment/registry/EquipmentTypeEntry;
        28: pop
        29: return
      LineNumberTable:
        line 157: 0
        line 158: 14
        line 159: 22
        line 160: 25
        line 157: 29
      LocalVariableTable:
        Start  Length  Slot  Name   Signature
            0      30     0 builder   Lcom/minecolonies/api/equipment/registry/EquipmentTypeEntry$Builder;

  private static java.lang.Integer lambda$static$42(net.minecraft.world.item.ItemStack, com.minecolonies.api.equipment.registry.EquipmentTypeEntry);
    descriptor: (Lnet/minecraft/world/item/ItemStack;Lcom/minecolonies/api/equipment/registry/EquipmentTypeEntry;)Ljava/lang/Integer;
    flags: (0x100a) ACC_PRIVATE, ACC_STATIC, ACC_SYNTHETIC
    Code:
      stack=1, locals=2, args_size=2
         0: iconst_m1
         1: invokestatic  #246                // Method java/lang/Integer.valueOf:(I)Ljava/lang/Integer;
         4: areturn
      LineNumberTable:
        line 159: 0
      LocalVariableTable:
        Start  Length  Slot  Name   Signature
            0       5     0 itemStack   Lnet/minecraft/world/item/ItemStack;
            0       5     1 equipmentType   Lcom/minecolonies/api/equipment/registry/EquipmentTypeEntry;

  private static boolean lambda$static$41(net.minecraft.world.item.ItemStack, com.minecolonies.api.equipment.registry.EquipmentTypeEntry);
    descriptor: (Lnet/minecraft/world/item/ItemStack;Lcom/minecolonies/api/equipment/registry/EquipmentTypeEntry;)Z
    flags: (0x100a) ACC_PRIVATE, ACC_STATIC, ACC_SYNTHETIC
    Code:
      stack=1, locals=2, args_size=2
         0: aload_0
         1: invokevirtual #132                // Method net/minecraft/world/item/ItemStack.m_41720_:()Lnet/minecraft/world/item/Item;
         4: instanceof    #248                // class net/minecraft/world/item/LeadItem
         7: ireturn
      LineNumberTable:
        line 158: 0
      LocalVariableTable:
        Start  Length  Slot  Name   Signature
            0       8     0 itemStack   Lnet/minecraft/world/item/ItemStack;
            0       8     1 equipmentType   Lcom/minecolonies/api/equipment/registry/EquipmentTypeEntry;

  private static void lambda$static$40(com.minecolonies.api.equipment.registry.EquipmentTypeEntry$Builder);
    descriptor: (Lcom/minecolonies/api/equipment/registry/EquipmentTypeEntry$Builder;)V
    flags: (0x100a) ACC_PRIVATE, ACC_STATIC, ACC_SYNTHETIC
    Code:
      stack=2, locals=1, args_size=1
         0: aload_0
         1: ldc           #251                // String com.minecolonies.coremod.tooltype.lighter
         3: invokestatic  #204                // InterfaceMethod net/minecraft/network/chat/Component.m_237115_:(Ljava/lang/String;)Lnet/minecraft/network/chat/MutableComponent;
         6: invokevirtual #208                // Method com/minecolonies/api/equipment/registry/EquipmentTypeEntry$Builder.setDisplayName:(Lnet/minecraft/network/chat/Component;)Lcom/minecolonies/api/equipment/registry/EquipmentTypeEntry$Builder;
         9: invokedynamic #256,  0            // InvokeDynamic #3:test:()Ljava/util/function/BiPredicate;
        14: invokevirtual #223                // Method com/minecolonies/api/equipment/registry/EquipmentTypeEntry$Builder.setIsEquipment:(Ljava/util/function/BiPredicate;)Lcom/minecolonies/api/equipment/registry/EquipmentTypeEntry$Builder;
        17: invokedynamic #261,  0            // InvokeDynamic #4:apply:()Ljava/util/function/BiFunction;
        22: invokevirtual #239                // Method com/minecolonies/api/equipment/registry/EquipmentTypeEntry$Builder.setEquipmentLevel:(Ljava/util/function/BiFunction;)Lcom/minecolonies/api/equipment/registry/EquipmentTypeEntry$Builder;
        25: invokevirtual #89                 // Method com/minecolonies/api/equipment/registry/EquipmentTypeEntry$Builder.build:()Lcom/minecolonies/api/equipment/registry/EquipmentTypeEntry;
        28: pop
        29: return
      LineNumberTable:
        line 151: 0
        line 152: 14
        line 153: 22
        line 154: 25
        line 151: 29
      LocalVariableTable:
        Start  Length  Slot  Name   Signature
            0      30     0 builder   Lcom/minecolonies/api/equipment/registry/EquipmentTypeEntry$Builder;

  private static java.lang.Integer lambda$static$39(net.minecraft.world.item.ItemStack, com.minecolonies.api.equipment.registry.EquipmentTypeEntry);
    descriptor: (Lnet/minecraft/world/item/ItemStack;Lcom/minecolonies/api/equipment/registry/EquipmentTypeEntry;)Ljava/lang/Integer;
    flags: (0x100a) ACC_PRIVATE, ACC_STATIC, ACC_SYNTHETIC
    Code:
      stack=2, locals=2, args_size=2
         0: aload_0
         1: getstatic     #267                // Field net/minecraft/world/item/Items.f_42409_:Lnet/minecraft/world/item/Item;
         4: invokevirtual #272                // Method net/minecraft/world/item/Item.m_41462_:()I
         7: invokestatic  #274                // Method durabilityBasedLevel:(Lnet/minecraft/world/item/ItemStack;I)I
        10: invokestatic  #246                // Method java/lang/Integer.valueOf:(I)Ljava/lang/Integer;
        13: areturn
      LineNumberTable:
        line 153: 0
      LocalVariableTable:
        Start  Length  Slot  Name   Signature
            0      14     0 itemStack   Lnet/minecraft/world/item/ItemStack;
            0      14     1 equipmentType   Lcom/minecolonies/api/equipment/registry/EquipmentTypeEntry;

  private static boolean lambda$static$38(net.minecraft.world.item.ItemStack, com.minecolonies.api.equipment.registry.EquipmentTypeEntry);
    descriptor: (Lnet/minecraft/world/item/ItemStack;Lcom/minecolonies/api/equipment/registry/EquipmentTypeEntry;)Z
    flags: (0x100a) ACC_PRIVATE, ACC_STATIC, ACC_SYNTHETIC
    Code:
      stack=1, locals=2, args_size=2
         0: aload_0
         1: invokevirtual #132                // Method net/minecraft/world/item/ItemStack.m_41720_:()Lnet/minecraft/world/item/Item;
         4: instanceof    #276                // class net/minecraft/world/item/FlintAndSteelItem
         7: ireturn
      LineNumberTable:
        line 152: 0
      LocalVariableTable:
        Start  Length  Slot  Name   Signature
            0       8     0 itemStack   Lnet/minecraft/world/item/ItemStack;
            0       8     1 equipmentType   Lcom/minecolonies/api/equipment/registry/EquipmentTypeEntry;

  private static void lambda$static$37(com.minecolonies.api.equipment.registry.EquipmentTypeEntry$Builder);
    descriptor: (Lcom/minecolonies/api/equipment/registry/EquipmentTypeEntry$Builder;)V
    flags: (0x100a) ACC_PRIVATE, ACC_STATIC, ACC_SYNTHETIC
    Code:
      stack=2, locals=1, args_size=1
         0: aload_0
         1: ldc_w         #279                // String com.minecolonies.coremod.tooltype.boots
         4: invokestatic  #204                // InterfaceMethod net/minecraft/network/chat/Component.m_237115_:(Ljava/lang/String;)Lnet/minecraft/network/chat/MutableComponent;
         7: invokevirtual #208                // Method com/minecolonies/api/equipment/registry/EquipmentTypeEntry$Builder.setDisplayName:(Lnet/minecraft/network/chat/Component;)Lcom/minecolonies/api/equipment/registry/EquipmentTypeEntry$Builder;
        10: invokedynamic #284,  0            // InvokeDynamic #5:test:()Ljava/util/function/BiPredicate;
        15: invokevirtual #223                // Method com/minecolonies/api/equipment/registry/EquipmentTypeEntry$Builder.setIsEquipment:(Ljava/util/function/BiPredicate;)Lcom/minecolonies/api/equipment/registry/EquipmentTypeEntry$Builder;
        18: invokedynamic #289,  0            // InvokeDynamic #6:apply:()Ljava/util/function/BiFunction;
        23: invokevirtual #239                // Method com/minecolonies/api/equipment/registry/EquipmentTypeEntry$Builder.setEquipmentLevel:(Ljava/util/function/BiFunction;)Lcom/minecolonies/api/equipment/registry/EquipmentTypeEntry$Builder;
        26: invokevirtual #89                 // Method com/minecolonies/api/equipment/registry/EquipmentTypeEntry$Builder.build:()Lcom/minecolonies/api/equipment/registry/EquipmentTypeEntry;
        29: pop
        30: return
      LineNumberTable:
        line 145: 0
        line 146: 15
        line 147: 23
        line 148: 26
        line 145: 30
      LocalVariableTable:
        Start  Length  Slot  Name   Signature
            0      31     0 builder   Lcom/minecolonies/api/equipment/registry/EquipmentTypeEntry$Builder;

  private static java.lang.Integer lambda$static$36(net.minecraft.world.item.ItemStack, com.minecolonies.api.equipment.registry.EquipmentTypeEntry);
    descriptor: (Lnet/minecraft/world/item/ItemStack;Lcom/minecolonies/api/equipment/registry/EquipmentTypeEntry;)Ljava/lang/Integer;
    flags: (0x100a) ACC_PRIVATE, ACC_STATIC, ACC_SYNTHETIC
    Code:
      stack=1, locals=2, args_size=2
         0: aload_0
         1: invokestatic  #294                // Method com/minecolonies/api/util/ItemStackUtils.getArmorLevel:(Lnet/minecraft/world/item/ItemStack;)I
         4: invokestatic  #246                // Method java/lang/Integer.valueOf:(I)Ljava/lang/Integer;
         7: areturn
      LineNumberTable:
        line 147: 0
      LocalVariableTable:
        Start  Length  Slot  Name   Signature
            0       8     0 itemStack   Lnet/minecraft/world/item/ItemStack;
            0       8     1 equipmentType   Lcom/minecolonies/api/equipment/registry/EquipmentTypeEntry;

  private static boolean lambda$static$35(net.minecraft.world.item.ItemStack, com.minecolonies.api.equipment.registry.EquipmentTypeEntry);
    descriptor: (Lnet/minecraft/world/item/ItemStack;Lcom/minecolonies/api/equipment/registry/EquipmentTypeEntry;)Z
    flags: (0x100a) ACC_PRIVATE, ACC_STATIC, ACC_SYNTHETIC
    Code:
      stack=2, locals=4, args_size=2
         0: aload_0
         1: invokevirtual #132                // Method net/minecraft/world/item/ItemStack.m_41720_:()Lnet/minecraft/world/item/Item;
         4: astore_3
         5: aload_3
         6: instanceof    #296                // class net/minecraft/world/item/ArmorItem
         9: ifeq          34
        12: aload_3
        13: checkcast     #296                // class net/minecraft/world/item/ArmorItem
        16: astore_2
        17: getstatic     #302                // Field net/minecraft/world/entity/EquipmentSlot.FEET:Lnet/minecraft/world/entity/EquipmentSlot;
        20: aload_2
        21: invokevirtual #306                // Method net/minecraft/world/item/ArmorItem.m_40402_:()Lnet/minecraft/world/entity/EquipmentSlot;
        24: invokevirtual #310                // Method net/minecraft/world/entity/EquipmentSlot.equals:(Ljava/lang/Object;)Z
        27: ifeq          34
        30: iconst_1
        31: goto          35
        34: iconst_0
        35: ireturn
      StackMapTable: number_of_entries = 2
        frame_type = 34 /* same */
        frame_type = 64 /* same_locals_1_stack_item */
          stack = [ int ]
      LineNumberTable:
        line 146: 0
      LocalVariableTable:
        Start  Length  Slot  Name   Signature
            5      12     3 patt8875$temp   Lnet/minecraft/world/item/Item;
           17      17     2 armor   Lnet/minecraft/world/item/ArmorItem;
            0      36     0 itemStack   Lnet/minecraft/world/item/ItemStack;
            0      36     1 equipmentType   Lcom/minecolonies/api/equipment/registry/EquipmentTypeEntry;

  private static void lambda$static$34(com.minecolonies.api.equipment.registry.EquipmentTypeEntry$Builder);
    descriptor: (Lcom/minecolonies/api/equipment/registry/EquipmentTypeEntry$Builder;)V
    flags: (0x100a) ACC_PRIVATE, ACC_STATIC, ACC_SYNTHETIC
    Code:
      stack=2, locals=1, args_size=1
         0: aload_0
         1: ldc_w         #316                // String com.minecolonies.coremod.tooltype.chestplate
         4: invokestatic  #204                // InterfaceMethod net/minecraft/network/chat/Component.m_237115_:(Ljava/lang/String;)Lnet/minecraft/network/chat/MutableComponent;
         7: invokevirtual #208                // Method com/minecolonies/api/equipment/registry/EquipmentTypeEntry$Builder.setDisplayName:(Lnet/minecraft/network/chat/Component;)Lcom/minecolonies/api/equipment/registry/EquipmentTypeEntry$Builder;
        10: invokedynamic #321,  0            // InvokeDynamic #7:test:()Ljava/util/function/BiPredicate;
        15: invokevirtual #223                // Method com/minecolonies/api/equipment/registry/EquipmentTypeEntry$Builder.setIsEquipment:(Ljava/util/function/BiPredicate;)Lcom/minecolonies/api/equipment/registry/EquipmentTypeEntry$Builder;
        18: invokedynamic #326,  0            // InvokeDynamic #8:apply:()Ljava/util/function/BiFunction;
        23: invokevirtual #239                // Method com/minecolonies/api/equipment/registry/EquipmentTypeEntry$Builder.setEquipmentLevel:(Ljava/util/function/BiFunction;)Lcom/minecolonies/api/equipment/registry/EquipmentTypeEntry$Builder;
        26: invokevirtual #89                 // Method com/minecolonies/api/equipment/registry/EquipmentTypeEntry$Builder.build:()Lcom/minecolonies/api/equipment/registry/EquipmentTypeEntry;
        29: pop
        30: return
      LineNumberTable:
        line 139: 0
        line 140: 15
        line 141: 23
        line 142: 26
        line 139: 30
      LocalVariableTable:
        Start  Length  Slot  Name   Signature
            0      31     0 builder   Lcom/minecolonies/api/equipment/registry/EquipmentTypeEntry$Builder;

  private static java.lang.Integer lambda$static$33(net.minecraft.world.item.ItemStack, com.minecolonies.api.equipment.registry.EquipmentTypeEntry);
    descriptor: (Lnet/minecraft/world/item/ItemStack;Lcom/minecolonies/api/equipment/registry/EquipmentTypeEntry;)Ljava/lang/Integer;
    flags: (0x100a) ACC_PRIVATE, ACC_STATIC, ACC_SYNTHETIC
    Code:
      stack=1, locals=2, args_size=2
         0: aload_0
         1: invokestatic  #294                // Method com/minecolonies/api/util/ItemStackUtils.getArmorLevel:(Lnet/minecraft/world/item/ItemStack;)I
         4: invokestatic  #246                // Method java/lang/Integer.valueOf:(I)Ljava/lang/Integer;
         7: areturn
      LineNumberTable:
        line 141: 0
      LocalVariableTable:
        Start  Length  Slot  Name   Signature
            0       8     0 itemStack   Lnet/minecraft/world/item/ItemStack;
            0       8     1 equipmentType   Lcom/minecolonies/api/equipment/registry/EquipmentTypeEntry;

  private static boolean lambda$static$32(net.minecraft.world.item.ItemStack, com.minecolonies.api.equipment.registry.EquipmentTypeEntry);
    descriptor: (Lnet/minecraft/world/item/ItemStack;Lcom/minecolonies/api/equipment/registry/EquipmentTypeEntry;)Z
    flags: (0x100a) ACC_PRIVATE, ACC_STATIC, ACC_SYNTHETIC
    Code:
      stack=2, locals=4, args_size=2
         0: aload_0
         1: invokevirtual #132                // Method net/minecraft/world/item/ItemStack.m_41720_:()Lnet/minecraft/world/item/Item;
         4: astore_3
         5: aload_3
         6: instanceof    #296                // class net/minecraft/world/item/ArmorItem
         9: ifeq          34
        12: aload_3
        13: checkcast     #296                // class net/minecraft/world/item/ArmorItem
        16: astore_2
        17: getstatic     #329                // Field net/minecraft/world/entity/EquipmentSlot.CHEST:Lnet/minecraft/world/entity/EquipmentSlot;
        20: aload_2
        21: invokevirtual #306                // Method net/minecraft/world/item/ArmorItem.m_40402_:()Lnet/minecraft/world/entity/EquipmentSlot;
        24: invokevirtual #310                // Method net/minecraft/world/entity/EquipmentSlot.equals:(Ljava/lang/Object;)Z
        27: ifeq          34
        30: iconst_1
        31: goto          35
        34: iconst_0
        35: ireturn
      StackMapTable: number_of_entries = 2
        frame_type = 34 /* same */
        frame_type = 64 /* same_locals_1_stack_item */
          stack = [ int ]
      LineNumberTable:
        line 140: 0
      LocalVariableTable:
        Start  Length  Slot  Name   Signature
            5      12     3 patt8415$temp   Lnet/minecraft/world/item/Item;
           17      17     2 armor   Lnet/minecraft/world/item/ArmorItem;
            0      36     0 itemStack   Lnet/minecraft/world/item/ItemStack;
            0      36     1 equipmentType   Lcom/minecolonies/api/equipment/registry/EquipmentTypeEntry;

  private static void lambda$static$31(com.minecolonies.api.equipment.registry.EquipmentTypeEntry$Builder);
    descriptor: (Lcom/minecolonies/api/equipment/registry/EquipmentTypeEntry$Builder;)V
    flags: (0x100a) ACC_PRIVATE, ACC_STATIC, ACC_SYNTHETIC
    Code:
      stack=2, locals=1, args_size=1
         0: aload_0
         1: ldc_w         #333                // String com.minecolonies.coremod.tooltype.leggings
         4: invokestatic  #204                // InterfaceMethod net/minecraft/network/chat/Component.m_237115_:(Ljava/lang/String;)Lnet/minecraft/network/chat/MutableComponent;
         7: invokevirtual #208                // Method com/minecolonies/api/equipment/registry/EquipmentTypeEntry$Builder.setDisplayName:(Lnet/minecraft/network/chat/Component;)Lcom/minecolonies/api/equipment/registry/EquipmentTypeEntry$Builder;
        10: invokedynamic #338,  0            // InvokeDynamic #9:test:()Ljava/util/function/BiPredicate;
        15: invokevirtual #223                // Method com/minecolonies/api/equipment/registry/EquipmentTypeEntry$Builder.setIsEquipment:(Ljava/util/function/BiPredicate;)Lcom/minecolonies/api/equipment/registry/EquipmentTypeEntry$Builder;
        18: invokedynamic #343,  0            // InvokeDynamic #10:apply:()Ljava/util/function/BiFunction;
        23: invokevirtual #239                // Method com/minecolonies/api/equipment/registry/EquipmentTypeEntry$Builder.setEquipmentLevel:(Ljava/util/function/BiFunction;)Lcom/minecolonies/api/equipment/registry/EquipmentTypeEntry$Builder;
        26: invokevirtual #89                 // Method com/minecolonies/api/equipment/registry/EquipmentTypeEntry$Builder.build:()Lcom/minecolonies/api/equipment/registry/EquipmentTypeEntry;
        29: pop
        30: return
      LineNumberTable:
        line 133: 0
        line 134: 15
        line 135: 23
        line 136: 26
        line 133: 30
      LocalVariableTable:
        Start  Length  Slot  Name   Signature
            0      31     0 builder   Lcom/minecolonies/api/equipment/registry/EquipmentTypeEntry$Builder;

  private static java.lang.Integer lambda$static$30(net.minecraft.world.item.ItemStack, com.minecolonies.api.equipment.registry.EquipmentTypeEntry);
    descriptor: (Lnet/minecraft/world/item/ItemStack;Lcom/minecolonies/api/equipment/registry/EquipmentTypeEntry;)Ljava/lang/Integer;
    flags: (0x100a) ACC_PRIVATE, ACC_STATIC, ACC_SYNTHETIC
    Code:
      stack=1, locals=2, args_size=2
         0: aload_0
         1: invokestatic  #294                // Method com/minecolonies/api/util/ItemStackUtils.getArmorLevel:(Lnet/minecraft/world/item/ItemStack;)I
         4: invokestatic  #246                // Method java/lang/Integer.valueOf:(I)Ljava/lang/Integer;
         7: areturn
      LineNumberTable:
        line 135: 0
      LocalVariableTable:
        Start  Length  Slot  Name   Signature
            0       8     0 itemStack   Lnet/minecraft/world/item/ItemStack;
            0       8     1 equipmentType   Lcom/minecolonies/api/equipment/registry/EquipmentTypeEntry;

  private static boolean lambda$static$29(net.minecraft.world.item.ItemStack, com.minecolonies.api.equipment.registry.EquipmentTypeEntry);
    descriptor: (Lnet/minecraft/world/item/ItemStack;Lcom/minecolonies/api/equipment/registry/EquipmentTypeEntry;)Z
    flags: (0x100a) ACC_PRIVATE, ACC_STATIC, ACC_SYNTHETIC
    Code:
      stack=2, locals=4, args_size=2
         0: aload_0
         1: invokevirtual #132                // Method net/minecraft/world/item/ItemStack.m_41720_:()Lnet/minecraft/world/item/Item;
         4: astore_3
         5: aload_3
         6: instanceof    #296                // class net/minecraft/world/item/ArmorItem
         9: ifeq          34
        12: aload_3
        13: checkcast     #296                // class net/minecraft/world/item/ArmorItem
        16: astore_2
        17: getstatic     #346                // Field net/minecraft/world/entity/EquipmentSlot.LEGS:Lnet/minecraft/world/entity/EquipmentSlot;
        20: aload_2
        21: invokevirtual #306                // Method net/minecraft/world/item/ArmorItem.m_40402_:()Lnet/minecraft/world/entity/EquipmentSlot;
        24: invokevirtual #310                // Method net/minecraft/world/entity/EquipmentSlot.equals:(Ljava/lang/Object;)Z
        27: ifeq          34
        30: iconst_1
        31: goto          35
        34: iconst_0
        35: ireturn
      StackMapTable: number_of_entries = 2
        frame_type = 34 /* same */
        frame_type = 64 /* same_locals_1_stack_item */
          stack = [ int ]
      LineNumberTable:
        line 134: 0
      LocalVariableTable:
        Start  Length  Slot  Name   Signature
            5      12     3 patt7940$temp   Lnet/minecraft/world/item/Item;
           17      17     2 armor   Lnet/minecraft/world/item/ArmorItem;
            0      36     0 itemStack   Lnet/minecraft/world/item/ItemStack;
            0      36     1 equipmentType   Lcom/minecolonies/api/equipment/registry/EquipmentTypeEntry;

  private static void lambda$static$28(com.minecolonies.api.equipment.registry.EquipmentTypeEntry$Builder);
    descriptor: (Lcom/minecolonies/api/equipment/registry/EquipmentTypeEntry$Builder;)V
    flags: (0x100a) ACC_PRIVATE, ACC_STATIC, ACC_SYNTHETIC
    Code:
      stack=2, locals=1, args_size=1
         0: aload_0
         1: ldc_w         #350                // String com.minecolonies.coremod.tooltype.helmet
         4: invokestatic  #204                // InterfaceMethod net/minecraft/network/chat/Component.m_237115_:(Ljava/lang/String;)Lnet/minecraft/network/chat/MutableComponent;
         7: invokevirtual #208                // Method com/minecolonies/api/equipment/registry/EquipmentTypeEntry$Builder.setDisplayName:(Lnet/minecraft/network/chat/Component;)Lcom/minecolonies/api/equipment/registry/EquipmentTypeEntry$Builder;
        10: invokedynamic #355,  0            // InvokeDynamic #11:test:()Ljava/util/function/BiPredicate;
        15: invokevirtual #223                // Method com/minecolonies/api/equipment/registry/EquipmentTypeEntry$Builder.setIsEquipment:(Ljava/util/function/BiPredicate;)Lcom/minecolonies/api/equipment/registry/EquipmentTypeEntry$Builder;
        18: invokedynamic #360,  0            // InvokeDynamic #12:apply:()Ljava/util/function/BiFunction;
        23: invokevirtual #239                // Method com/minecolonies/api/equipment/registry/EquipmentTypeEntry$Builder.setEquipmentLevel:(Ljava/util/function/BiFunction;)Lcom/minecolonies/api/equipment/registry/EquipmentTypeEntry$Builder;
        26: invokevirtual #89                 // Method com/minecolonies/api/equipment/registry/EquipmentTypeEntry$Builder.build:()Lcom/minecolonies/api/equipment/registry/EquipmentTypeEntry;
        29: pop
        30: return
      LineNumberTable:
        line 127: 0
        line 128: 15
        line 129: 23
        line 130: 26
        line 127: 30
      LocalVariableTable:
        Start  Length  Slot  Name   Signature
            0      31     0 builder   Lcom/minecolonies/api/equipment/registry/EquipmentTypeEntry$Builder;

  private static java.lang.Integer lambda$static$27(net.minecraft.world.item.ItemStack, com.minecolonies.api.equipment.registry.EquipmentTypeEntry);
    descriptor: (Lnet/minecraft/world/item/ItemStack;Lcom/minecolonies/api/equipment/registry/EquipmentTypeEntry;)Ljava/lang/Integer;
    flags: (0x100a) ACC_PRIVATE, ACC_STATIC, ACC_SYNTHETIC
    Code:
      stack=1, locals=2, args_size=2
         0: aload_0
         1: invokestatic  #294                // Method com/minecolonies/api/util/ItemStackUtils.getArmorLevel:(Lnet/minecraft/world/item/ItemStack;)I
         4: invokestatic  #246                // Method java/lang/Integer.valueOf:(I)Ljava/lang/Integer;
         7: areturn
      LineNumberTable:
        line 129: 0
      LocalVariableTable:
        Start  Length  Slot  Name   Signature
            0       8     0 itemStack   Lnet/minecraft/world/item/ItemStack;
            0       8     1 equipmentType   Lcom/minecolonies/api/equipment/registry/EquipmentTypeEntry;

  private static boolean lambda$static$26(net.minecraft.world.item.ItemStack, com.minecolonies.api.equipment.registry.EquipmentTypeEntry);
    descriptor: (Lnet/minecraft/world/item/ItemStack;Lcom/minecolonies/api/equipment/registry/EquipmentTypeEntry;)Z
    flags: (0x100a) ACC_PRIVATE, ACC_STATIC, ACC_SYNTHETIC
    Code:
      stack=2, locals=4, args_size=2
         0: aload_0
         1: invokevirtual #132                // Method net/minecraft/world/item/ItemStack.m_41720_:()Lnet/minecraft/world/item/Item;
         4: astore_3
         5: aload_3
         6: instanceof    #296                // class net/minecraft/world/item/ArmorItem
         9: ifeq          34
        12: aload_3
        13: checkcast     #296                // class net/minecraft/world/item/ArmorItem
        16: astore_2
        17: getstatic     #363                // Field net/minecraft/world/entity/EquipmentSlot.HEAD:Lnet/minecraft/world/entity/EquipmentSlot;
        20: aload_2
        21: invokevirtual #306                // Method net/minecraft/world/item/ArmorItem.m_40402_:()Lnet/minecraft/world/entity/EquipmentSlot;
        24: invokevirtual #310                // Method net/minecraft/world/entity/EquipmentSlot.equals:(Ljava/lang/Object;)Z
        27: ifeq          34
        30: iconst_1
        31: goto          35
        34: iconst_0
        35: ireturn
      StackMapTable: number_of_entries = 2
        frame_type = 34 /* same */
        frame_type = 64 /* same_locals_1_stack_item */
          stack = [ int ]
      LineNumberTable:
        line 128: 0
      LocalVariableTable:
        Start  Length  Slot  Name   Signature
            5      12     3 patt7472$temp   Lnet/minecraft/world/item/Item;
           17      17     2 armor   Lnet/minecraft/world/item/ArmorItem;
            0      36     0 itemStack   Lnet/minecraft/world/item/ItemStack;
            0      36     1 equipmentType   Lcom/minecolonies/api/equipment/registry/EquipmentTypeEntry;

  private static void lambda$static$25(com.minecolonies.api.equipment.registry.EquipmentTypeEntry$Builder);
    descriptor: (Lcom/minecolonies/api/equipment/registry/EquipmentTypeEntry$Builder;)V
    flags: (0x100a) ACC_PRIVATE, ACC_STATIC, ACC_SYNTHETIC
    Code:
      stack=2, locals=1, args_size=1
         0: aload_0
         1: ldc_w         #367                // String com.minecolonies.coremod.tooltype.shield
         4: invokestatic  #204                // InterfaceMethod net/minecraft/network/chat/Component.m_237115_:(Ljava/lang/String;)Lnet/minecraft/network/chat/MutableComponent;
         7: invokevirtual #208                // Method com/minecolonies/api/equipment/registry/EquipmentTypeEntry$Builder.setDisplayName:(Lnet/minecraft/network/chat/Component;)Lcom/minecolonies/api/equipment/registry/EquipmentTypeEntry$Builder;
        10: invokedynamic #372,  0            // InvokeDynamic #13:test:()Ljava/util/function/BiPredicate;
        15: invokevirtual #223                // Method com/minecolonies/api/equipment/registry/EquipmentTypeEntry$Builder.setIsEquipment:(Ljava/util/function/BiPredicate;)Lcom/minecolonies/api/equipment/registry/EquipmentTypeEntry$Builder;
        18: invokedynamic #377,  0            // InvokeDynamic #14:apply:()Ljava/util/function/BiFunction;
        23: invokevirtual #239                // Method com/minecolonies/api/equipment/registry/EquipmentTypeEntry$Builder.setEquipmentLevel:(Ljava/util/function/BiFunction;)Lcom/minecolonies/api/equipment/registry/EquipmentTypeEntry$Builder;
        26: invokevirtual #89                 // Method com/minecolonies/api/equipment/registry/EquipmentTypeEntry$Builder.build:()Lcom/minecolonies/api/equipment/registry/EquipmentTypeEntry;
        29: pop
        30: return
      LineNumberTable:
        line 121: 0
        line 122: 15
        line 123: 23
        line 124: 26
        line 121: 30
      LocalVariableTable:
        Start  Length  Slot  Name   Signature
            0      31     0 builder   Lcom/minecolonies/api/equipment/registry/EquipmentTypeEntry$Builder;

  private static java.lang.Integer lambda$static$24(net.minecraft.world.item.ItemStack, com.minecolonies.api.equipment.registry.EquipmentTypeEntry);
    descriptor: (Lnet/minecraft/world/item/ItemStack;Lcom/minecolonies/api/equipment/registry/EquipmentTypeEntry;)Ljava/lang/Integer;
    flags: (0x100a) ACC_PRIVATE, ACC_STATIC, ACC_SYNTHETIC
    Code:
      stack=2, locals=2, args_size=2
         0: aload_0
         1: getstatic     #380                // Field net/minecraft/world/item/Items.f_42740_:Lnet/minecraft/world/item/Item;
         4: invokevirtual #272                // Method net/minecraft/world/item/Item.m_41462_:()I
         7: invokestatic  #274                // Method durabilityBasedLevel:(Lnet/minecraft/world/item/ItemStack;I)I
        10: invokestatic  #246                // Method java/lang/Integer.valueOf:(I)Ljava/lang/Integer;
        13: areturn
      LineNumberTable:
        line 123: 0
      LocalVariableTable:
        Start  Length  Slot  Name   Signature
            0      14     0 itemStack   Lnet/minecraft/world/item/ItemStack;
            0      14     1 equipmentType   Lcom/minecolonies/api/equipment/registry/EquipmentTypeEntry;

  private static boolean lambda$static$23(net.minecraft.world.item.ItemStack, com.minecolonies.api.equipment.registry.EquipmentTypeEntry);
    descriptor: (Lnet/minecraft/world/item/ItemStack;Lcom/minecolonies/api/equipment/registry/EquipmentTypeEntry;)Z
    flags: (0x100a) ACC_PRIVATE, ACC_STATIC, ACC_SYNTHETIC
    Code:
      stack=2, locals=2, args_size=2
         0: aload_0
         1: getstatic     #385                // Field net/minecraftforge/common/ToolActions.DEFAULT_SHIELD_ACTIONS:Ljava/util/Set;
         4: invokestatic  #387                // Method canPerformDefaultActions:(Lnet/minecraft/world/item/ItemStack;Ljava/util/Set;)Z
         7: ireturn
      LineNumberTable:
        line 122: 0
      LocalVariableTable:
        Start  Length  Slot  Name   Signature
            0       8     0 itemStack   Lnet/minecraft/world/item/ItemStack;
            0       8     1 equipmentType   Lcom/minecolonies/api/equipment/registry/EquipmentTypeEntry;

  private static void lambda$static$22(com.minecolonies.api.equipment.registry.EquipmentTypeEntry$Builder);
    descriptor: (Lcom/minecolonies/api/equipment/registry/EquipmentTypeEntry$Builder;)V
    flags: (0x100a) ACC_PRIVATE, ACC_STATIC, ACC_SYNTHETIC
    Code:
      stack=2, locals=1, args_size=1
         0: aload_0
         1: ldc_w         #390                // String com.minecolonies.coremod.tooltype.shears
         4: invokestatic  #204                // InterfaceMethod net/minecraft/network/chat/Component.m_237115_:(Ljava/lang/String;)Lnet/minecraft/network/chat/MutableComponent;
         7: invokevirtual #208                // Method com/minecolonies/api/equipment/registry/EquipmentTypeEntry$Builder.setDisplayName:(Lnet/minecraft/network/chat/Component;)Lcom/minecolonies/api/equipment/registry/EquipmentTypeEntry$Builder;
        10: invokedynamic #395,  0            // InvokeDynamic #15:test:()Ljava/util/function/BiPredicate;
        15: invokevirtual #223                // Method com/minecolonies/api/equipment/registry/EquipmentTypeEntry$Builder.setIsEquipment:(Ljava/util/function/BiPredicate;)Lcom/minecolonies/api/equipment/registry/EquipmentTypeEntry$Builder;
        18: invokedynamic #400,  0            // InvokeDynamic #16:apply:()Ljava/util/function/BiFunction;
        23: invokevirtual #239                // Method com/minecolonies/api/equipment/registry/EquipmentTypeEntry$Builder.setEquipmentLevel:(Ljava/util/function/BiFunction;)Lcom/minecolonies/api/equipment/registry/EquipmentTypeEntry$Builder;
        26: invokevirtual #89                 // Method com/minecolonies/api/equipment/registry/EquipmentTypeEntry$Builder.build:()Lcom/minecolonies/api/equipment/registry/EquipmentTypeEntry;
        29: pop
        30: return
      LineNumberTable:
        line 115: 0
        line 116: 15
        line 117: 23
        line 118: 26
        line 115: 30
      LocalVariableTable:
        Start  Length  Slot  Name   Signature
            0      31     0 builder   Lcom/minecolonies/api/equipment/registry/EquipmentTypeEntry$Builder;

  private static java.lang.Integer lambda$static$21(net.minecraft.world.item.ItemStack, com.minecolonies.api.equipment.registry.EquipmentTypeEntry);
    descriptor: (Lnet/minecraft/world/item/ItemStack;Lcom/minecolonies/api/equipment/registry/EquipmentTypeEntry;)Ljava/lang/Integer;
    flags: (0x100a) ACC_PRIVATE, ACC_STATIC, ACC_SYNTHETIC
    Code:
      stack=2, locals=2, args_size=2
         0: aload_0
         1: getstatic     #403                // Field net/minecraft/world/item/Items.f_42574_:Lnet/minecraft/world/item/Item;
         4: invokevirtual #272                // Method net/minecraft/world/item/Item.m_41462_:()I
         7: invokestatic  #274                // Method durabilityBasedLevel:(Lnet/minecraft/world/item/ItemStack;I)I
        10: invokestatic  #246                // Method java/lang/Integer.valueOf:(I)Ljava/lang/Integer;
        13: areturn
      LineNumberTable:
        line 117: 0
      LocalVariableTable:
        Start  Length  Slot  Name   Signature
            0      14     0 itemStack   Lnet/minecraft/world/item/ItemStack;
            0      14     1 equipmentType   Lcom/minecolonies/api/equipment/registry/EquipmentTypeEntry;

  private static boolean lambda$static$20(net.minecraft.world.item.ItemStack, com.minecolonies.api.equipment.registry.EquipmentTypeEntry);
    descriptor: (Lnet/minecraft/world/item/ItemStack;Lcom/minecolonies/api/equipment/registry/EquipmentTypeEntry;)Z
    flags: (0x100a) ACC_PRIVATE, ACC_STATIC, ACC_SYNTHETIC
    Code:
      stack=2, locals=2, args_size=2
         0: aload_0
         1: getstatic     #406                // Field net/minecraftforge/common/ToolActions.DEFAULT_SHEARS_ACTIONS:Ljava/util/Set;
         4: invokestatic  #387                // Method canPerformDefaultActions:(Lnet/minecraft/world/item/ItemStack;Ljava/util/Set;)Z
         7: ireturn
      LineNumberTable:
        line 116: 0
      LocalVariableTable:
        Start  Length  Slot  Name   Signature
            0       8     0 itemStack   Lnet/minecraft/world/item/ItemStack;
            0       8     1 equipmentType   Lcom/minecolonies/api/equipment/registry/EquipmentTypeEntry;

  private static void lambda$static$19(com.minecolonies.api.equipment.registry.EquipmentTypeEntry$Builder);
    descriptor: (Lcom/minecolonies/api/equipment/registry/EquipmentTypeEntry$Builder;)V
    flags: (0x100a) ACC_PRIVATE, ACC_STATIC, ACC_SYNTHETIC
    Code:
      stack=2, locals=1, args_size=1
         0: aload_0
         1: ldc_w         #409                // String com.minecolonies.coremod.tooltype.fishingrod
         4: invokestatic  #204                // InterfaceMethod net/minecraft/network/chat/Component.m_237115_:(Ljava/lang/String;)Lnet/minecraft/network/chat/MutableComponent;
         7: invokevirtual #208                // Method com/minecolonies/api/equipment/registry/EquipmentTypeEntry$Builder.setDisplayName:(Lnet/minecraft/network/chat/Component;)Lcom/minecolonies/api/equipment/registry/EquipmentTypeEntry$Builder;
        10: invokedynamic #414,  0            // InvokeDynamic #17:test:()Ljava/util/function/BiPredicate;
        15: invokevirtual #223                // Method com/minecolonies/api/equipment/registry/EquipmentTypeEntry$Builder.setIsEquipment:(Ljava/util/function/BiPredicate;)Lcom/minecolonies/api/equipment/registry/EquipmentTypeEntry$Builder;
        18: invokedynamic #419,  0            // InvokeDynamic #18:apply:()Ljava/util/function/BiFunction;
        23: invokevirtual #239                // Method com/minecolonies/api/equipment/registry/EquipmentTypeEntry$Builder.setEquipmentLevel:(Ljava/util/function/BiFunction;)Lcom/minecolonies/api/equipment/registry/EquipmentTypeEntry$Builder;
        26: invokevirtual #89                 // Method com/minecolonies/api/equipment/registry/EquipmentTypeEntry$Builder.build:()Lcom/minecolonies/api/equipment/registry/EquipmentTypeEntry;
        29: pop
        30: return
      LineNumberTable:
        line 109: 0
        line 110: 15
        line 111: 23
        line 112: 26
        line 109: 30
      LocalVariableTable:
        Start  Length  Slot  Name   Signature
            0      31     0 builder   Lcom/minecolonies/api/equipment/registry/EquipmentTypeEntry$Builder;

  private static java.lang.Integer lambda$static$18(net.minecraft.world.item.ItemStack, com.minecolonies.api.equipment.registry.EquipmentTypeEntry);
    descriptor: (Lnet/minecraft/world/item/ItemStack;Lcom/minecolonies/api/equipment/registry/EquipmentTypeEntry;)Ljava/lang/Integer;
    flags: (0x100a) ACC_PRIVATE, ACC_STATIC, ACC_SYNTHETIC
    Code:
      stack=2, locals=2, args_size=2
         0: aload_0
         1: getstatic     #422                // Field net/minecraft/world/item/Items.f_42523_:Lnet/minecraft/world/item/Item;
         4: invokevirtual #272                // Method net/minecraft/world/item/Item.m_41462_:()I
         7: invokestatic  #274                // Method durabilityBasedLevel:(Lnet/minecraft/world/item/ItemStack;I)I
        10: invokestatic  #246                // Method java/lang/Integer.valueOf:(I)Ljava/lang/Integer;
        13: areturn
      LineNumberTable:
        line 111: 0
      LocalVariableTable:
        Start  Length  Slot  Name   Signature
            0      14     0 itemStack   Lnet/minecraft/world/item/ItemStack;
            0      14     1 equipmentType   Lcom/minecolonies/api/equipment/registry/EquipmentTypeEntry;

  private static boolean lambda$static$17(net.minecraft.world.item.ItemStack, com.minecolonies.api.equipment.registry.EquipmentTypeEntry);
    descriptor: (Lnet/minecraft/world/item/ItemStack;Lcom/minecolonies/api/equipment/registry/EquipmentTypeEntry;)Z
    flags: (0x100a) ACC_PRIVATE, ACC_STATIC, ACC_SYNTHETIC
    Code:
      stack=2, locals=2, args_size=2
         0: aload_0
         1: getstatic     #425                // Field net/minecraftforge/common/ToolActions.DEFAULT_FISHING_ROD_ACTIONS:Ljava/util/Set;
         4: invokestatic  #387                // Method canPerformDefaultActions:(Lnet/minecraft/world/item/ItemStack;Ljava/util/Set;)Z
         7: ireturn
      LineNumberTable:
        line 110: 0
      LocalVariableTable:
        Start  Length  Slot  Name   Signature
            0       8     0 itemStack   Lnet/minecraft/world/item/ItemStack;
            0       8     1 equipmentType   Lcom/minecolonies/api/equipment/registry/EquipmentTypeEntry;

  private static void lambda$static$16(com.minecolonies.api.equipment.registry.EquipmentTypeEntry$Builder);
    descriptor: (Lcom/minecolonies/api/equipment/registry/EquipmentTypeEntry$Builder;)V
    flags: (0x100a) ACC_PRIVATE, ACC_STATIC, ACC_SYNTHETIC
    Code:
      stack=2, locals=1, args_size=1
         0: aload_0
         1: ldc_w         #428                // String com.minecolonies.coremod.tooltype.bow
         4: invokestatic  #204                // InterfaceMethod net/minecraft/network/chat/Component.m_237115_:(Ljava/lang/String;)Lnet/minecraft/network/chat/MutableComponent;
         7: invokevirtual #208                // Method com/minecolonies/api/equipment/registry/EquipmentTypeEntry$Builder.setDisplayName:(Lnet/minecraft/network/chat/Component;)Lcom/minecolonies/api/equipment/registry/EquipmentTypeEntry$Builder;
        10: invokedynamic #433,  0            // InvokeDynamic #19:test:()Ljava/util/function/BiPredicate;
        15: invokevirtual #223                // Method com/minecolonies/api/equipment/registry/EquipmentTypeEntry$Builder.setIsEquipment:(Ljava/util/function/BiPredicate;)Lcom/minecolonies/api/equipment/registry/EquipmentTypeEntry$Builder;
        18: invokedynamic #438,  0            // InvokeDynamic #20:apply:()Ljava/util/function/BiFunction;
        23: invokevirtual #239                // Method com/minecolonies/api/equipment/registry/EquipmentTypeEntry$Builder.setEquipmentLevel:(Ljava/util/function/BiFunction;)Lcom/minecolonies/api/equipment/registry/EquipmentTypeEntry$Builder;
        26: invokevirtual #89                 // Method com/minecolonies/api/equipment/registry/EquipmentTypeEntry$Builder.build:()Lcom/minecolonies/api/equipment/registry/EquipmentTypeEntry;
        29: pop
        30: return
      LineNumberTable:
        line 103: 0
        line 104: 15
        line 105: 23
        line 106: 26
        line 103: 30
      LocalVariableTable:
        Start  Length  Slot  Name   Signature
            0      31     0 builder   Lcom/minecolonies/api/equipment/registry/EquipmentTypeEntry$Builder;

  private static java.lang.Integer lambda$static$15(net.minecraft.world.item.ItemStack, com.minecolonies.api.equipment.registry.EquipmentTypeEntry);
    descriptor: (Lnet/minecraft/world/item/ItemStack;Lcom/minecolonies/api/equipment/registry/EquipmentTypeEntry;)Ljava/lang/Integer;
    flags: (0x100a) ACC_PRIVATE, ACC_STATIC, ACC_SYNTHETIC
    Code:
      stack=2, locals=2, args_size=2
         0: aload_0
         1: getstatic     #441                // Field net/minecraft/world/item/Items.f_42411_:Lnet/minecraft/world/item/Item;
         4: invokevirtual #272                // Method net/minecraft/world/item/Item.m_41462_:()I
         7: invokestatic  #274                // Method durabilityBasedLevel:(Lnet/minecraft/world/item/ItemStack;I)I
        10: invokestatic  #246                // Method java/lang/Integer.valueOf:(I)Ljava/lang/Integer;
        13: areturn
      LineNumberTable:
        line 105: 0
      LocalVariableTable:
        Start  Length  Slot  Name   Signature
            0      14     0 itemStack   Lnet/minecraft/world/item/ItemStack;
            0      14     1 equipmentType   Lcom/minecolonies/api/equipment/registry/EquipmentTypeEntry;

  private static boolean lambda$static$14(net.minecraft.world.item.ItemStack, com.minecolonies.api.equipment.registry.EquipmentTypeEntry);
    descriptor: (Lnet/minecraft/world/item/ItemStack;Lcom/minecolonies/api/equipment/registry/EquipmentTypeEntry;)Z
    flags: (0x100a) ACC_PRIVATE, ACC_STATIC, ACC_SYNTHETIC
    Code:
      stack=1, locals=2, args_size=2
         0: aload_0
         1: invokevirtual #132                // Method net/minecraft/world/item/ItemStack.m_41720_:()Lnet/minecraft/world/item/Item;
         4: instanceof    #443                // class net/minecraft/world/item/BowItem
         7: ireturn
      LineNumberTable:
        line 104: 0
      LocalVariableTable:
        Start  Length  Slot  Name   Signature
            0       8     0 itemStack   Lnet/minecraft/world/item/ItemStack;
            0       8     1 equipmentType   Lcom/minecolonies/api/equipment/registry/EquipmentTypeEntry;

  private static void lambda$static$13(com.minecolonies.api.equipment.registry.EquipmentTypeEntry$Builder);
    descriptor: (Lcom/minecolonies/api/equipment/registry/EquipmentTypeEntry$Builder;)V
    flags: (0x100a) ACC_PRIVATE, ACC_STATIC, ACC_SYNTHETIC
    Code:
      stack=2, locals=1, args_size=1
         0: aload_0
         1: ldc_w         #446                // String com.minecolonies.coremod.tooltype.sword
         4: invokestatic  #204                // InterfaceMethod net/minecraft/network/chat/Component.m_237115_:(Ljava/lang/String;)Lnet/minecraft/network/chat/MutableComponent;
         7: invokevirtual #208                // Method com/minecolonies/api/equipment/registry/EquipmentTypeEntry$Builder.setDisplayName:(Lnet/minecraft/network/chat/Component;)Lcom/minecolonies/api/equipment/registry/EquipmentTypeEntry$Builder;
        10: invokedynamic #451,  0            // InvokeDynamic #21:test:()Ljava/util/function/BiPredicate;
        15: invokevirtual #223                // Method com/minecolonies/api/equipment/registry/EquipmentTypeEntry$Builder.setIsEquipment:(Ljava/util/function/BiPredicate;)Lcom/minecolonies/api/equipment/registry/EquipmentTypeEntry$Builder;
        18: invokedynamic #456,  0            // InvokeDynamic #22:apply:()Ljava/util/function/BiFunction;
        23: invokevirtual #239                // Method com/minecolonies/api/equipment/registry/EquipmentTypeEntry$Builder.setEquipmentLevel:(Ljava/util/function/BiFunction;)Lcom/minecolonies/api/equipment/registry/EquipmentTypeEntry$Builder;
        26: invokevirtual #89                 // Method com/minecolonies/api/equipment/registry/EquipmentTypeEntry$Builder.build:()Lcom/minecolonies/api/equipment/registry/EquipmentTypeEntry;
        29: pop
        30: return
      LineNumberTable:
        line 86: 0
        line 87: 15
        line 89: 23
        line 100: 26
        line 86: 30
      LocalVariableTable:
        Start  Length  Slot  Name   Signature
            0      31     0 builder   Lcom/minecolonies/api/equipment/registry/EquipmentTypeEntry$Builder;

  private static java.lang.Integer lambda$static$12(net.minecraft.world.item.ItemStack, com.minecolonies.api.equipment.registry.EquipmentTypeEntry);
    descriptor: (Lnet/minecraft/world/item/ItemStack;Lcom/minecolonies/api/equipment/registry/EquipmentTypeEntry;)Ljava/lang/Integer;
    flags: (0x100a) ACC_PRIVATE, ACC_STATIC, ACC_SYNTHETIC
    Code:
      stack=1, locals=4, args_size=2
         0: aload_0
         1: invokestatic  #460                // Method com/minecolonies/api/compatibility/Compatibility.isTinkersWeapon:(Lnet/minecraft/world/item/ItemStack;)Z
         4: ifeq          15
         7: aload_0
         8: invokestatic  #126                // Method com/minecolonies/api/compatibility/Compatibility.getToolLevel:(Lnet/minecraft/world/item/ItemStack;)I
        11: invokestatic  #246                // Method java/lang/Integer.valueOf:(I)Ljava/lang/Integer;
        14: areturn
        15: aload_0
        16: invokevirtual #132                // Method net/minecraft/world/item/ItemStack.m_41720_:()Lnet/minecraft/world/item/Item;
        19: astore_3
        20: aload_3
        21: instanceof    #134                // class net/minecraft/world/item/TieredItem
        24: ifeq          45
        27: aload_3
        28: checkcast     #134                // class net/minecraft/world/item/TieredItem
        31: astore_2
        32: aload_2
        33: invokevirtual #138                // Method net/minecraft/world/item/TieredItem.m_43314_:()Lnet/minecraft/world/item/Tier;
        36: invokeinterface #144,  1          // InterfaceMethod net/minecraft/world/item/Tier.m_6604_:()I
        41: invokestatic  #246                // Method java/lang/Integer.valueOf:(I)Ljava/lang/Integer;
        44: areturn
        45: iconst_m1
        46: invokestatic  #246                // Method java/lang/Integer.valueOf:(I)Ljava/lang/Integer;
        49: areturn
      StackMapTable: number_of_entries = 2
        frame_type = 15 /* same */
        frame_type = 29 /* same */
      LineNumberTable:
        line 90: 0
        line 92: 7
        line 94: 15
        line 96: 32
        line 98: 45
      LocalVariableTable:
        Start  Length  Slot  Name   Signature
           20      12     3 patt5214$temp   Lnet/minecraft/world/item/Item;
           32      13     2 tieredItem   Lnet/minecraft/world/item/TieredItem;
            0      50     0 itemStack   Lnet/minecraft/world/item/ItemStack;
            0      50     1 equipmentType   Lcom/minecolonies/api/equipment/registry/EquipmentTypeEntry;

  private static boolean lambda$static$11(net.minecraft.world.item.ItemStack, com.minecolonies.api.equipment.registry.EquipmentTypeEntry);
    descriptor: (Lnet/minecraft/world/item/ItemStack;Lcom/minecolonies/api/equipment/registry/EquipmentTypeEntry;)Z
    flags: (0x100a) ACC_PRIVATE, ACC_STATIC, ACC_SYNTHETIC
    Code:
      stack=2, locals=2, args_size=2
         0: aload_0
         1: getstatic     #464                // Field net/minecraftforge/common/ToolActions.DEFAULT_SWORD_ACTIONS:Ljava/util/Set;
         4: invokestatic  #387                // Method canPerformDefaultActions:(Lnet/minecraft/world/item/ItemStack;Ljava/util/Set;)Z
         7: ifne          17
        10: aload_0
        11: invokestatic  #460                // Method com/minecolonies/api/compatibility/Compatibility.isTinkersWeapon:(Lnet/minecraft/world/item/ItemStack;)Z
        14: ifeq          21
        17: iconst_1
        18: goto          22
        21: iconst_0
        22: ireturn
      StackMapTable: number_of_entries = 3
        frame_type = 17 /* same */
        frame_type = 3 /* same */
        frame_type = 64 /* same_locals_1_stack_item */
          stack = [ int ]
      LineNumberTable:
        line 87: 0
      LocalVariableTable:
        Start  Length  Slot  Name   Signature
            0      23     0 itemStack   Lnet/minecraft/world/item/ItemStack;
            0      23     1 equipmentType   Lcom/minecolonies/api/equipment/registry/EquipmentTypeEntry;

  private static void lambda$static$10(com.minecolonies.api.equipment.registry.EquipmentTypeEntry$Builder);
    descriptor: (Lcom/minecolonies/api/equipment/registry/EquipmentTypeEntry$Builder;)V
    flags: (0x100a) ACC_PRIVATE, ACC_STATIC, ACC_SYNTHETIC
    Code:
      stack=2, locals=1, args_size=1
         0: aload_0
         1: ldc_w         #467                // String com.minecolonies.coremod.tooltype.hoe
         4: invokestatic  #204                // InterfaceMethod net/minecraft/network/chat/Component.m_237115_:(Ljava/lang/String;)Lnet/minecraft/network/chat/MutableComponent;
         7: invokevirtual #208                // Method com/minecolonies/api/equipment/registry/EquipmentTypeEntry$Builder.setDisplayName:(Lnet/minecraft/network/chat/Component;)Lcom/minecolonies/api/equipment/registry/EquipmentTypeEntry$Builder;
        10: invokedynamic #472,  0            // InvokeDynamic #23:test:()Ljava/util/function/BiPredicate;
        15: invokevirtual #223                // Method com/minecolonies/api/equipment/registry/EquipmentTypeEntry$Builder.setIsEquipment:(Ljava/util/function/BiPredicate;)Lcom/minecolonies/api/equipment/registry/EquipmentTypeEntry$Builder;
        18: invokedynamic #476,  0            // InvokeDynamic #24:apply:()Ljava/util/function/BiFunction;
        23: invokevirtual #239                // Method com/minecolonies/api/equipment/registry/EquipmentTypeEntry$Builder.setEquipmentLevel:(Ljava/util/function/BiFunction;)Lcom/minecolonies/api/equipment/registry/EquipmentTypeEntry$Builder;
        26: invokevirtual #89                 // Method com/minecolonies/api/equipment/registry/EquipmentTypeEntry$Builder.build:()Lcom/minecolonies/api/equipment/registry/EquipmentTypeEntry;
        29: pop
        30: return
      LineNumberTable:
        line 79: 0
        line 80: 15
        line 82: 23
        line 83: 26
        line 79: 30
      LocalVariableTable:
        Start  Length  Slot  Name   Signature
            0      31     0 builder   Lcom/minecolonies/api/equipment/registry/EquipmentTypeEntry$Builder;

  private static boolean lambda$static$9(net.minecraft.world.item.ItemStack, com.minecolonies.api.equipment.registry.EquipmentTypeEntry);
    descriptor: (Lnet/minecraft/world/item/ItemStack;Lcom/minecolonies/api/equipment/registry/EquipmentTypeEntry;)Z
    flags: (0x100a) ACC_PRIVATE, ACC_STATIC, ACC_SYNTHETIC
    Code:
      stack=2, locals=2, args_size=2
         0: aload_0
         1: getstatic     #479                // Field net/minecraftforge/common/ToolActions.DEFAULT_HOE_ACTIONS:Ljava/util/Set;
         4: invokestatic  #387                // Method canPerformDefaultActions:(Lnet/minecraft/world/item/ItemStack;Ljava/util/Set;)Z
         7: ifne          18
        10: aload_0
        11: aload_1
        12: invokestatic  #122                // Method com/minecolonies/api/compatibility/Compatibility.isTinkersTool:(Lnet/minecraft/world/item/ItemStack;Lcom/minecolonies/api/equipment/registry/EquipmentTypeEntry;)Z
        15: ifeq          22
        18: iconst_1
        19: goto          23
        22: iconst_0
        23: ireturn
      StackMapTable: number_of_entries = 3
        frame_type = 18 /* same */
        frame_type = 3 /* same */
        frame_type = 64 /* same_locals_1_stack_item */
          stack = [ int ]
      LineNumberTable:
        line 80: 0
      LocalVariableTable:
        Start  Length  Slot  Name   Signature
            0      24     0 itemStack   Lnet/minecraft/world/item/ItemStack;
            0      24     1 equipmentType   Lcom/minecolonies/api/equipment/registry/EquipmentTypeEntry;

  private static void lambda$static$8(com.minecolonies.api.equipment.registry.EquipmentTypeEntry$Builder);
    descriptor: (Lcom/minecolonies/api/equipment/registry/EquipmentTypeEntry$Builder;)V
    flags: (0x100a) ACC_PRIVATE, ACC_STATIC, ACC_SYNTHETIC
    Code:
      stack=2, locals=1, args_size=1
         0: aload_0
         1: ldc_w         #482                // String com.minecolonies.coremod.tooltype.axe
         4: invokestatic  #204                // InterfaceMethod net/minecraft/network/chat/Component.m_237115_:(Ljava/lang/String;)Lnet/minecraft/network/chat/MutableComponent;
         7: invokevirtual #208                // Method com/minecolonies/api/equipment/registry/EquipmentTypeEntry$Builder.setDisplayName:(Lnet/minecraft/network/chat/Component;)Lcom/minecolonies/api/equipment/registry/EquipmentTypeEntry$Builder;
        10: invokedynamic #487,  0            // InvokeDynamic #25:test:()Ljava/util/function/BiPredicate;
        15: invokevirtual #223                // Method com/minecolonies/api/equipment/registry/EquipmentTypeEntry$Builder.setIsEquipment:(Ljava/util/function/BiPredicate;)Lcom/minecolonies/api/equipment/registry/EquipmentTypeEntry$Builder;
        18: invokedynamic #476,  0            // InvokeDynamic #24:apply:()Ljava/util/function/BiFunction;
        23: invokevirtual #239                // Method com/minecolonies/api/equipment/registry/EquipmentTypeEntry$Builder.setEquipmentLevel:(Ljava/util/function/BiFunction;)Lcom/minecolonies/api/equipment/registry/EquipmentTypeEntry$Builder;
        26: invokevirtual #89                 // Method com/minecolonies/api/equipment/registry/EquipmentTypeEntry$Builder.build:()Lcom/minecolonies/api/equipment/registry/EquipmentTypeEntry;
        29: pop
        30: return
      LineNumberTable:
        line 72: 0
        line 73: 15
        line 75: 23
        line 76: 26
        line 72: 30
      LocalVariableTable:
        Start  Length  Slot  Name   Signature
            0      31     0 builder   Lcom/minecolonies/api/equipment/registry/EquipmentTypeEntry$Builder;

  private static boolean lambda$static$7(net.minecraft.world.item.ItemStack, com.minecolonies.api.equipment.registry.EquipmentTypeEntry);
    descriptor: (Lnet/minecraft/world/item/ItemStack;Lcom/minecolonies/api/equipment/registry/EquipmentTypeEntry;)Z
    flags: (0x100a) ACC_PRIVATE, ACC_STATIC, ACC_SYNTHETIC
    Code:
      stack=2, locals=2, args_size=2
         0: aload_0
         1: getstatic     #490                // Field net/minecraftforge/common/ToolActions.DEFAULT_AXE_ACTIONS:Ljava/util/Set;
         4: invokestatic  #387                // Method canPerformDefaultActions:(Lnet/minecraft/world/item/ItemStack;Ljava/util/Set;)Z
         7: ifne          18
        10: aload_0
        11: aload_1
        12: invokestatic  #122                // Method com/minecolonies/api/compatibility/Compatibility.isTinkersTool:(Lnet/minecraft/world/item/ItemStack;Lcom/minecolonies/api/equipment/registry/EquipmentTypeEntry;)Z
        15: ifeq          22
        18: iconst_1
        19: goto          23
        22: iconst_0
        23: ireturn
      StackMapTable: number_of_entries = 3
        frame_type = 18 /* same */
        frame_type = 3 /* same */
        frame_type = 64 /* same_locals_1_stack_item */
          stack = [ int ]
      LineNumberTable:
        line 73: 0
      LocalVariableTable:
        Start  Length  Slot  Name   Signature
            0      24     0 itemStack   Lnet/minecraft/world/item/ItemStack;
            0      24     1 equipmentType   Lcom/minecolonies/api/equipment/registry/EquipmentTypeEntry;

  private static void lambda$static$6(com.minecolonies.api.equipment.registry.EquipmentTypeEntry$Builder);
    descriptor: (Lcom/minecolonies/api/equipment/registry/EquipmentTypeEntry$Builder;)V
    flags: (0x100a) ACC_PRIVATE, ACC_STATIC, ACC_SYNTHETIC
    Code:
      stack=2, locals=1, args_size=1
         0: aload_0
         1: ldc_w         #493                // String com.minecolonies.coremod.tooltype.shovel
         4: invokestatic  #204                // InterfaceMethod net/minecraft/network/chat/Component.m_237115_:(Ljava/lang/String;)Lnet/minecraft/network/chat/MutableComponent;
         7: invokevirtual #208                // Method com/minecolonies/api/equipment/registry/EquipmentTypeEntry$Builder.setDisplayName:(Lnet/minecraft/network/chat/Component;)Lcom/minecolonies/api/equipment/registry/EquipmentTypeEntry$Builder;
        10: invokedynamic #498,  0            // InvokeDynamic #26:test:()Ljava/util/function/BiPredicate;
        15: invokevirtual #223                // Method com/minecolonies/api/equipment/registry/EquipmentTypeEntry$Builder.setIsEquipment:(Ljava/util/function/BiPredicate;)Lcom/minecolonies/api/equipment/registry/EquipmentTypeEntry$Builder;
        18: invokedynamic #476,  0            // InvokeDynamic #24:apply:()Ljava/util/function/BiFunction;
        23: invokevirtual #239                // Method com/minecolonies/api/equipment/registry/EquipmentTypeEntry$Builder.setEquipmentLevel:(Ljava/util/function/BiFunction;)Lcom/minecolonies/api/equipment/registry/EquipmentTypeEntry$Builder;
        26: invokevirtual #89                 // Method com/minecolonies/api/equipment/registry/EquipmentTypeEntry$Builder.build:()Lcom/minecolonies/api/equipment/registry/EquipmentTypeEntry;
        29: pop
        30: return
      LineNumberTable:
        line 64: 0
        line 65: 15
        line 68: 23
        line 69: 26
        line 64: 30
      LocalVariableTable:
        Start  Length  Slot  Name   Signature
            0      31     0 builder   Lcom/minecolonies/api/equipment/registry/EquipmentTypeEntry$Builder;

  private static boolean lambda$static$5(net.minecraft.world.item.ItemStack, com.minecolonies.api.equipment.registry.EquipmentTypeEntry);
    descriptor: (Lnet/minecraft/world/item/ItemStack;Lcom/minecolonies/api/equipment/registry/EquipmentTypeEntry;)Z
    flags: (0x100a) ACC_PRIVATE, ACC_STATIC, ACC_SYNTHETIC
    Code:
      stack=2, locals=2, args_size=2
         0: aload_0
         1: getstatic     #501                // Field net/minecraftforge/common/ToolActions.DEFAULT_SHOVEL_ACTIONS:Ljava/util/Set;
         4: invokestatic  #387                // Method canPerformDefaultActions:(Lnet/minecraft/world/item/ItemStack;Ljava/util/Set;)Z
         7: ifne          18
        10: aload_0
        11: aload_1
        12: invokestatic  #122                // Method com/minecolonies/api/compatibility/Compatibility.isTinkersTool:(Lnet/minecraft/world/item/ItemStack;Lcom/minecolonies/api/equipment/registry/EquipmentTypeEntry;)Z
        15: ifeq          22
        18: iconst_1
        19: goto          23
        22: iconst_0
        23: ireturn
      StackMapTable: number_of_entries = 3
        frame_type = 18 /* same */
        frame_type = 3 /* same */
        frame_type = 64 /* same_locals_1_stack_item */
          stack = [ int ]
      LineNumberTable:
        line 65: 0
      LocalVariableTable:
        Start  Length  Slot  Name   Signature
            0      24     0 itemStack   Lnet/minecraft/world/item/ItemStack;
            0      24     1 equipmentType   Lcom/minecolonies/api/equipment/registry/EquipmentTypeEntry;

  private static void lambda$static$4(com.minecolonies.api.equipment.registry.EquipmentTypeEntry$Builder);
    descriptor: (Lcom/minecolonies/api/equipment/registry/EquipmentTypeEntry$Builder;)V
    flags: (0x100a) ACC_PRIVATE, ACC_STATIC, ACC_SYNTHETIC
    Code:
      stack=2, locals=1, args_size=1
         0: aload_0
         1: ldc_w         #504                // String com.minecolonies.coremod.tooltype.pickaxe
         4: invokestatic  #204                // InterfaceMethod net/minecraft/network/chat/Component.m_237115_:(Ljava/lang/String;)Lnet/minecraft/network/chat/MutableComponent;
         7: invokevirtual #208                // Method com/minecolonies/api/equipment/registry/EquipmentTypeEntry$Builder.setDisplayName:(Lnet/minecraft/network/chat/Component;)Lcom/minecolonies/api/equipment/registry/EquipmentTypeEntry$Builder;
        10: invokedynamic #509,  0            // InvokeDynamic #27:test:()Ljava/util/function/BiPredicate;
        15: invokevirtual #223                // Method com/minecolonies/api/equipment/registry/EquipmentTypeEntry$Builder.setIsEquipment:(Ljava/util/function/BiPredicate;)Lcom/minecolonies/api/equipment/registry/EquipmentTypeEntry$Builder;
        18: invokedynamic #476,  0            // InvokeDynamic #24:apply:()Ljava/util/function/BiFunction;
        23: invokevirtual #239                // Method com/minecolonies/api/equipment/registry/EquipmentTypeEntry$Builder.setEquipmentLevel:(Ljava/util/function/BiFunction;)Lcom/minecolonies/api/equipment/registry/EquipmentTypeEntry$Builder;
        26: invokevirtual #89                 // Method com/minecolonies/api/equipment/registry/EquipmentTypeEntry$Builder.build:()Lcom/minecolonies/api/equipment/registry/EquipmentTypeEntry;
        29: pop
        30: return
      LineNumberTable:
        line 56: 0
        line 57: 15
        line 60: 23
        line 61: 26
        line 56: 30
      LocalVariableTable:
        Start  Length  Slot  Name   Signature
            0      31     0 builder   Lcom/minecolonies/api/equipment/registry/EquipmentTypeEntry$Builder;

  private static boolean lambda$static$3(net.minecraft.world.item.ItemStack, com.minecolonies.api.equipment.registry.EquipmentTypeEntry);
    descriptor: (Lnet/minecraft/world/item/ItemStack;Lcom/minecolonies/api/equipment/registry/EquipmentTypeEntry;)Z
    flags: (0x100a) ACC_PRIVATE, ACC_STATIC, ACC_SYNTHETIC
    Code:
      stack=2, locals=2, args_size=2
         0: aload_0
         1: getstatic     #512                // Field net/minecraftforge/common/ToolActions.DEFAULT_PICKAXE_ACTIONS:Ljava/util/Set;
         4: invokestatic  #387                // Method canPerformDefaultActions:(Lnet/minecraft/world/item/ItemStack;Ljava/util/Set;)Z
         7: ifne          18
        10: aload_0
        11: aload_1
        12: invokestatic  #122                // Method com/minecolonies/api/compatibility/Compatibility.isTinkersTool:(Lnet/minecraft/world/item/ItemStack;Lcom/minecolonies/api/equipment/registry/EquipmentTypeEntry;)Z
        15: ifeq          22
        18: iconst_1
        19: goto          23
        22: iconst_0
        23: ireturn
      StackMapTable: number_of_entries = 3
        frame_type = 18 /* same */
        frame_type = 3 /* same */
        frame_type = 64 /* same_locals_1_stack_item */
          stack = [ int ]
      LineNumberTable:
        line 57: 0
      LocalVariableTable:
        Start  Length  Slot  Name   Signature
            0      24     0 itemStack   Lnet/minecraft/world/item/ItemStack;
            0      24     1 equipmentType   Lcom/minecolonies/api/equipment/registry/EquipmentTypeEntry;

  private static void lambda$static$2(com.minecolonies.api.equipment.registry.EquipmentTypeEntry$Builder);
    descriptor: (Lcom/minecolonies/api/equipment/registry/EquipmentTypeEntry$Builder;)V
    flags: (0x100a) ACC_PRIVATE, ACC_STATIC, ACC_SYNTHETIC
    Code:
      stack=2, locals=1, args_size=1
         0: aload_0
         1: ldc_w         #515                // String com.minecolonies.coremod.tooltype.none
         4: invokestatic  #204                // InterfaceMethod net/minecraft/network/chat/Component.m_237115_:(Ljava/lang/String;)Lnet/minecraft/network/chat/MutableComponent;
         7: invokevirtual #208                // Method com/minecolonies/api/equipment/registry/EquipmentTypeEntry$Builder.setDisplayName:(Lnet/minecraft/network/chat/Component;)Lcom/minecolonies/api/equipment/registry/EquipmentTypeEntry$Builder;
        10: invokedynamic #520,  0            // InvokeDynamic #28:test:()Ljava/util/function/BiPredicate;
        15: invokevirtual #223                // Method com/minecolonies/api/equipment/registry/EquipmentTypeEntry$Builder.setIsEquipment:(Ljava/util/function/BiPredicate;)Lcom/minecolonies/api/equipment/registry/EquipmentTypeEntry$Builder;
        18: invokedynamic #525,  0            // InvokeDynamic #29:apply:()Ljava/util/function/BiFunction;
        23: invokevirtual #239                // Method com/minecolonies/api/equipment/registry/EquipmentTypeEntry$Builder.setEquipmentLevel:(Ljava/util/function/BiFunction;)Lcom/minecolonies/api/equipment/registry/EquipmentTypeEntry$Builder;
        26: invokevirtual #89                 // Method com/minecolonies/api/equipment/registry/EquipmentTypeEntry$Builder.build:()Lcom/minecolonies/api/equipment/registry/EquipmentTypeEntry;
        29: pop
        30: return
      LineNumberTable:
        line 50: 0
        line 51: 15
        line 52: 23
        line 53: 26
        line 50: 30
      LocalVariableTable:
        Start  Length  Slot  Name   Signature
            0      31     0 builder   Lcom/minecolonies/api/equipment/registry/EquipmentTypeEntry$Builder;

  private static java.lang.Integer lambda$static$1(net.minecraft.world.item.ItemStack, com.minecolonies.api.equipment.registry.EquipmentTypeEntry);
    descriptor: (Lnet/minecraft/world/item/ItemStack;Lcom/minecolonies/api/equipment/registry/EquipmentTypeEntry;)Ljava/lang/Integer;
    flags: (0x100a) ACC_PRIVATE, ACC_STATIC, ACC_SYNTHETIC
    Code:
      stack=1, locals=2, args_size=2
         0: iconst_m1
         1: invokestatic  #246                // Method java/lang/Integer.valueOf:(I)Ljava/lang/Integer;
         4: areturn
      LineNumberTable:
        line 52: 0
      LocalVariableTable:
        Start  Length  Slot  Name   Signature
            0       5     0 itemStack   Lnet/minecraft/world/item/ItemStack;
            0       5     1 equipmentType   Lcom/minecolonies/api/equipment/registry/EquipmentTypeEntry;

  private static boolean lambda$static$0(net.minecraft.world.item.ItemStack, com.minecolonies.api.equipment.registry.EquipmentTypeEntry);
    descriptor: (Lnet/minecraft/world/item/ItemStack;Lcom/minecolonies/api/equipment/registry/EquipmentTypeEntry;)Z
    flags: (0x100a) ACC_PRIVATE, ACC_STATIC, ACC_SYNTHETIC
    Code:
      stack=1, locals=2, args_size=2
         0: iconst_1
         1: ireturn
      LineNumberTable:
        line 51: 0
      LocalVariableTable:
        Start  Length  Slot  Name   Signature
            0       2     0 itemStack   Lnet/minecraft/world/item/ItemStack;
            0       2     1 equipmentType   Lcom/minecolonies/api/equipment/registry/EquipmentTypeEntry;

  static {};
    descriptor: ()V
    flags: (0x0008) ACC_STATIC
    Code:
      stack=4, locals=0, args_size=0
         0: new           #60                 // class net/minecraft/resources/ResourceLocation
         3: dup
         4: ldc           #62                 // String minecolonies
         6: ldc_w         #528                // String equipmenttypes
         9: invokespecial #65                 // Method net/minecraft/resources/ResourceLocation."<init>":(Ljava/lang/String;Ljava/lang/String;)V
        12: ldc           #62                 // String minecolonies
        14: invokestatic  #532                // Method net/minecraftforge/registries/DeferredRegister.create:(Lnet/minecraft/resources/ResourceLocation;Ljava/lang/String;)Lnet/minecraftforge/registries/DeferredRegister;
        17: putstatic     #77                 // Field DEFERRED_REGISTER:Lnet/minecraftforge/registries/DeferredRegister;
        20: ldc_w         #533                // String none
        23: invokedynamic #541,  0            // InvokeDynamic #30:accept:()Ljava/util/function/Consumer;
        28: invokestatic  #543                // Method register:(Ljava/lang/String;Ljava/util/function/Consumer;)Lnet/minecraftforge/registries/RegistryObject;
        31: putstatic     #545                // Field none:Lnet/minecraftforge/registries/RegistryObject;
        34: ldc_w         #546                // String pickaxe
        37: invokedynamic #550,  0            // InvokeDynamic #31:accept:()Ljava/util/function/Consumer;
        42: invokestatic  #543                // Method register:(Ljava/lang/String;Ljava/util/function/Consumer;)Lnet/minecraftforge/registries/RegistryObject;
        45: putstatic     #552                // Field pickaxe:Lnet/minecraftforge/registries/RegistryObject;
        48: ldc_w         #553                // String shovel
        51: invokedynamic #557,  0            // InvokeDynamic #32:accept:()Ljava/util/function/Consumer;
        56: invokestatic  #543                // Method register:(Ljava/lang/String;Ljava/util/function/Consumer;)Lnet/minecraftforge/registries/RegistryObject;
        59: putstatic     #559                // Field shovel:Lnet/minecraftforge/registries/RegistryObject;
        62: ldc_w         #560                // String axe
        65: invokedynamic #564,  0            // InvokeDynamic #33:accept:()Ljava/util/function/Consumer;
        70: invokestatic  #543                // Method register:(Ljava/lang/String;Ljava/util/function/Consumer;)Lnet/minecraftforge/registries/RegistryObject;
        73: putstatic     #566                // Field axe:Lnet/minecraftforge/registries/RegistryObject;
        76: ldc_w         #567                // String hoe
        79: invokedynamic #571,  0            // InvokeDynamic #34:accept:()Ljava/util/function/Consumer;
        84: invokestatic  #543                // Method register:(Ljava/lang/String;Ljava/util/function/Consumer;)Lnet/minecraftforge/registries/RegistryObject;
        87: putstatic     #573                // Field hoe:Lnet/minecraftforge/registries/RegistryObject;
        90: ldc_w         #574                // String sword
        93: invokedynamic #578,  0            // InvokeDynamic #35:accept:()Ljava/util/function/Consumer;
        98: invokestatic  #543                // Method register:(Ljava/lang/String;Ljava/util/function/Consumer;)Lnet/minecraftforge/registries/RegistryObject;
       101: putstatic     #580                // Field sword:Lnet/minecraftforge/registries/RegistryObject;
       104: ldc_w         #581                // String bow
       107: invokedynamic #585,  0            // InvokeDynamic #36:accept:()Ljava/util/function/Consumer;
       112: invokestatic  #543                // Method register:(Ljava/lang/String;Ljava/util/function/Consumer;)Lnet/minecraftforge/registries/RegistryObject;
       115: putstatic     #587                // Field bow:Lnet/minecraftforge/registries/RegistryObject;
       118: ldc_w         #589                // String rod
       121: invokedynamic #593,  0            // InvokeDynamic #37:accept:()Ljava/util/function/Consumer;
       126: invokestatic  #543                // Method register:(Ljava/lang/String;Ljava/util/function/Consumer;)Lnet/minecraftforge/registries/RegistryObject;
       129: putstatic     #595                // Field fishing_rod:Lnet/minecraftforge/registries/RegistryObject;
       132: ldc_w         #596                // String shears
       135: invokedynamic #600,  0            // InvokeDynamic #38:accept:()Ljava/util/function/Consumer;
       140: invokestatic  #543                // Method register:(Ljava/lang/String;Ljava/util/function/Consumer;)Lnet/minecraftforge/registries/RegistryObject;
       143: putstatic     #602                // Field shears:Lnet/minecraftforge/registries/RegistryObject;
       146: ldc_w         #603                // String shield
       149: invokedynamic #607,  0            // InvokeDynamic #39:accept:()Ljava/util/function/Consumer;
       154: invokestatic  #543                // Method register:(Ljava/lang/String;Ljava/util/function/Consumer;)Lnet/minecraftforge/registries/RegistryObject;
       157: putstatic     #609                // Field shield:Lnet/minecraftforge/registries/RegistryObject;
       160: ldc_w         #610                // String helmet
       163: invokedynamic #614,  0            // InvokeDynamic #40:accept:()Ljava/util/function/Consumer;
       168: invokestatic  #543                // Method register:(Ljava/lang/String;Ljava/util/function/Consumer;)Lnet/minecraftforge/registries/RegistryObject;
       171: putstatic     #616                // Field helmet:Lnet/minecraftforge/registries/RegistryObject;
       174: ldc_w         #617                // String leggings
       177: invokedynamic #621,  0            // InvokeDynamic #41:accept:()Ljava/util/function/Consumer;
       182: invokestatic  #543                // Method register:(Ljava/lang/String;Ljava/util/function/Consumer;)Lnet/minecraftforge/registries/RegistryObject;
       185: putstatic     #623                // Field leggings:Lnet/minecraftforge/registries/RegistryObject;
       188: ldc_w         #624                // String chestplate
       191: invokedynamic #628,  0            // InvokeDynamic #42:accept:()Ljava/util/function/Consumer;
       196: invokestatic  #543                // Method register:(Ljava/lang/String;Ljava/util/function/Consumer;)Lnet/minecraftforge/registries/RegistryObject;
       199: putstatic     #630                // Field chestplate:Lnet/minecraftforge/registries/RegistryObject;
       202: ldc_w         #631                // String boots
       205: invokedynamic #635,  0            // InvokeDynamic #43:accept:()Ljava/util/function/Consumer;
       210: invokestatic  #543                // Method register:(Ljava/lang/String;Ljava/util/function/Consumer;)Lnet/minecraftforge/registries/RegistryObject;
       213: putstatic     #637                // Field boots:Lnet/minecraftforge/registries/RegistryObject;
       216: ldc_w         #639                // String flintandsteel
       219: invokedynamic #643,  0            // InvokeDynamic #44:accept:()Ljava/util/function/Consumer;
       224: invokestatic  #543                // Method register:(Ljava/lang/String;Ljava/util/function/Consumer;)Lnet/minecraftforge/registries/RegistryObject;
       227: putstatic     #645                // Field flint_and_steel:Lnet/minecraftforge/registries/RegistryObject;
       230: ldc_w         #646                // String lead
       233: invokedynamic #650,  0            // InvokeDynamic #45:accept:()Ljava/util/function/Consumer;
       238: invokestatic  #543                // Method register:(Ljava/lang/String;Ljava/util/function/Consumer;)Lnet/minecraftforge/registries/RegistryObject;
       241: putstatic     #652                // Field lead:Lnet/minecraftforge/registries/RegistryObject;
       244: return
      LineNumberTable:
        line 27: 0
        line 28: 14
        line 49: 20
        line 55: 34
        line 63: 48
        line 71: 62
        line 78: 76
        line 85: 90
        line 102: 104
        line 108: 118
        line 114: 132
        line 120: 146
        line 126: 160
        line 132: 174
        line 138: 188
        line 144: 202
        line 150: 216
        line 156: 230
        line 162: 244
}
InnerClasses:
  public static #10= #7 of #9;            // Builder=class com/minecolonies/api/equipment/registry/EquipmentTypeEntry$Builder of class com/minecolonies/api/equipment/registry/EquipmentTypeEntry
  public static final #15= #12 of #14;    // Lookup=class java/lang/invoke/MethodHandles$Lookup of class java/lang/invoke/MethodHandles
SourceFile: "ModEquipmentTypes.java"
BootstrapMethods:
  0: #98 REF_invokeStatic java/lang/invoke/LambdaMetafactory.metafactory:(Ljava/lang/invoke/MethodHandles$Lookup;Ljava/lang/String;Ljava/lang/invoke/MethodType;Ljava/lang/invoke/MethodType;Ljava/lang/invoke/MethodHandle;Ljava/lang/invoke/MethodType;)Ljava/lang/invoke/CallSite;
    Method arguments:
      #85 ()Ljava/lang/Object;
      #90 REF_invokeVirtual com/minecolonies/api/equipment/registry/EquipmentTypeEntry$Builder.build:()Lcom/minecolonies/api/equipment/registry/EquipmentTypeEntry;
      #91 ()Lcom/minecolonies/api/equipment/registry/EquipmentTypeEntry;
  1: #98 REF_invokeStatic java/lang/invoke/LambdaMetafactory.metafactory:(Ljava/lang/invoke/MethodHandles$Lookup;Ljava/lang/String;Ljava/lang/invoke/MethodType;Ljava/lang/invoke/MethodType;Ljava/lang/invoke/MethodHandle;Ljava/lang/invoke/MethodType;)Ljava/lang/invoke/CallSite;
    Method arguments:
      #210 (Ljava/lang/Object;Ljava/lang/Object;)Z
      #214 REF_invokeStatic com/minecolonies/api/equipment/ModEquipmentTypes.lambda$static$41:(Lnet/minecraft/world/item/ItemStack;Lcom/minecolonies/api/equipment/registry/EquipmentTypeEntry;)Z
      #215 (Lnet/minecraft/world/item/ItemStack;Lcom/minecolonies/api/equipment/registry/EquipmentTypeEntry;)Z
  2: #98 REF_invokeStatic java/lang/invoke/LambdaMetafactory.metafactory:(Ljava/lang/invoke/MethodHandles$Lookup;Ljava/lang/String;Ljava/lang/invoke/MethodType;Ljava/lang/invoke/MethodType;Ljava/lang/invoke/MethodHandle;Ljava/lang/invoke/MethodType;)Ljava/lang/invoke/CallSite;
    Method arguments:
      #225 (Ljava/lang/Object;Ljava/lang/Object;)Ljava/lang/Object;
      #230 REF_invokeStatic com/minecolonies/api/equipment/ModEquipmentTypes.lambda$static$42:(Lnet/minecraft/world/item/ItemStack;Lcom/minecolonies/api/equipment/registry/EquipmentTypeEntry;)Ljava/lang/Integer;
      #231 (Lnet/minecraft/world/item/ItemStack;Lcom/minecolonies/api/equipment/registry/EquipmentTypeEntry;)Ljava/lang/Integer;
  3: #98 REF_invokeStatic java/lang/invoke/LambdaMetafactory.metafactory:(Ljava/lang/invoke/MethodHandles$Lookup;Ljava/lang/String;Ljava/lang/invoke/MethodType;Ljava/lang/invoke/MethodType;Ljava/lang/invoke/MethodHandle;Ljava/lang/invoke/MethodType;)Ljava/lang/invoke/CallSite;
    Method arguments:
      #210 (Ljava/lang/Object;Ljava/lang/Object;)Z
      #255 REF_invokeStatic com/minecolonies/api/equipment/ModEquipmentTypes.lambda$static$38:(Lnet/minecraft/world/item/ItemStack;Lcom/minecolonies/api/equipment/registry/EquipmentTypeEntry;)Z
      #215 (Lnet/minecraft/world/item/ItemStack;Lcom/minecolonies/api/equipment/registry/EquipmentTypeEntry;)Z
  4: #98 REF_invokeStatic java/lang/invoke/LambdaMetafactory.metafactory:(Ljava/lang/invoke/MethodHandles$Lookup;Ljava/lang/String;Ljava/lang/invoke/MethodType;Ljava/lang/invoke/MethodType;Ljava/lang/invoke/MethodHandle;Ljava/lang/invoke/MethodType;)Ljava/lang/invoke/CallSite;
    Method arguments:
      #225 (Ljava/lang/Object;Ljava/lang/Object;)Ljava/lang/Object;
      #260 REF_invokeStatic com/minecolonies/api/equipment/ModEquipmentTypes.lambda$static$39:(Lnet/minecraft/world/item/ItemStack;Lcom/minecolonies/api/equipment/registry/EquipmentTypeEntry;)Ljava/lang/Integer;
      #231 (Lnet/minecraft/world/item/ItemStack;Lcom/minecolonies/api/equipment/registry/EquipmentTypeEntry;)Ljava/lang/Integer;
  5: #98 REF_invokeStatic java/lang/invoke/LambdaMetafactory.metafactory:(Ljava/lang/invoke/MethodHandles$Lookup;Ljava/lang/String;Ljava/lang/invoke/MethodType;Ljava/lang/invoke/MethodType;Ljava/lang/invoke/MethodHandle;Ljava/lang/invoke/MethodType;)Ljava/lang/invoke/CallSite;
    Method arguments:
      #210 (Ljava/lang/Object;Ljava/lang/Object;)Z
      #283 REF_invokeStatic com/minecolonies/api/equipment/ModEquipmentTypes.lambda$static$35:(Lnet/minecraft/world/item/ItemStack;Lcom/minecolonies/api/equipment/registry/EquipmentTypeEntry;)Z
      #215 (Lnet/minecraft/world/item/ItemStack;Lcom/minecolonies/api/equipment/registry/EquipmentTypeEntry;)Z
  6: #98 REF_invokeStatic java/lang/invoke/LambdaMetafactory.metafactory:(Ljava/lang/invoke/MethodHandles$Lookup;Ljava/lang/String;Ljava/lang/invoke/MethodType;Ljava/lang/invoke/MethodType;Ljava/lang/invoke/MethodHandle;Ljava/lang/invoke/MethodType;)Ljava/lang/invoke/CallSite;
    Method arguments:
      #225 (Ljava/lang/Object;Ljava/lang/Object;)Ljava/lang/Object;
      #288 REF_invokeStatic com/minecolonies/api/equipment/ModEquipmentTypes.lambda$static$36:(Lnet/minecraft/world/item/ItemStack;Lcom/minecolonies/api/equipment/registry/EquipmentTypeEntry;)Ljava/lang/Integer;
      #231 (Lnet/minecraft/world/item/ItemStack;Lcom/minecolonies/api/equipment/registry/EquipmentTypeEntry;)Ljava/lang/Integer;
  7: #98 REF_invokeStatic java/lang/invoke/LambdaMetafactory.metafactory:(Ljava/lang/invoke/MethodHandles$Lookup;Ljava/lang/String;Ljava/lang/invoke/MethodType;Ljava/lang/invoke/MethodType;Ljava/lang/invoke/MethodHandle;Ljava/lang/invoke/MethodType;)Ljava/lang/invoke/CallSite;
    Method arguments:
      #210 (Ljava/lang/Object;Ljava/lang/Object;)Z
      #320 REF_invokeStatic com/minecolonies/api/equipment/ModEquipmentTypes.lambda$static$32:(Lnet/minecraft/world/item/ItemStack;Lcom/minecolonies/api/equipment/registry/EquipmentTypeEntry;)Z
      #215 (Lnet/minecraft/world/item/ItemStack;Lcom/minecolonies/api/equipment/registry/EquipmentTypeEntry;)Z
  8: #98 REF_invokeStatic java/lang/invoke/LambdaMetafactory.metafactory:(Ljava/lang/invoke/MethodHandles$Lookup;Ljava/lang/String;Ljava/lang/invoke/MethodType;Ljava/lang/invoke/MethodType;Ljava/lang/invoke/MethodHandle;Ljava/lang/invoke/MethodType;)Ljava/lang/invoke/CallSite;
    Method arguments:
      #225 (Ljava/lang/Object;Ljava/lang/Object;)Ljava/lang/Object;
      #325 REF_invokeStatic com/minecolonies/api/equipment/ModEquipmentTypes.lambda$static$33:(Lnet/minecraft/world/item/ItemStack;Lcom/minecolonies/api/equipment/registry/EquipmentTypeEntry;)Ljava/lang/Integer;
      #231 (Lnet/minecraft/world/item/ItemStack;Lcom/minecolonies/api/equipment/registry/EquipmentTypeEntry;)Ljava/lang/Integer;
  9: #98 REF_invokeStatic java/lang/invoke/LambdaMetafactory.metafactory:(Ljava/lang/invoke/MethodHandles$Lookup;Ljava/lang/String;Ljava/lang/invoke/MethodType;Ljava/lang/invoke/MethodType;Ljava/lang/invoke/MethodHandle;Ljava/lang/invoke/MethodType;)Ljava/lang/invoke/CallSite;
    Method arguments:
      #210 (Ljava/lang/Object;Ljava/lang/Object;)Z
      #337 REF_invokeStatic com/minecolonies/api/equipment/ModEquipmentTypes.lambda$static$29:(Lnet/minecraft/world/item/ItemStack;Lcom/minecolonies/api/equipment/registry/EquipmentTypeEntry;)Z
      #215 (Lnet/minecraft/world/item/ItemStack;Lcom/minecolonies/api/equipment/registry/EquipmentTypeEntry;)Z
  10: #98 REF_invokeStatic java/lang/invoke/LambdaMetafactory.metafactory:(Ljava/lang/invoke/MethodHandles$Lookup;Ljava/lang/String;Ljava/lang/invoke/MethodType;Ljava/lang/invoke/MethodType;Ljava/lang/invoke/MethodHandle;Ljava/lang/invoke/MethodType;)Ljava/lang/invoke/CallSite;
    Method arguments:
      #225 (Ljava/lang/Object;Ljava/lang/Object;)Ljava/lang/Object;
      #342 REF_invokeStatic com/minecolonies/api/equipment/ModEquipmentTypes.lambda$static$30:(Lnet/minecraft/world/item/ItemStack;Lcom/minecolonies/api/equipment/registry/EquipmentTypeEntry;)Ljava/lang/Integer;
      #231 (Lnet/minecraft/world/item/ItemStack;Lcom/minecolonies/api/equipment/registry/EquipmentTypeEntry;)Ljava/lang/Integer;
  11: #98 REF_invokeStatic java/lang/invoke/LambdaMetafactory.metafactory:(Ljava/lang/invoke/MethodHandles$Lookup;Ljava/lang/String;Ljava/lang/invoke/MethodType;Ljava/lang/invoke/MethodType;Ljava/lang/invoke/MethodHandle;Ljava/lang/invoke/MethodType;)Ljava/lang/invoke/CallSite;
    Method arguments:
      #210 (Ljava/lang/Object;Ljava/lang/Object;)Z
      #354 REF_invokeStatic com/minecolonies/api/equipment/ModEquipmentTypes.lambda$static$26:(Lnet/minecraft/world/item/ItemStack;Lcom/minecolonies/api/equipment/registry/EquipmentTypeEntry;)Z
      #215 (Lnet/minecraft/world/item/ItemStack;Lcom/minecolonies/api/equipment/registry/EquipmentTypeEntry;)Z
  12: #98 REF_invokeStatic java/lang/invoke/LambdaMetafactory.metafactory:(Ljava/lang/invoke/MethodHandles$Lookup;Ljava/lang/String;Ljava/lang/invoke/MethodType;Ljava/lang/invoke/MethodType;Ljava/lang/invoke/MethodHandle;Ljava/lang/invoke/MethodType;)Ljava/lang/invoke/CallSite;
    Method arguments:
      #225 (Ljava/lang/Object;Ljava/lang/Object;)Ljava/lang/Object;
      #359 REF_invokeStatic com/minecolonies/api/equipment/ModEquipmentTypes.lambda$static$27:(Lnet/minecraft/world/item/ItemStack;Lcom/minecolonies/api/equipment/registry/EquipmentTypeEntry;)Ljava/lang/Integer;
      #231 (Lnet/minecraft/world/item/ItemStack;Lcom/minecolonies/api/equipment/registry/EquipmentTypeEntry;)Ljava/lang/Integer;
  13: #98 REF_invokeStatic java/lang/invoke/LambdaMetafactory.metafactory:(Ljava/lang/invoke/MethodHandles$Lookup;Ljava/lang/String;Ljava/lang/invoke/MethodType;Ljava/lang/invoke/MethodType;Ljava/lang/invoke/MethodHandle;Ljava/lang/invoke/MethodType;)Ljava/lang/invoke/CallSite;
    Method arguments:
      #210 (Ljava/lang/Object;Ljava/lang/Object;)Z
      #371 REF_invokeStatic com/minecolonies/api/equipment/ModEquipmentTypes.lambda$static$23:(Lnet/minecraft/world/item/ItemStack;Lcom/minecolonies/api/equipment/registry/EquipmentTypeEntry;)Z
      #215 (Lnet/minecraft/world/item/ItemStack;Lcom/minecolonies/api/equipment/registry/EquipmentTypeEntry;)Z
  14: #98 REF_invokeStatic java/lang/invoke/LambdaMetafactory.metafactory:(Ljava/lang/invoke/MethodHandles$Lookup;Ljava/lang/String;Ljava/lang/invoke/MethodType;Ljava/lang/invoke/MethodType;Ljava/lang/invoke/MethodHandle;Ljava/lang/invoke/MethodType;)Ljava/lang/invoke/CallSite;
    Method arguments:
      #225 (Ljava/lang/Object;Ljava/lang/Object;)Ljava/lang/Object;
      #376 REF_invokeStatic com/minecolonies/api/equipment/ModEquipmentTypes.lambda$static$24:(Lnet/minecraft/world/item/ItemStack;Lcom/minecolonies/api/equipment/registry/EquipmentTypeEntry;)Ljava/lang/Integer;
      #231 (Lnet/minecraft/world/item/ItemStack;Lcom/minecolonies/api/equipment/registry/EquipmentTypeEntry;)Ljava/lang/Integer;
  15: #98 REF_invokeStatic java/lang/invoke/LambdaMetafactory.metafactory:(Ljava/lang/invoke/MethodHandles$Lookup;Ljava/lang/String;Ljava/lang/invoke/MethodType;Ljava/lang/invoke/MethodType;Ljava/lang/invoke/MethodHandle;Ljava/lang/invoke/MethodType;)Ljava/lang/invoke/CallSite;
    Method arguments:
      #210 (Ljava/lang/Object;Ljava/lang/Object;)Z
      #394 REF_invokeStatic com/minecolonies/api/equipment/ModEquipmentTypes.lambda$static$20:(Lnet/minecraft/world/item/ItemStack;Lcom/minecolonies/api/equipment/registry/EquipmentTypeEntry;)Z
      #215 (Lnet/minecraft/world/item/ItemStack;Lcom/minecolonies/api/equipment/registry/EquipmentTypeEntry;)Z
  16: #98 REF_invokeStatic java/lang/invoke/LambdaMetafactory.metafactory:(Ljava/lang/invoke/MethodHandles$Lookup;Ljava/lang/String;Ljava/lang/invoke/MethodType;Ljava/lang/invoke/MethodType;Ljava/lang/invoke/MethodHandle;Ljava/lang/invoke/MethodType;)Ljava/lang/invoke/CallSite;
    Method arguments:
      #225 (Ljava/lang/Object;Ljava/lang/Object;)Ljava/lang/Object;
      #399 REF_invokeStatic com/minecolonies/api/equipment/ModEquipmentTypes.lambda$static$21:(Lnet/minecraft/world/item/ItemStack;Lcom/minecolonies/api/equipment/registry/EquipmentTypeEntry;)Ljava/lang/Integer;
      #231 (Lnet/minecraft/world/item/ItemStack;Lcom/minecolonies/api/equipment/registry/EquipmentTypeEntry;)Ljava/lang/Integer;
  17: #98 REF_invokeStatic java/lang/invoke/LambdaMetafactory.metafactory:(Ljava/lang/invoke/MethodHandles$Lookup;Ljava/lang/String;Ljava/lang/invoke/MethodType;Ljava/lang/invoke/MethodType;Ljava/lang/invoke/MethodHandle;Ljava/lang/invoke/MethodType;)Ljava/lang/invoke/CallSite;
    Method arguments:
      #210 (Ljava/lang/Object;Ljava/lang/Object;)Z
      #413 REF_invokeStatic com/minecolonies/api/equipment/ModEquipmentTypes.lambda$static$17:(Lnet/minecraft/world/item/ItemStack;Lcom/minecolonies/api/equipment/registry/EquipmentTypeEntry;)Z
      #215 (Lnet/minecraft/world/item/ItemStack;Lcom/minecolonies/api/equipment/registry/EquipmentTypeEntry;)Z
  18: #98 REF_invokeStatic java/lang/invoke/LambdaMetafactory.metafactory:(Ljava/lang/invoke/MethodHandles$Lookup;Ljava/lang/String;Ljava/lang/invoke/MethodType;Ljava/lang/invoke/MethodType;Ljava/lang/invoke/MethodHandle;Ljava/lang/invoke/MethodType;)Ljava/lang/invoke/CallSite;
    Method arguments:
      #225 (Ljava/lang/Object;Ljava/lang/Object;)Ljava/lang/Object;
      #418 REF_invokeStatic com/minecolonies/api/equipment/ModEquipmentTypes.lambda$static$18:(Lnet/minecraft/world/item/ItemStack;Lcom/minecolonies/api/equipment/registry/EquipmentTypeEntry;)Ljava/lang/Integer;
      #231 (Lnet/minecraft/world/item/ItemStack;Lcom/minecolonies/api/equipment/registry/EquipmentTypeEntry;)Ljava/lang/Integer;
  19: #98 REF_invokeStatic java/lang/invoke/LambdaMetafactory.metafactory:(Ljava/lang/invoke/MethodHandles$Lookup;Ljava/lang/String;Ljava/lang/invoke/MethodType;Ljava/lang/invoke/MethodType;Ljava/lang/invoke/MethodHandle;Ljava/lang/invoke/MethodType;)Ljava/lang/invoke/CallSite;
    Method arguments:
      #210 (Ljava/lang/Object;Ljava/lang/Object;)Z
      #432 REF_invokeStatic com/minecolonies/api/equipment/ModEquipmentTypes.lambda$static$14:(Lnet/minecraft/world/item/ItemStack;Lcom/minecolonies/api/equipment/registry/EquipmentTypeEntry;)Z
      #215 (Lnet/minecraft/world/item/ItemStack;Lcom/minecolonies/api/equipment/registry/EquipmentTypeEntry;)Z
  20: #98 REF_invokeStatic java/lang/invoke/LambdaMetafactory.metafactory:(Ljava/lang/invoke/MethodHandles$Lookup;Ljava/lang/String;Ljava/lang/invoke/MethodType;Ljava/lang/invoke/MethodType;Ljava/lang/invoke/MethodHandle;Ljava/lang/invoke/MethodType;)Ljava/lang/invoke/CallSite;
    Method arguments:
      #225 (Ljava/lang/Object;Ljava/lang/Object;)Ljava/lang/Object;
      #437 REF_invokeStatic com/minecolonies/api/equipment/ModEquipmentTypes.lambda$static$15:(Lnet/minecraft/world/item/ItemStack;Lcom/minecolonies/api/equipment/registry/EquipmentTypeEntry;)Ljava/lang/Integer;
      #231 (Lnet/minecraft/world/item/ItemStack;Lcom/minecolonies/api/equipment/registry/EquipmentTypeEntry;)Ljava/lang/Integer;
  21: #98 REF_invokeStatic java/lang/invoke/LambdaMetafactory.metafactory:(Ljava/lang/invoke/MethodHandles$Lookup;Ljava/lang/String;Ljava/lang/invoke/MethodType;Ljava/lang/invoke/MethodType;Ljava/lang/invoke/MethodHandle;Ljava/lang/invoke/MethodType;)Ljava/lang/invoke/CallSite;
    Method arguments:
      #210 (Ljava/lang/Object;Ljava/lang/Object;)Z
      #450 REF_invokeStatic com/minecolonies/api/equipment/ModEquipmentTypes.lambda$static$11:(Lnet/minecraft/world/item/ItemStack;Lcom/minecolonies/api/equipment/registry/EquipmentTypeEntry;)Z
      #215 (Lnet/minecraft/world/item/ItemStack;Lcom/minecolonies/api/equipment/registry/EquipmentTypeEntry;)Z
  22: #98 REF_invokeStatic java/lang/invoke/LambdaMetafactory.metafactory:(Ljava/lang/invoke/MethodHandles$Lookup;Ljava/lang/String;Ljava/lang/invoke/MethodType;Ljava/lang/invoke/MethodType;Ljava/lang/invoke/MethodHandle;Ljava/lang/invoke/MethodType;)Ljava/lang/invoke/CallSite;
    Method arguments:
      #225 (Ljava/lang/Object;Ljava/lang/Object;)Ljava/lang/Object;
      #455 REF_invokeStatic com/minecolonies/api/equipment/ModEquipmentTypes.lambda$static$12:(Lnet/minecraft/world/item/ItemStack;Lcom/minecolonies/api/equipment/registry/EquipmentTypeEntry;)Ljava/lang/Integer;
      #231 (Lnet/minecraft/world/item/ItemStack;Lcom/minecolonies/api/equipment/registry/EquipmentTypeEntry;)Ljava/lang/Integer;
  23: #98 REF_invokeStatic java/lang/invoke/LambdaMetafactory.metafactory:(Ljava/lang/invoke/MethodHandles$Lookup;Ljava/lang/String;Ljava/lang/invoke/MethodType;Ljava/lang/invoke/MethodType;Ljava/lang/invoke/MethodHandle;Ljava/lang/invoke/MethodType;)Ljava/lang/invoke/CallSite;
    Method arguments:
      #210 (Ljava/lang/Object;Ljava/lang/Object;)Z
      #471 REF_invokeStatic com/minecolonies/api/equipment/ModEquipmentTypes.lambda$static$9:(Lnet/minecraft/world/item/ItemStack;Lcom/minecolonies/api/equipment/registry/EquipmentTypeEntry;)Z
      #215 (Lnet/minecraft/world/item/ItemStack;Lcom/minecolonies/api/equipment/registry/EquipmentTypeEntry;)Z
  24: #98 REF_invokeStatic java/lang/invoke/LambdaMetafactory.metafactory:(Ljava/lang/invoke/MethodHandles$Lookup;Ljava/lang/String;Ljava/lang/invoke/MethodType;Ljava/lang/invoke/MethodType;Ljava/lang/invoke/MethodHandle;Ljava/lang/invoke/MethodType;)Ljava/lang/invoke/CallSite;
    Method arguments:
      #225 (Ljava/lang/Object;Ljava/lang/Object;)Ljava/lang/Object;
      #475 REF_invokeStatic com/minecolonies/api/equipment/ModEquipmentTypes.vanillaToolLevel:(Lnet/minecraft/world/item/ItemStack;Lcom/minecolonies/api/equipment/registry/EquipmentTypeEntry;)I
      #231 (Lnet/minecraft/world/item/ItemStack;Lcom/minecolonies/api/equipment/registry/EquipmentTypeEntry;)Ljava/lang/Integer;
  25: #98 REF_invokeStatic java/lang/invoke/LambdaMetafactory.metafactory:(Ljava/lang/invoke/MethodHandles$Lookup;Ljava/lang/String;Ljava/lang/invoke/MethodType;Ljava/lang/invoke/MethodType;Ljava/lang/invoke/MethodHandle;Ljava/lang/invoke/MethodType;)Ljava/lang/invoke/CallSite;
    Method arguments:
      #210 (Ljava/lang/Object;Ljava/lang/Object;)Z
      #486 REF_invokeStatic com/minecolonies/api/equipment/ModEquipmentTypes.lambda$static$7:(Lnet/minecraft/world/item/ItemStack;Lcom/minecolonies/api/equipment/registry/EquipmentTypeEntry;)Z
      #215 (Lnet/minecraft/world/item/ItemStack;Lcom/minecolonies/api/equipment/registry/EquipmentTypeEntry;)Z
  26: #98 REF_invokeStatic java/lang/invoke/LambdaMetafactory.metafactory:(Ljava/lang/invoke/MethodHandles$Lookup;Ljava/lang/String;Ljava/lang/invoke/MethodType;Ljava/lang/invoke/MethodType;Ljava/lang/invoke/MethodHandle;Ljava/lang/invoke/MethodType;)Ljava/lang/invoke/CallSite;
    Method arguments:
      #210 (Ljava/lang/Object;Ljava/lang/Object;)Z
      #497 REF_invokeStatic com/minecolonies/api/equipment/ModEquipmentTypes.lambda$static$5:(Lnet/minecraft/world/item/ItemStack;Lcom/minecolonies/api/equipment/registry/EquipmentTypeEntry;)Z
      #215 (Lnet/minecraft/world/item/ItemStack;Lcom/minecolonies/api/equipment/registry/EquipmentTypeEntry;)Z
  27: #98 REF_invokeStatic java/lang/invoke/LambdaMetafactory.metafactory:(Ljava/lang/invoke/MethodHandles$Lookup;Ljava/lang/String;Ljava/lang/invoke/MethodType;Ljava/lang/invoke/MethodType;Ljava/lang/invoke/MethodHandle;Ljava/lang/invoke/MethodType;)Ljava/lang/invoke/CallSite;
    Method arguments:
      #210 (Ljava/lang/Object;Ljava/lang/Object;)Z
      #508 REF_invokeStatic com/minecolonies/api/equipment/ModEquipmentTypes.lambda$static$3:(Lnet/minecraft/world/item/ItemStack;Lcom/minecolonies/api/equipment/registry/EquipmentTypeEntry;)Z
      #215 (Lnet/minecraft/world/item/ItemStack;Lcom/minecolonies/api/equipment/registry/EquipmentTypeEntry;)Z
  28: #98 REF_invokeStatic java/lang/invoke/LambdaMetafactory.metafactory:(Ljava/lang/invoke/MethodHandles$Lookup;Ljava/lang/String;Ljava/lang/invoke/MethodType;Ljava/lang/invoke/MethodType;Ljava/lang/invoke/MethodHandle;Ljava/lang/invoke/MethodType;)Ljava/lang/invoke/CallSite;
    Method arguments:
      #210 (Ljava/lang/Object;Ljava/lang/Object;)Z
      #519 REF_invokeStatic com/minecolonies/api/equipment/ModEquipmentTypes.lambda$static$0:(Lnet/minecraft/world/item/ItemStack;Lcom/minecolonies/api/equipment/registry/EquipmentTypeEntry;)Z
      #215 (Lnet/minecraft/world/item/ItemStack;Lcom/minecolonies/api/equipment/registry/EquipmentTypeEntry;)Z
  29: #98 REF_invokeStatic java/lang/invoke/LambdaMetafactory.metafactory:(Ljava/lang/invoke/MethodHandles$Lookup;Ljava/lang/String;Ljava/lang/invoke/MethodType;Ljava/lang/invoke/MethodType;Ljava/lang/invoke/MethodHandle;Ljava/lang/invoke/MethodType;)Ljava/lang/invoke/CallSite;
    Method arguments:
      #225 (Ljava/lang/Object;Ljava/lang/Object;)Ljava/lang/Object;
      #524 REF_invokeStatic com/minecolonies/api/equipment/ModEquipmentTypes.lambda$static$1:(Lnet/minecraft/world/item/ItemStack;Lcom/minecolonies/api/equipment/registry/EquipmentTypeEntry;)Ljava/lang/Integer;
      #231 (Lnet/minecraft/world/item/ItemStack;Lcom/minecolonies/api/equipment/registry/EquipmentTypeEntry;)Ljava/lang/Integer;
  30: #98 REF_invokeStatic java/lang/invoke/LambdaMetafactory.metafactory:(Ljava/lang/invoke/MethodHandles$Lookup;Ljava/lang/String;Ljava/lang/invoke/MethodType;Ljava/lang/invoke/MethodType;Ljava/lang/invoke/MethodHandle;Ljava/lang/invoke/MethodType;)Ljava/lang/invoke/CallSite;
    Method arguments:
      #534 (Ljava/lang/Object;)V
      #537 REF_invokeStatic com/minecolonies/api/equipment/ModEquipmentTypes.lambda$static$2:(Lcom/minecolonies/api/equipment/registry/EquipmentTypeEntry$Builder;)V
      #538 (Lcom/minecolonies/api/equipment/registry/EquipmentTypeEntry$Builder;)V
  31: #98 REF_invokeStatic java/lang/invoke/LambdaMetafactory.metafactory:(Ljava/lang/invoke/MethodHandles$Lookup;Ljava/lang/String;Ljava/lang/invoke/MethodType;Ljava/lang/invoke/MethodType;Ljava/lang/invoke/MethodHandle;Ljava/lang/invoke/MethodType;)Ljava/lang/invoke/CallSite;
    Method arguments:
      #534 (Ljava/lang/Object;)V
      #549 REF_invokeStatic com/minecolonies/api/equipment/ModEquipmentTypes.lambda$static$4:(Lcom/minecolonies/api/equipment/registry/EquipmentTypeEntry$Builder;)V
      #538 (Lcom/minecolonies/api/equipment/registry/EquipmentTypeEntry$Builder;)V
  32: #98 REF_invokeStatic java/lang/invoke/LambdaMetafactory.metafactory:(Ljava/lang/invoke/MethodHandles$Lookup;Ljava/lang/String;Ljava/lang/invoke/MethodType;Ljava/lang/invoke/MethodType;Ljava/lang/invoke/MethodHandle;Ljava/lang/invoke/MethodType;)Ljava/lang/invoke/CallSite;
    Method arguments:
      #534 (Ljava/lang/Object;)V
      #556 REF_invokeStatic com/minecolonies/api/equipment/ModEquipmentTypes.lambda$static$6:(Lcom/minecolonies/api/equipment/registry/EquipmentTypeEntry$Builder;)V
      #538 (Lcom/minecolonies/api/equipment/registry/EquipmentTypeEntry$Builder;)V
  33: #98 REF_invokeStatic java/lang/invoke/LambdaMetafactory.metafactory:(Ljava/lang/invoke/MethodHandles$Lookup;Ljava/lang/String;Ljava/lang/invoke/MethodType;Ljava/lang/invoke/MethodType;Ljava/lang/invoke/MethodHandle;Ljava/lang/invoke/MethodType;)Ljava/lang/invoke/CallSite;
    Method arguments:
      #534 (Ljava/lang/Object;)V
      #563 REF_invokeStatic com/minecolonies/api/equipment/ModEquipmentTypes.lambda$static$8:(Lcom/minecolonies/api/equipment/registry/EquipmentTypeEntry$Builder;)V
      #538 (Lcom/minecolonies/api/equipment/registry/EquipmentTypeEntry$Builder;)V
  34: #98 REF_invokeStatic java/lang/invoke/LambdaMetafactory.metafactory:(Ljava/lang/invoke/MethodHandles$Lookup;Ljava/lang/String;Ljava/lang/invoke/MethodType;Ljava/lang/invoke/MethodType;Ljava/lang/invoke/MethodHandle;Ljava/lang/invoke/MethodType;)Ljava/lang/invoke/CallSite;
    Method arguments:
      #534 (Ljava/lang/Object;)V
      #570 REF_invokeStatic com/minecolonies/api/equipment/ModEquipmentTypes.lambda$static$10:(Lcom/minecolonies/api/equipment/registry/EquipmentTypeEntry$Builder;)V
      #538 (Lcom/minecolonies/api/equipment/registry/EquipmentTypeEntry$Builder;)V
  35: #98 REF_invokeStatic java/lang/invoke/LambdaMetafactory.metafactory:(Ljava/lang/invoke/MethodHandles$Lookup;Ljava/lang/String;Ljava/lang/invoke/MethodType;Ljava/lang/invoke/MethodType;Ljava/lang/invoke/MethodHandle;Ljava/lang/invoke/MethodType;)Ljava/lang/invoke/CallSite;
    Method arguments:
      #534 (Ljava/lang/Object;)V
      #577 REF_invokeStatic com/minecolonies/api/equipment/ModEquipmentTypes.lambda$static$13:(Lcom/minecolonies/api/equipment/registry/EquipmentTypeEntry$Builder;)V
      #538 (Lcom/minecolonies/api/equipment/registry/EquipmentTypeEntry$Builder;)V
  36: #98 REF_invokeStatic java/lang/invoke/LambdaMetafactory.metafactory:(Ljava/lang/invoke/MethodHandles$Lookup;Ljava/lang/String;Ljava/lang/invoke/MethodType;Ljava/lang/invoke/MethodType;Ljava/lang/invoke/MethodHandle;Ljava/lang/invoke/MethodType;)Ljava/lang/invoke/CallSite;
    Method arguments:
      #534 (Ljava/lang/Object;)V
      #584 REF_invokeStatic com/minecolonies/api/equipment/ModEquipmentTypes.lambda$static$16:(Lcom/minecolonies/api/equipment/registry/EquipmentTypeEntry$Builder;)V
      #538 (Lcom/minecolonies/api/equipment/registry/EquipmentTypeEntry$Builder;)V
  37: #98 REF_invokeStatic java/lang/invoke/LambdaMetafactory.metafactory:(Ljava/lang/invoke/MethodHandles$Lookup;Ljava/lang/String;Ljava/lang/invoke/MethodType;Ljava/lang/invoke/MethodType;Ljava/lang/invoke/MethodHandle;Ljava/lang/invoke/MethodType;)Ljava/lang/invoke/CallSite;
    Method arguments:
      #534 (Ljava/lang/Object;)V
      #592 REF_invokeStatic com/minecolonies/api/equipment/ModEquipmentTypes.lambda$static$19:(Lcom/minecolonies/api/equipment/registry/EquipmentTypeEntry$Builder;)V
      #538 (Lcom/minecolonies/api/equipment/registry/EquipmentTypeEntry$Builder;)V
  38: #98 REF_invokeStatic java/lang/invoke/LambdaMetafactory.metafactory:(Ljava/lang/invoke/MethodHandles$Lookup;Ljava/lang/String;Ljava/lang/invoke/MethodType;Ljava/lang/invoke/MethodType;Ljava/lang/invoke/MethodHandle;Ljava/lang/invoke/MethodType;)Ljava/lang/invoke/CallSite;
    Method arguments:
      #534 (Ljava/lang/Object;)V
      #599 REF_invokeStatic com/minecolonies/api/equipment/ModEquipmentTypes.lambda$static$22:(Lcom/minecolonies/api/equipment/registry/EquipmentTypeEntry$Builder;)V
      #538 (Lcom/minecolonies/api/equipment/registry/EquipmentTypeEntry$Builder;)V
  39: #98 REF_invokeStatic java/lang/invoke/LambdaMetafactory.metafactory:(Ljava/lang/invoke/MethodHandles$Lookup;Ljava/lang/String;Ljava/lang/invoke/MethodType;Ljava/lang/invoke/MethodType;Ljava/lang/invoke/MethodHandle;Ljava/lang/invoke/MethodType;)Ljava/lang/invoke/CallSite;
    Method arguments:
      #534 (Ljava/lang/Object;)V
      #606 REF_invokeStatic com/minecolonies/api/equipment/ModEquipmentTypes.lambda$static$25:(Lcom/minecolonies/api/equipment/registry/EquipmentTypeEntry$Builder;)V
      #538 (Lcom/minecolonies/api/equipment/registry/EquipmentTypeEntry$Builder;)V
  40: #98 REF_invokeStatic java/lang/invoke/LambdaMetafactory.metafactory:(Ljava/lang/invoke/MethodHandles$Lookup;Ljava/lang/String;Ljava/lang/invoke/MethodType;Ljava/lang/invoke/MethodType;Ljava/lang/invoke/MethodHandle;Ljava/lang/invoke/MethodType;)Ljava/lang/invoke/CallSite;
    Method arguments:
      #534 (Ljava/lang/Object;)V
      #613 REF_invokeStatic com/minecolonies/api/equipment/ModEquipmentTypes.lambda$static$28:(Lcom/minecolonies/api/equipment/registry/EquipmentTypeEntry$Builder;)V
      #538 (Lcom/minecolonies/api/equipment/registry/EquipmentTypeEntry$Builder;)V
  41: #98 REF_invokeStatic java/lang/invoke/LambdaMetafactory.metafactory:(Ljava/lang/invoke/MethodHandles$Lookup;Ljava/lang/String;Ljava/lang/invoke/MethodType;Ljava/lang/invoke/MethodType;Ljava/lang/invoke/MethodHandle;Ljava/lang/invoke/MethodType;)Ljava/lang/invoke/CallSite;
    Method arguments:
      #534 (Ljava/lang/Object;)V
      #620 REF_invokeStatic com/minecolonies/api/equipment/ModEquipmentTypes.lambda$static$31:(Lcom/minecolonies/api/equipment/registry/EquipmentTypeEntry$Builder;)V
      #538 (Lcom/minecolonies/api/equipment/registry/EquipmentTypeEntry$Builder;)V
  42: #98 REF_invokeStatic java/lang/invoke/LambdaMetafactory.metafactory:(Ljava/lang/invoke/MethodHandles$Lookup;Ljava/lang/String;Ljava/lang/invoke/MethodType;Ljava/lang/invoke/MethodType;Ljava/lang/invoke/MethodHandle;Ljava/lang/invoke/MethodType;)Ljava/lang/invoke/CallSite;
    Method arguments:
      #534 (Ljava/lang/Object;)V
      #627 REF_invokeStatic com/minecolonies/api/equipment/ModEquipmentTypes.lambda$static$34:(Lcom/minecolonies/api/equipment/registry/EquipmentTypeEntry$Builder;)V
      #538 (Lcom/minecolonies/api/equipment/registry/EquipmentTypeEntry$Builder;)V
  43: #98 REF_invokeStatic java/lang/invoke/LambdaMetafactory.metafactory:(Ljava/lang/invoke/MethodHandles$Lookup;Ljava/lang/String;Ljava/lang/invoke/MethodType;Ljava/lang/invoke/MethodType;Ljava/lang/invoke/MethodHandle;Ljava/lang/invoke/MethodType;)Ljava/lang/invoke/CallSite;
    Method arguments:
      #534 (Ljava/lang/Object;)V
      #634 REF_invokeStatic com/minecolonies/api/equipment/ModEquipmentTypes.lambda$static$37:(Lcom/minecolonies/api/equipment/registry/EquipmentTypeEntry$Builder;)V
      #538 (Lcom/minecolonies/api/equipment/registry/EquipmentTypeEntry$Builder;)V
  44: #98 REF_invokeStatic java/lang/invoke/LambdaMetafactory.metafactory:(Ljava/lang/invoke/MethodHandles$Lookup;Ljava/lang/String;Ljava/lang/invoke/MethodType;Ljava/lang/invoke/MethodType;Ljava/lang/invoke/MethodHandle;Ljava/lang/invoke/MethodType;)Ljava/lang/invoke/CallSite;
    Method arguments:
      #534 (Ljava/lang/Object;)V
      #642 REF_invokeStatic com/minecolonies/api/equipment/ModEquipmentTypes.lambda$static$40:(Lcom/minecolonies/api/equipment/registry/EquipmentTypeEntry$Builder;)V
      #538 (Lcom/minecolonies/api/equipment/registry/EquipmentTypeEntry$Builder;)V
  45: #98 REF_invokeStatic java/lang/invoke/LambdaMetafactory.metafactory:(Ljava/lang/invoke/MethodHandles$Lookup;Ljava/lang/String;Ljava/lang/invoke/MethodType;Ljava/lang/invoke/MethodType;Ljava/lang/invoke/MethodHandle;Ljava/lang/invoke/MethodType;)Ljava/lang/invoke/CallSite;
    Method arguments:
      #534 (Ljava/lang/Object;)V
      #649 REF_invokeStatic com/minecolonies/api/equipment/ModEquipmentTypes.lambda$static$43:(Lcom/minecolonies/api/equipment/registry/EquipmentTypeEntry$Builder;)V
      #538 (Lcom/minecolonies/api/equipment/registry/EquipmentTypeEntry$Builder;)V
